Workbook
Name Arrendamento_total: #REF!
Name Porcentagem_Gestão: #REF!
Name TUSDg_total: #REF!

Sheet Infos Clientes
Q1: =MAX('Detalhe Por UC'!R:R) -> 45962 | T1: =SUBTOTAL(9,T3:T873) -> 36941.467 | U1: =SUBTOTAL(9,U3:U873) -> 37613.277
B2: INSTALACAO | C2: Linha | D2: Nome/Razão Social | E2: Região | F2: CPF/CNPJ | G2: E-mail | H2: INSTALACAO | I2: TENSAO | J2: MEDIDOR | K2: USINA | L2: CAPTADOR COMERCIAL | M2: Desconto sobre Tarifa Compensada ATUAL (Se teve alteração vai estar no próprio relatório ref. meses anteriores) | N2: Meses com desconto em dobro | O2: Tempo de Fidelidade (meses) | P2: Status | Q2: 1º mês compensação | R2: Meses remanescente de fidelidade | T2: Participação no consorcio kWh inicial (90% do consumo) | U2: Média Consumo | W2: 45261 | X2: 45292 | Y2: 45323 | Z2: 45352 | AA2: 45383 | AB2: 45413 | AC2: 45444 | AD2: 45474 | AE2: 45505 | AF2: 45536 | AG2: 45566 | AH2: 45597 | AI2: 45627 | AJ2: 45658 | AK2: 45689 | AL2: 45717 | AM2: 45748 | AN2: 45778 | AO2: 45809 | AP2: 45839 | AQ2: 45870 | AR2: 45901 | AS2: 45931 | AT2: 45962 | AU2: 45992 | AV2: 46023 | AW2: 46054 | AX2: 46082 | AY2: 46113 | AZ2: 46143 | BA2: 46174 | BB2: 46204 | BC2: 46235 | BD2: 46266 | BE2: 46296 | BF2: 46327 | BG2: 46357 | BH2: 46388 | BI2: 46419 | BJ2: 46447 | BK2: 46478 | BL2: 46508 | BM2: 46539 | BN2: 46569 | BO2: 46600 | BP2: 46631 | BQ2: 46661 | BR2: 46692 | BS2: 46722
B3: 10/10232-7 | C3: =ROW(F3) -> 3 | D3: IGREJA DO EVANGELHO QUADRANGULAR | E3: 302 | F3: 62.955.505/3932-07 | G3: katiaconceicaogomes2020@gmail.com; israelregiao302@gmail.com | H3: 10/10232-7 | I3: BT | J3: bifasico | K3: GIROSSOL II | M3: 0.25 | Q3: =IF(_xlfn.MINIFS('Detalhe Por UC'!R:R,'Detalhe Por UC'!C:C,B3,'Detalhe Por UC'!AD:AD,">"&0)=0,"",_xlfn.MINIFS('Detalhe Por UC'!R:R,'Detalhe Por UC'!C:C,B3,'Detalhe Por UC'!AD:AD,">"&0)) -> 45627 | R3: =IF(P3<>"ATIVO",0, IF(OR(Q3="",Q3=0,O3=0),O3, O3-ROUND((MAX('Detalhe Por UC'!R:R) -Q3)/(365/12),0))) -> 0 | T3: 99.833333 | U3: =IFERROR((SUMIFS(W3:CN3,$W$2:$CN$2,">"&$Q$1-365,$W$2:$CN$2,"<="&$Q$1)/COUNTIFS(W3:CN3,">="&0,$W$2:$CN$2,">"&$Q$1-365,$W$2:$CN$2,"<="&$Q$1)),"") -> 153.83333 | W3: 114 | X3: 108 | Y3: 78 | Z3: 109 | AA3: 96 | AB3: 155 | AC3: 119 | AD3: 72 | AE3: 77 | AF3: 88 | AG3: 116 | AH3: 113 | AI3: 82 | AJ3: =IF(SUMIFS('Detalhe Por UC'!$AB:$AB,'Detalhe Por UC'!$C:$C,'Infos Clientes'!$B3,'Detalhe Por UC'!$R:$R,'Infos Clientes'!AJ$2)=0,"", SUMIFS('Detalhe Por UC'!$AB:$AB,'Detalhe Por UC'!$C:$C,'Infos Clientes'!$B3,'Detalhe Por UC'!$R:$R,'Infos Clientes'!AJ$2) +SUMIFS('Detalhe Por UC'!$AC:$AC,'Detalhe Por UC'!$C:$C,'Infos Clientes'!$B3,'Detalhe Por UC'!$R:$R,'Infos Clientes'!AJ$2)) -> 93 | AK3: =IF(SUMIFS('Detalhe Por UC'!$AB:$AB,'Detalhe Por UC'!$C:$C,'Infos Clientes'!$B3,'Detalhe Por UC'!$R:$R,'Infos Clientes'!AK$2)=0,"", SUMIFS('Detalhe Por UC'!$AB:$AB,'Detalhe Por UC'!$C:$C,'Infos Clientes'!$B3,'Detalhe Por UC'!$R:$R,'Infos Clientes'!AK$2) +SUMIFS('Detalhe Por UC'!$AC:$AC,'Detalhe Por UC'!$C:$C,'Infos Clientes'!$B3,'Detalhe Por UC'!$R:$R,'Infos Clientes'!AK$2)) -> 203 | AL3: =IF(SUMIFS('Detalhe Por UC'!$AB:$AB,'Detalhe Por UC'!$C:$C,'Infos Clientes'!$B3,'Detalhe Por UC'!$R:$R,'Infos Clientes'!AL$2)=0,"", SUMIFS('Detalhe Por UC'!$AB:$AB,'Detalhe Por UC'!$C:$C,'Infos Clientes'!$B3,'Detalhe Por UC'!$R:$R,'Infos Clientes'!AL$2) +SUMIFS('Detalhe Por UC'!$AC:$AC,'Detalhe Por UC'!$C:$C,'Infos Clientes'!$B3,'Detalhe Por UC'!$R:$R,'Infos Clientes'!AL$2)) -> 234 | AM3: =IF(SUMIFS('Detalhe Por UC'!$AB:$AB,'Detalhe Por UC'!$C:$C,'Infos Clientes'!$B3,'Detalhe Por UC'!$R:$R,'Infos Clientes'!AM$2)=0,"", SUMIFS('Detalhe Por UC'!$AB:$AB,'Detalhe Por UC'!$C:$C,'Infos Clientes'!$B3,'Detalhe Por UC'!$R:$R,'Infos Clientes'!AM$2) +SUMIFS('Detalhe Por UC'!$AC:$AC,'Detalhe Por UC'!$C:$C,'Infos Clientes'!$B3,'Detalhe Por UC'!$R:$R,'Infos Clientes'!AM$2)) -> 199 | AN3: =IF(SUMIFS('Detalhe Por UC'!$AB:$AB,'Detalhe Por UC'!$C:$C,'Infos Clientes'!$B3,'Detalhe Por UC'!$R:$R,'Infos Clientes'!AN$2)=0,"", SUMIFS('Detalhe Por UC'!$AB:$AB,'Detalhe Por UC'!$C:$C,'Infos Clientes'!$B3,'Detalhe Por UC'!$R:$R,'Infos Clientes'!AN$2) +SUMIFS('Detalhe Por UC'!$AC:$AC,'Detalhe Por UC'!$C:$C,'Infos Clientes'!$B3,'Detalhe Por UC'!$R:$R,'Infos Clientes'!AN$2)) -> 146 | AO3: =IF(SUMIFS('Detalhe Por UC'!$AB:$AB,'Detalhe Por UC'!$C:$C,'Infos Clientes'!$B3,'Detalhe Por UC'!$R:$R,'Infos Clientes'!AO$2)=0,"", SUMIFS('Detalhe Por UC'!$AB:$AB,'Detalhe Por UC'!$C:$C,'Infos Clientes'!$B3,'Detalhe Por UC'!$R:$R,'Infos Clientes'!AO$2) +SUMIFS('Detalhe Por UC'!$AC:$AC,'Detalhe Por UC'!$C:$C,'Infos Clientes'!$B3,'Detalhe Por UC'!$R:$R,'Infos Clientes'!AO$2)) -> 78 | AP3: =IF(SUMIFS('Detalhe Por UC'!$AB:$AB,'Detalhe Por UC'!$C:$C,'Infos Clientes'!$B3,'Detalhe Por UC'!$R:$R,'Infos Clientes'!AP$2)=0,"", SUMIFS('Detalhe Por UC'!$AB:$AB,'Detalhe Por UC'!$C:$C,'Infos Clientes'!$B3,'Detalhe Por UC'!$R:$R,'Infos Clientes'!AP$2) +SUMIFS('Detalhe Por UC'!$AC:$AC,'Detalhe Por UC'!$C:$C,'Infos Clientes'!$B3,'Detalhe Por UC'!$R:$R,'Infos Clientes'!AP$2)) -> 67 | AQ3: =IF(SUMIFS('Detalhe Por UC'!$AB:$AB,'Detalhe Por UC'!$C:$C,'Infos Clientes'!$B3,'Detalhe Por UC'!$R:$R,'Infos Clientes'!AQ$2)=0,"", SUMIFS('Detalhe Por UC'!$AB:$AB,'Detalhe Por UC'!$C:$C,'Infos Clientes'!$B3,'Detalhe Por UC'!$R:$R,'Infos Clientes'!AQ$2) +SUMIFS('Detalhe Por UC'!$AC:$AC,'Detalhe Por UC'!$C:$C,'Infos Clientes'!$B3,'Detalhe Por UC'!$R:$R,'Infos Clientes'!AQ$2)) -> 81 | ... AU3: =IF(SUMIFS('Detalhe Por UC'!$AB:$AB,'Detalhe Por UC'!$C:$C,'Infos Clientes'!$B3,'Detalhe Por UC'!$R:$R,'Infos Clientes'!AU$2)=0,"", SUMIFS('Detalhe Por UC'!$AB:$AB,'Detalhe Por UC'!$C:$C,'Infos Clientes'!$B3,'Detalhe Por UC'!$R:$R,'Infos Clientes'!AU$2) +SUMIFS('Detalhe Por UC'!$AC:$AC,'Detalhe Por UC'!$C:$C,'Infos Clientes'!$B3,'Detalhe Por UC'!$R:$R,'Infos Clientes'!AU$2))
B4: 10/1035655-8 | C4: =ROW(F4) -> 4 | D4: IGREJA DO EVANGELHO QUADRANGULAR | E4: 319 | F4: 62.955.505/1822-57 | G4: evaniabenites@hotmail.com | H4: 10/1035655-8 | I4: BT | J4: trifasico | K4: GIROSSOL II | M4: 0.25 | Q4: =IF(_xlfn.MINIFS('Detalhe Por UC'!R:R,'Detalhe Por UC'!C:C,B4,'Detalhe Por UC'!AD:AD,">"&0)=0,"",_xlfn.MINIFS('Detalhe Por UC'!R:R,'Detalhe Por UC'!C:C,B4,'Detalhe Por UC'!AD:AD,">"&0)) -> 45627 | R4: =IF(P4<>"ATIVO",0, IF(OR(Q4="",Q4=0,O4=0),O4, O4-ROUND((MAX('Detalhe Por UC'!R:R) -Q4)/(365/12),0))) -> 0 | T4: 453.58333 | U4: =IFERROR((SUMIFS(W4:CN4,$W$2:$CN$2,">"&$Q$1-365,$W$2:$CN$2,"<="&$Q$1)/COUNTIFS(W4:CN4,">="&0,$W$2:$CN$2,">"&$Q$1-365,$W$2:$CN$2,"<="&$Q$1)),"") -> 375.91667 | W4: 298 | X4: 455 | Y4: 591 | Z4: 630 | AA4: 540 | AB4: 369 | AC4: 381 | AD4: 214 | AE4: 273 | AF4: 321 | AG4: 385 | AH4: 671 | AI4: 528 | AJ4: =IF(SUMIFS('Detalhe Por UC'!$AB:$AB,'Detalhe Por UC'!$C:$C,'Infos Clientes'!$B4,'Detalhe Por UC'!$R:$R,'Infos Clientes'!AJ$2)=0,"", SUMIFS('Detalhe Por UC'!$AB:$AB,'Detalhe Por UC'!$C:$C,'Infos Clientes'!$B4,'Detalhe Por UC'!$R:$R,'Infos Clientes'!AJ$2) +SUMIFS('Detalhe Por UC'!$AC:$AC,'Detalhe Por UC'!$C:$C,'Infos Clientes'!$B4,'Detalhe Por UC'!$R:$R,'Infos Clientes'!AJ$2)) -> 540 | AK4: =IF(SUMIFS('Detalhe Por UC'!$AB:$AB,'Detalhe Por UC'!$C:$C,'Infos Clientes'!$B4,'Detalhe Por UC'!$R:$R,'Infos Clientes'!AK$2)=0,"", SUMIFS('Detalhe Por UC'!$AB:$AB,'Detalhe Por UC'!$C:$C,'Infos Clientes'!$B4,'Detalhe Por UC'!$R:$R,'Infos Clientes'!AK$2) +SUMIFS('Detalhe Por UC'!$AC:$AC,'Detalhe Por UC'!$C:$C,'Infos Clientes'!$B4,'Detalhe Por UC'!$R:$R,'Infos Clientes'!AK$2)) -> 433 | AL4: =IF(SUMIFS('Detalhe Por UC'!$AB:$AB,'Detalhe Por UC'!$C:$C,'Infos Clientes'!$B4,'Detalhe Por UC'!$R:$R,'Infos Clientes'!AL$2)=0,"", SUMIFS('Detalhe Por UC'!$AB:$AB,'Detalhe Por UC'!$C:$C,'Infos Clientes'!$B4,'Detalhe Por UC'!$R:$R,'Infos Clientes'!AL$2) +SUMIFS('Detalhe Por UC'!$AC:$AC,'Detalhe Por UC'!$C:$C,'Infos Clientes'!$B4,'Detalhe Por UC'!$R:$R,'Infos Clientes'!AL$2)) -> 581 | AM4: =IF(SUMIFS('Detalhe Por UC'!$AB:$AB,'Detalhe Por UC'!$C:$C,'Infos Clientes'!$B4,'Detalhe Por UC'!$R:$R,'Infos Clientes'!AM$2)=0,"", SUMIFS('Detalhe Por UC'!$AB:$AB,'Detalhe Por UC'!$C:$C,'Infos Clientes'!$B4,'Detalhe Por UC'!$R:$R,'Infos Clientes'!AM$2) +SUMIFS('Detalhe Por UC'!$AC:$AC,'Detalhe Por UC'!$C:$C,'Infos Clientes'!$B4,'Detalhe Por UC'!$R:$R,'Infos Clientes'!AM$2)) -> 338 | AN4: =IF(SUMIFS('Detalhe Por UC'!$AB:$AB,'Detalhe Por UC'!$C:$C,'Infos Clientes'!$B4,'Detalhe Por UC'!$R:$R,'Infos Clientes'!AN$2)=0,"", SUMIFS('Detalhe Por UC'!$AB:$AB,'Detalhe Por UC'!$C:$C,'Infos Clientes'!$B4,'Detalhe Por UC'!$R:$R,'Infos Clientes'!AN$2) +SUMIFS('Detalhe Por UC'!$AC:$AC,'Detalhe Por UC'!$C:$C,'Infos Clientes'!$B4,'Detalhe Por UC'!$R:$R,'Infos Clientes'!AN$2)) -> 259 | AO4: =IF(SUMIFS('Detalhe Por UC'!$AB:$AB,'Detalhe Por UC'!$C:$C,'Infos Clientes'!$B4,'Detalhe Por UC'!$R:$R,'Infos Clientes'!AO$2)=0,"", SUMIFS('Detalhe Por UC'!$AB:$AB,'Detalhe Por UC'!$C:$C,'Infos Clientes'!$B4,'Detalhe Por UC'!$R:$R,'Infos Clientes'!AO$2) +SUMIFS('Detalhe Por UC'!$AC:$AC,'Detalhe Por UC'!$C:$C,'Infos Clientes'!$B4,'Detalhe Por UC'!$R:$R,'Infos Clientes'!AO$2)) -> 272 | AP4: =IF(SUMIFS('Detalhe Por UC'!$AB:$AB,'Detalhe Por UC'!$C:$C,'Infos Clientes'!$B4,'Detalhe Por UC'!$R:$R,'Infos Clientes'!AP$2)=0,"", SUMIFS('Detalhe Por UC'!$AB:$AB,'Detalhe Por UC'!$C:$C,'Infos Clientes'!$B4,'Detalhe Por UC'!$R:$R,'Infos Clientes'!AP$2) +SUMIFS('Detalhe Por UC'!$AC:$AC,'Detalhe Por UC'!$C:$C,'Infos Clientes'!$B4,'Detalhe Por UC'!$R:$R,'Infos Clientes'!AP$2)) -> 172 | AQ4: =IF(SUMIFS('Detalhe Por UC'!$AB:$AB,'Detalhe Por UC'!$C:$C,'Infos Clientes'!$B4,'Detalhe Por UC'!$R:$R,'Infos Clientes'!AQ$2)=0,"", SUMIFS('Detalhe Por UC'!$AB:$AB,'Detalhe Por UC'!$C:$C,'Infos Clientes'!$B4,'Detalhe Por UC'!$R:$R,'Infos Clientes'!AQ$2) +SUMIFS('Detalhe Por UC'!$AC:$AC,'Detalhe Por UC'!$C:$C,'Infos Clientes'!$B4,'Detalhe Por UC'!$R:$R,'Infos Clientes'!AQ$2)) -> 205 | ... AU4: =IF(SUMIFS('Detalhe Por UC'!$AB:$AB,'Detalhe Por UC'!$C:$C,'Infos Clientes'!$B4,'Detalhe Por UC'!$R:$R,'Infos Clientes'!AU$2)=0,"", SUMIFS('Detalhe Por UC'!$AB:$AB,'Detalhe Por UC'!$C:$C,'Infos Clientes'!$B4,'Detalhe Por UC'!$R:$R,'Infos Clientes'!AU$2) +SUMIFS('Detalhe Por UC'!$AC:$AC,'Detalhe Por UC'!$C:$C,'Infos Clientes'!$B4,'Detalhe Por UC'!$R:$R,'Infos Clientes'!AU$2))
B5: 10/1117293-9 | C5: =ROW(F5) -> 5 | D5: IGREJA DO EVANGELHO QUADRANGULAR | E5: 362 | F5: 62.955.505/8921-14 | G5: pastordamilton@gmail.com | H5: 10/1117293-9 | I5: BT | J5: trifasico | K5: GIROSSOL II | M5: 0.25 | Q5: =IF(_xlfn.MINIFS('Detalhe Por UC'!R:R,'Detalhe Por UC'!C:C,B5,'Detalhe Por UC'!AD:AD,">"&0)=0,"",_xlfn.MINIFS('Detalhe Por UC'!R:R,'Detalhe Por UC'!C:C,B5,'Detalhe Por UC'!AD:AD,">"&0)) -> 45627 | R5: =IF(P5<>"ATIVO",0, IF(OR(Q5="",Q5=0,O5=0),O5, O5-ROUND((MAX('Detalhe Por UC'!R:R) -Q5)/(365/12),0))) -> 0 | T5: 178.41667 | U5: =IFERROR((SUMIFS(W5:CN5,$W$2:$CN$2,">"&$Q$1-365,$W$2:$CN$2,"<="&$Q$1)/COUNTIFS(W5:CN5,">="&0,$W$2:$CN$2,">"&$Q$1-365,$W$2:$CN$2,"<="&$Q$1)),"") -> 161.33333 | W5: 163 | X5: 185 | Y5: 161 | Z5: 221 | AA5: 180 | AB5: 165 | AC5: 160 | AD5: 145 | AE5: 160 | AF5: 152 | AG5: 175 | AH5: 179 | AI5: 161 | AJ5: =IF(SUMIFS('Detalhe Por UC'!$AB:$AB,'Detalhe Por UC'!$C:$C,'Infos Clientes'!$B5,'Detalhe Por UC'!$R:$R,'Infos Clientes'!AJ$2)=0,"", SUMIFS('Detalhe Por UC'!$AB:$AB,'Detalhe Por UC'!$C:$C,'Infos Clientes'!$B5,'Detalhe Por UC'!$R:$R,'Infos Clientes'!AJ$2) +SUMIFS('Detalhe Por UC'!$AC:$AC,'Detalhe Por UC'!$C:$C,'Infos Clientes'!$B5,'Detalhe Por UC'!$R:$R,'Infos Clientes'!AJ$2)) -> 282 | AK5: =IF(SUMIFS('Detalhe Por UC'!$AB:$AB,'Detalhe Por UC'!$C:$C,'Infos Clientes'!$B5,'Detalhe Por UC'!$R:$R,'Infos Clientes'!AK$2)=0,"", SUMIFS('Detalhe Por UC'!$AB:$AB,'Detalhe Por UC'!$C:$C,'Infos Clientes'!$B5,'Detalhe Por UC'!$R:$R,'Infos Clientes'!AK$2) +SUMIFS('Detalhe Por UC'!$AC:$AC,'Detalhe Por UC'!$C:$C,'Infos Clientes'!$B5,'Detalhe Por UC'!$R:$R,'Infos Clientes'!AK$2)) -> 171 | AL5: =IF(SUMIFS('Detalhe Por UC'!$AB:$AB,'Detalhe Por UC'!$C:$C,'Infos Clientes'!$B5,'Detalhe Por UC'!$R:$R,'Infos Clientes'!AL$2)=0,"", SUMIFS('Detalhe Por UC'!$AB:$AB,'Detalhe Por UC'!$C:$C,'Infos Clientes'!$B5,'Detalhe Por UC'!$R:$R,'Infos Clientes'!AL$2) +SUMIFS('Detalhe Por UC'!$AC:$AC,'Detalhe Por UC'!$C:$C,'Infos Clientes'!$B5,'Detalhe Por UC'!$R:$R,'Infos Clientes'!AL$2)) -> 185 | AM5: =IF(SUMIFS('Detalhe Por UC'!$AB:$AB,'Detalhe Por UC'!$C:$C,'Infos Clientes'!$B5,'Detalhe Por UC'!$R:$R,'Infos Clientes'!AM$2)=0,"", SUMIFS('Detalhe Por UC'!$AB:$AB,'Detalhe Por UC'!$C:$C,'Infos Clientes'!$B5,'Detalhe Por UC'!$R:$R,'Infos Clientes'!AM$2) +SUMIFS('Detalhe Por UC'!$AC:$AC,'Detalhe Por UC'!$C:$C,'Infos Clientes'!$B5,'Detalhe Por UC'!$R:$R,'Infos Clientes'!AM$2)) -> 176 | AN5: =IF(SUMIFS('Detalhe Por UC'!$AB:$AB,'Detalhe Por UC'!$C:$C,'Infos Clientes'!$B5,'Detalhe Por UC'!$R:$R,'Infos Clientes'!AN$2)=0,"", SUMIFS('Detalhe Por UC'!$AB:$AB,'Detalhe Por UC'!$C:$C,'Infos Clientes'!$B5,'Detalhe Por UC'!$R:$R,'Infos Clientes'!AN$2) +SUMIFS('Detalhe Por UC'!$AC:$AC,'Detalhe Por UC'!$C:$C,'Infos Clientes'!$B5,'Detalhe Por UC'!$R:$R,'Infos Clientes'!AN$2)) -> 153 | AO5: =IF(SUMIFS('Detalhe Por UC'!$AB:$AB,'Detalhe Por UC'!$C:$C,'Infos Clientes'!$B5,'Detalhe Por UC'!$R:$R,'Infos Clientes'!AO$2)=0,"", SUMIFS('Detalhe Por UC'!$AB:$AB,'Detalhe Por UC'!$C:$C,'Infos Clientes'!$B5,'Detalhe Por UC'!$R:$R,'Infos Clientes'!AO$2) +SUMIFS('Detalhe Por UC'!$AC:$AC,'Detalhe Por UC'!$C:$C,'Infos Clientes'!$B5,'Detalhe Por UC'!$R:$R,'Infos Clientes'!AO$2)) -> 118 | AP5: =IF(SUMIFS('Detalhe Por UC'!$AB:$AB,'Detalhe Por UC'!$C:$C,'Infos Clientes'!$B5,'Detalhe Por UC'!$R:$R,'Infos Clientes'!AP$2)=0,"", SUMIFS('Detalhe Por UC'!$AB:$AB,'Detalhe Por UC'!$C:$C,'Infos Clientes'!$B5,'Detalhe Por UC'!$R:$R,'Infos Clientes'!AP$2) +SUMIFS('Detalhe Por UC'!$AC:$AC,'Detalhe Por UC'!$C:$C,'Infos Clientes'!$B5,'Detalhe Por UC'!$R:$R,'Infos Clientes'!AP$2)) -> 115 | AQ5: =IF(SUMIFS('Detalhe Por UC'!$AB:$AB,'Detalhe Por UC'!$C:$C,'Infos Clientes'!$B5,'Detalhe Por UC'!$R:$R,'Infos Clientes'!AQ$2)=0,"", SUMIFS('Detalhe Por UC'!$AB:$AB,'Detalhe Por UC'!$C:$C,'Infos Clientes'!$B5,'Detalhe Por UC'!$R:$R,'Infos Clientes'!AQ$2) +SUMIFS('Detalhe Por UC'!$AC:$AC,'Detalhe Por UC'!$C:$C,'Infos Clientes'!$B5,'Detalhe Por UC'!$R:$R,'Infos Clientes'!AQ$2)) -> 121 | ... AU5: =IF(SUMIFS('Detalhe Por UC'!$AB:$AB,'Detalhe Por UC'!$C:$C,'Infos Clientes'!$B5,'Detalhe Por UC'!$R:$R,'Infos Clientes'!AU$2)=0,"", SUMIFS('Detalhe Por UC'!$AB:$AB,'Detalhe Por UC'!$C:$C,'Infos Clientes'!$B5,'Detalhe Por UC'!$R:$R,'Infos Clientes'!AU$2) +SUMIFS('Detalhe Por UC'!$AC:$AC,'Detalhe Por UC'!$C:$C,'Infos Clientes'!$B5,'Detalhe Por UC'!$R:$R,'Infos Clientes'!AU$2))
B6: 10/113971-6 | C6: =ROW(F6) -> 6 | D6: IGREJA DO EVANGELHO QUADRANGULAR | E6: 319 | F6: 62.955.505/0156-01 | G6: pastora-regina@hotmail.com | H6: 10/113971-6 | I6: BT | J6: trifasico | K6: GIROSSOL II | M6: 0.25 | Q6: =IF(_xlfn.MINIFS('Detalhe Por UC'!R:R,'Detalhe Por UC'!C:C,B6,'Detalhe Por UC'!AD:AD,">"&0)=0,"",_xlfn.MINIFS('Detalhe Por UC'!R:R,'Detalhe Por UC'!C:C,B6,'Detalhe Por UC'!AD:AD,">"&0)) -> 45627 | R6: =IF(P6<>"ATIVO",0, IF(OR(Q6="",Q6=0,O6=0),O6, O6-ROUND((MAX('Detalhe Por UC'!R:R) -Q6)/(365/12),0))) -> 0 | T6: 236.08333 | U6: =IFERROR((SUMIFS(W6:CN6,$W$2:$CN$2,">"&$Q$1-365,$W$2:$CN$2,"<="&$Q$1)/COUNTIFS(W6:CN6,">="&0,$W$2:$CN$2,">"&$Q$1-365,$W$2:$CN$2,"<="&$Q$1)),"") -> 256.91667 | W6: 199 | X6: 189 | Y6: 230 | Z6: 213 | AA6: 329 | AB6: 259 | AC6: 203 | AD6: 211 | AE6: 218 | AF6: 177 | AG6: 244 | AH6: 218 | AI6: 278 | AJ6: =IF(SUMIFS('Detalhe Por UC'!$AB:$AB,'Detalhe Por UC'!$C:$C,'Infos Clientes'!$B6,'Detalhe Por UC'!$R:$R,'Infos Clientes'!AJ$2)=0,"", SUMIFS('Detalhe Por UC'!$AB:$AB,'Detalhe Por UC'!$C:$C,'Infos Clientes'!$B6,'Detalhe Por UC'!$R:$R,'Infos Clientes'!AJ$2) +SUMIFS('Detalhe Por UC'!$AC:$AC,'Detalhe Por UC'!$C:$C,'Infos Clientes'!$B6,'Detalhe Por UC'!$R:$R,'Infos Clientes'!AJ$2)) -> 253 | AK6: =IF(SUMIFS('Detalhe Por UC'!$AB:$AB,'Detalhe Por UC'!$C:$C,'Infos Clientes'!$B6,'Detalhe Por UC'!$R:$R,'Infos Clientes'!AK$2)=0,"", SUMIFS('Detalhe Por UC'!$AB:$AB,'Detalhe Por UC'!$C:$C,'Infos Clientes'!$B6,'Detalhe Por UC'!$R:$R,'Infos Clientes'!AK$2) +SUMIFS('Detalhe Por UC'!$AC:$AC,'Detalhe Por UC'!$C:$C,'Infos Clientes'!$B6,'Detalhe Por UC'!$R:$R,'Infos Clientes'!AK$2)) -> 324 | AL6: =IF(SUMIFS('Detalhe Por UC'!$AB:$AB,'Detalhe Por UC'!$C:$C,'Infos Clientes'!$B6,'Detalhe Por UC'!$R:$R,'Infos Clientes'!AL$2)=0,"", SUMIFS('Detalhe Por UC'!$AB:$AB,'Detalhe Por UC'!$C:$C,'Infos Clientes'!$B6,'Detalhe Por UC'!$R:$R,'Infos Clientes'!AL$2) +SUMIFS('Detalhe Por UC'!$AC:$AC,'Detalhe Por UC'!$C:$C,'Infos Clientes'!$B6,'Detalhe Por UC'!$R:$R,'Infos Clientes'!AL$2)) -> 394 | AM6: =IF(SUMIFS('Detalhe Por UC'!$AB:$AB,'Detalhe Por UC'!$C:$C,'Infos Clientes'!$B6,'Detalhe Por UC'!$R:$R,'Infos Clientes'!AM$2)=0,"", SUMIFS('Detalhe Por UC'!$AB:$AB,'Detalhe Por UC'!$C:$C,'Infos Clientes'!$B6,'Detalhe Por UC'!$R:$R,'Infos Clientes'!AM$2) +SUMIFS('Detalhe Por UC'!$AC:$AC,'Detalhe Por UC'!$C:$C,'Infos Clientes'!$B6,'Detalhe Por UC'!$R:$R,'Infos Clientes'!AM$2)) -> 290 | AN6: =IF(SUMIFS('Detalhe Por UC'!$AB:$AB,'Detalhe Por UC'!$C:$C,'Infos Clientes'!$B6,'Detalhe Por UC'!$R:$R,'Infos Clientes'!AN$2)=0,"", SUMIFS('Detalhe Por UC'!$AB:$AB,'Detalhe Por UC'!$C:$C,'Infos Clientes'!$B6,'Detalhe Por UC'!$R:$R,'Infos Clientes'!AN$2) +SUMIFS('Detalhe Por UC'!$AC:$AC,'Detalhe Por UC'!$C:$C,'Infos Clientes'!$B6,'Detalhe Por UC'!$R:$R,'Infos Clientes'!AN$2)) -> 226 | AO6: =IF(SUMIFS('Detalhe Por UC'!$AB:$AB,'Detalhe Por UC'!$C:$C,'Infos Clientes'!$B6,'Detalhe Por UC'!$R:$R,'Infos Clientes'!AO$2)=0,"", SUMIFS('Detalhe Por UC'!$AB:$AB,'Detalhe Por UC'!$C:$C,'Infos Clientes'!$B6,'Detalhe Por UC'!$R:$R,'Infos Clientes'!AO$2) +SUMIFS('Detalhe Por UC'!$AC:$AC,'Detalhe Por UC'!$C:$C,'Infos Clientes'!$B6,'Detalhe Por UC'!$R:$R,'Infos Clientes'!AO$2)) -> 202 | AP6: =IF(SUMIFS('Detalhe Por UC'!$AB:$AB,'Detalhe Por UC'!$C:$C,'Infos Clientes'!$B6,'Detalhe Por UC'!$R:$R,'Infos Clientes'!AP$2)=0,"", SUMIFS('Detalhe Por UC'!$AB:$AB,'Detalhe Por UC'!$C:$C,'Infos Clientes'!$B6,'Detalhe Por UC'!$R:$R,'Infos Clientes'!AP$2) +SUMIFS('Detalhe Por UC'!$AC:$AC,'Detalhe Por UC'!$C:$C,'Infos Clientes'!$B6,'Detalhe Por UC'!$R:$R,'Infos Clientes'!AP$2)) -> 197 | AQ6: =IF(SUMIFS('Detalhe Por UC'!$AB:$AB,'Detalhe Por UC'!$C:$C,'Infos Clientes'!$B6,'Detalhe Por UC'!$R:$R,'Infos Clientes'!AQ$2)=0,"", SUMIFS('Detalhe Por UC'!$AB:$AB,'Detalhe Por UC'!$C:$C,'Infos Clientes'!$B6,'Detalhe Por UC'!$R:$R,'Infos Clientes'!AQ$2) +SUMIFS('Detalhe Por UC'!$AC:$AC,'Detalhe Por UC'!$C:$C,'Infos Clientes'!$B6,'Detalhe Por UC'!$R:$R,'Infos Clientes'!AQ$2)) -> 184 | ... AU6: =IF(SUMIFS('Detalhe Por UC'!$AB:$AB,'Detalhe Por UC'!$C:$C,'Infos Clientes'!$B6,'Detalhe Por UC'!$R:$R,'Infos Clientes'!AU$2)=0,"", SUMIFS('Detalhe Por UC'!$AB:$AB,'Detalhe Por UC'!$C:$C,'Infos Clientes'!$B6,'Detalhe Por UC'!$R:$R,'Infos Clientes'!AU$2) +SUMIFS('Detalhe Por UC'!$AC:$AC,'Detalhe Por UC'!$C:$C,'Infos Clientes'!$B6,'Detalhe Por UC'!$R:$R,'Infos Clientes'!AU$2))
B7: 10/1184751-4 | C7: =ROW(F7) -> 7 | D7: IGREJA DO EVANGELHO QUADRANGULAR | E7: 319 | F7: 62.955.505/1490-47 | G7: monicadossantosfonseca@hotmail.com | H7: 10/1184751-4 | I7: BT | J7: trifasico | K7: GIROSSOL II | M7: 0.25 | Q7: =IF(_xlfn.MINIFS('Detalhe Por UC'!R:R,'Detalhe Por UC'!C:C,B7,'Detalhe Por UC'!AD:AD,">"&0)=0,"",_xlfn.MINIFS('Detalhe Por UC'!R:R,'Detalhe Por UC'!C:C,B7,'Detalhe Por UC'!AD:AD,">"&0)) -> 45627 | R7: =IF(P7<>"ATIVO",0, IF(OR(Q7="",Q7=0,O7=0),O7, O7-ROUND((MAX('Detalhe Por UC'!R:R) -Q7)/(365/12),0))) -> 0 | T7: 182.25 | U7: =IFERROR((SUMIFS(W7:CN7,$W$2:$CN$2,">"&$Q$1-365,$W$2:$CN$2,"<="&$Q$1)/COUNTIFS(W7:CN7,">="&0,$W$2:$CN$2,">"&$Q$1-365,$W$2:$CN$2,"<="&$Q$1)),"") -> 287.5 | W7: 216 | X7: 195 | Y7: 205 | Z7: 203 | AA7: 233 | AB7: 181 | AC7: 175 | AD7: 188 | AE7: 162 | AF7: 143 | AG7: 162 | AH7: 171 | AI7: 196 | AJ7: =IF(SUMIFS('Detalhe Por UC'!$AB:$AB,'Detalhe Por UC'!$C:$C,'Infos Clientes'!$B7,'Detalhe Por UC'!$R:$R,'Infos Clientes'!AJ$2)=0,"", SUMIFS('Detalhe Por UC'!$AB:$AB,'Detalhe Por UC'!$C:$C,'Infos Clientes'!$B7,'Detalhe Por UC'!$R:$R,'Infos Clientes'!AJ$2) +SUMIFS('Detalhe Por UC'!$AC:$AC,'Detalhe Por UC'!$C:$C,'Infos Clientes'!$B7,'Detalhe Por UC'!$R:$R,'Infos Clientes'!AJ$2)) -> 168 | AK7: =IF(SUMIFS('Detalhe Por UC'!$AB:$AB,'Detalhe Por UC'!$C:$C,'Infos Clientes'!$B7,'Detalhe Por UC'!$R:$R,'Infos Clientes'!AK$2)=0,"", SUMIFS('Detalhe Por UC'!$AB:$AB,'Detalhe Por UC'!$C:$C,'Infos Clientes'!$B7,'Detalhe Por UC'!$R:$R,'Infos Clientes'!AK$2) +SUMIFS('Detalhe Por UC'!$AC:$AC,'Detalhe Por UC'!$C:$C,'Infos Clientes'!$B7,'Detalhe Por UC'!$R:$R,'Infos Clientes'!AK$2)) -> 322 | AL7: =IF(SUMIFS('Detalhe Por UC'!$AB:$AB,'Detalhe Por UC'!$C:$C,'Infos Clientes'!$B7,'Detalhe Por UC'!$R:$R,'Infos Clientes'!AL$2)=0,"", SUMIFS('Detalhe Por UC'!$AB:$AB,'Detalhe Por UC'!$C:$C,'Infos Clientes'!$B7,'Detalhe Por UC'!$R:$R,'Infos Clientes'!AL$2) +SUMIFS('Detalhe Por UC'!$AC:$AC,'Detalhe Por UC'!$C:$C,'Infos Clientes'!$B7,'Detalhe Por UC'!$R:$R,'Infos Clientes'!AL$2)) -> 371 | AM7: =IF(SUMIFS('Detalhe Por UC'!$AB:$AB,'Detalhe Por UC'!$C:$C,'Infos Clientes'!$B7,'Detalhe Por UC'!$R:$R,'Infos Clientes'!AM$2)=0,"", SUMIFS('Detalhe Por UC'!$AB:$AB,'Detalhe Por UC'!$C:$C,'Infos Clientes'!$B7,'Detalhe Por UC'!$R:$R,'Infos Clientes'!AM$2) +SUMIFS('Detalhe Por UC'!$AC:$AC,'Detalhe Por UC'!$C:$C,'Infos Clientes'!$B7,'Detalhe Por UC'!$R:$R,'Infos Clientes'!AM$2)) -> 317 | AN7: =IF(SUMIFS('Detalhe Por UC'!$AB:$AB,'Detalhe Por UC'!$C:$C,'Infos Clientes'!$B7,'Detalhe Por UC'!$R:$R,'Infos Clientes'!AN$2)=0,"", SUMIFS('Detalhe Por UC'!$AB:$AB,'Detalhe Por UC'!$C:$C,'Infos Clientes'!$B7,'Detalhe Por UC'!$R:$R,'Infos Clientes'!AN$2) +SUMIFS('Detalhe Por UC'!$AC:$AC,'Detalhe Por UC'!$C:$C,'Infos Clientes'!$B7,'Detalhe Por UC'!$R:$R,'Infos Clientes'!AN$2)) -> 293 | AO7: =IF(SUMIFS('Detalhe Por UC'!$AB:$AB,'Detalhe Por UC'!$C:$C,'Infos Clientes'!$B7,'Detalhe Por UC'!$R:$R,'Infos Clientes'!AO$2)=0,"", SUMIFS('Detalhe Por UC'!$AB:$AB,'Detalhe Por UC'!$C:$C,'Infos Clientes'!$B7,'Detalhe Por UC'!$R:$R,'Infos Clientes'!AO$2) +SUMIFS('Detalhe Por UC'!$AC:$AC,'Detalhe Por UC'!$C:$C,'Infos Clientes'!$B7,'Detalhe Por UC'!$R:$R,'Infos Clientes'!AO$2)) -> 323 | AP7: =IF(SUMIFS('Detalhe Por UC'!$AB:$AB,'Detalhe Por UC'!$C:$C,'Infos Clientes'!$B7,'Detalhe Por UC'!$R:$R,'Infos Clientes'!AP$2)=0,"", SUMIFS('Detalhe Por UC'!$AB:$AB,'Detalhe Por UC'!$C:$C,'Infos Clientes'!$B7,'Detalhe Por UC'!$R:$R,'Infos Clientes'!AP$2) +SUMIFS('Detalhe Por UC'!$AC:$AC,'Detalhe Por UC'!$C:$C,'Infos Clientes'!$B7,'Detalhe Por UC'!$R:$R,'Infos Clientes'!AP$2)) -> 292 | AQ7: =IF(SUMIFS('Detalhe Por UC'!$AB:$AB,'Detalhe Por UC'!$C:$C,'Infos Clientes'!$B7,'Detalhe Por UC'!$R:$R,'Infos Clientes'!AQ$2)=0,"", SUMIFS('Detalhe Por UC'!$AB:$AB,'Detalhe Por UC'!$C:$C,'Infos Clientes'!$B7,'Detalhe Por UC'!$R:$R,'Infos Clientes'!AQ$2) +SUMIFS('Detalhe Por UC'!$AC:$AC,'Detalhe Por UC'!$C:$C,'Infos Clientes'!$B7,'Detalhe Por UC'!$R:$R,'Infos Clientes'!AQ$2)) -> 298 | ... AU7: =IF(SUMIFS('Detalhe Por UC'!$AB:$AB,'Detalhe Por UC'!$C:$C,'Infos Clientes'!$B7,'Detalhe Por UC'!$R:$R,'Infos Clientes'!AU$2)=0,"", SUMIFS('Detalhe Por UC'!$AB:$AB,'Detalhe Por UC'!$C:$C,'Infos Clientes'!$B7,'Detalhe Por UC'!$R:$R,'Infos Clientes'!AU$2) +SUMIFS('Detalhe Por UC'!$AC:$AC,'Detalhe Por UC'!$C:$C,'Infos Clientes'!$B7,'Detalhe Por UC'!$R:$R,'Infos Clientes'!AU$2))
B8: 10/135237-6 | C8: =ROW(F8) -> 8 | D8: IGREJA DO EVANGELHO QUADRANGULAR | E8: 351 | F8: 62.955.505/0800-98 | G8: igrejaquadrangularmaracaju1@hotmail.com | H8: 10/135237-6 | I8: BT | J8: trifasico | K8: GIROSSOL II | M8: 0.25 | Q8: =IF(_xlfn.MINIFS('Detalhe Por UC'!R:R,'Detalhe Por UC'!C:C,B8,'Detalhe Por UC'!AD:AD,">"&0)=0,"",_xlfn.MINIFS('Detalhe Por UC'!R:R,'Detalhe Por UC'!C:C,B8,'Detalhe Por UC'!AD:AD,">"&0)) -> 45627 | R8: =IF(P8<>"ATIVO",0, IF(OR(Q8="",Q8=0,O8=0),O8, O8-ROUND((MAX('Detalhe Por UC'!R:R) -Q8)/(365/12),0))) -> 0 | T8: 134.36364 | U8: =IFERROR((SUMIFS(W8:CN8,$W$2:$CN$2,">"&$Q$1-365,$W$2:$CN$2,"<="&$Q$1)/COUNTIFS(W8:CN8,">="&0,$W$2:$CN$2,">"&$Q$1-365,$W$2:$CN$2,"<="&$Q$1)),"") -> 148.125 | W8: 130 | X8: 124 | Y8: 151 | Z8: 183 | AA8: 156 | AB8: 184 | AC8: 100 | AD8: 90 | AE8: 103 | AF8: 113 | AG8: 148 | AH8: 112 | AI8: 138 | AJ8: =IF(SUMIFS('Detalhe Por UC'!$AB:$AB,'Detalhe Por UC'!$C:$C,'Infos Clientes'!$B8,'Detalhe Por UC'!$R:$R,'Infos Clientes'!AJ$2)=0,"", SUMIFS('Detalhe Por UC'!$AB:$AB,'Detalhe Por UC'!$C:$C,'Infos Clientes'!$B8,'Detalhe Por UC'!$R:$R,'Infos Clientes'!AJ$2) +SUMIFS('Detalhe Por UC'!$AC:$AC,'Detalhe Por UC'!$C:$C,'Infos Clientes'!$B8,'Detalhe Por UC'!$R:$R,'Infos Clientes'!AJ$2)) | AK8: =IF(SUMIFS('Detalhe Por UC'!$AB:$AB,'Detalhe Por UC'!$C:$C,'Infos Clientes'!$B8,'Detalhe Por UC'!$R:$R,'Infos Clientes'!AK$2)=0,"", SUMIFS('Detalhe Por UC'!$AB:$AB,'Detalhe Por UC'!$C:$C,'Infos Clientes'!$B8,'Detalhe Por UC'!$R:$R,'Infos Clientes'!AK$2) +SUMIFS('Detalhe Por UC'!$AC:$AC,'Detalhe Por UC'!$C:$C,'Infos Clientes'!$B8,'Detalhe Por UC'!$R:$R,'Infos Clientes'!AK$2)) -> 159 | AL8: =IF(SUMIFS('Detalhe Por UC'!$AB:$AB,'Detalhe Por UC'!$C:$C,'Infos Clientes'!$B8,'Detalhe Por UC'!$R:$R,'Infos Clientes'!AL$2)=0,"", SUMIFS('Detalhe Por UC'!$AB:$AB,'Detalhe Por UC'!$C:$C,'Infos Clientes'!$B8,'Detalhe Por UC'!$R:$R,'Infos Clientes'!AL$2) +SUMIFS('Detalhe Por UC'!$AC:$AC,'Detalhe Por UC'!$C:$C,'Infos Clientes'!$B8,'Detalhe Por UC'!$R:$R,'Infos Clientes'!AL$2)) -> 197 | AM8: =IF(SUMIFS('Detalhe Por UC'!$AB:$AB,'Detalhe Por UC'!$C:$C,'Infos Clientes'!$B8,'Detalhe Por UC'!$R:$R,'Infos Clientes'!AM$2)=0,"", SUMIFS('Detalhe Por UC'!$AB:$AB,'Detalhe Por UC'!$C:$C,'Infos Clientes'!$B8,'Detalhe Por UC'!$R:$R,'Infos Clientes'!AM$2) +SUMIFS('Detalhe Por UC'!$AC:$AC,'Detalhe Por UC'!$C:$C,'Infos Clientes'!$B8,'Detalhe Por UC'!$R:$R,'Infos Clientes'!AM$2)) -> 157 | AN8: =IF(SUMIFS('Detalhe Por UC'!$AB:$AB,'Detalhe Por UC'!$C:$C,'Infos Clientes'!$B8,'Detalhe Por UC'!$R:$R,'Infos Clientes'!AN$2)=0,"", SUMIFS('Detalhe Por UC'!$AB:$AB,'Detalhe Por UC'!$C:$C,'Infos Clientes'!$B8,'Detalhe Por UC'!$R:$R,'Infos Clientes'!AN$2) +SUMIFS('Detalhe Por UC'!$AC:$AC,'Detalhe Por UC'!$C:$C,'Infos Clientes'!$B8,'Detalhe Por UC'!$R:$R,'Infos Clientes'!AN$2)) -> 106 | AO8: =IF(SUMIFS('Detalhe Por UC'!$AB:$AB,'Detalhe Por UC'!$C:$C,'Infos Clientes'!$B8,'Detalhe Por UC'!$R:$R,'Infos Clientes'!AO$2)=0,"", SUMIFS('Detalhe Por UC'!$AB:$AB,'Detalhe Por UC'!$C:$C,'Infos Clientes'!$B8,'Detalhe Por UC'!$R:$R,'Infos Clientes'!AO$2) +SUMIFS('Detalhe Por UC'!$AC:$AC,'Detalhe Por UC'!$C:$C,'Infos Clientes'!$B8,'Detalhe Por UC'!$R:$R,'Infos Clientes'!AO$2)) | AP8: =IF(SUMIFS('Detalhe Por UC'!$AB:$AB,'Detalhe Por UC'!$C:$C,'Infos Clientes'!$B8,'Detalhe Por UC'!$R:$R,'Infos Clientes'!AP$2)=0,"", SUMIFS('Detalhe Por UC'!$AB:$AB,'Detalhe Por UC'!$C:$C,'Infos Clientes'!$B8,'Detalhe Por UC'!$R:$R,'Infos Clientes'!AP$2) +SUMIFS('Detalhe Por UC'!$AC:$AC,'Detalhe Por UC'!$C:$C,'Infos Clientes'!$B8,'Detalhe Por UC'!$R:$R,'Infos Clientes'!AP$2)) | AQ8: =IF(SUMIFS('Detalhe Por UC'!$AB:$AB,'Detalhe Por UC'!$C:$C,'Infos Clientes'!$B8,'Detalhe Por UC'!$R:$R,'Infos Clientes'!AQ$2)=0,"", SUMIFS('Detalhe Por UC'!$AB:$AB,'Detalhe Por UC'!$C:$C,'Infos Clientes'!$B8,'Detalhe Por UC'!$R:$R,'Infos Clientes'!AQ$2) +SUMIFS('Detalhe Por UC'!$AC:$AC,'Detalhe Por UC'!$C:$C,'Infos Clientes'!$B8,'Detalhe Por UC'!$R:$R,'Infos Clientes'!AQ$2)) -> 100 | ... AU8: =IF(SUMIFS('Detalhe Por UC'!$AB:$AB,'Detalhe Por UC'!$C:$C,'Infos Clientes'!$B8,'Detalhe Por UC'!$R:$R,'Infos Clientes'!AU$2)=0,"", SUMIFS('Detalhe Por UC'!$AB:$AB,'Detalhe Por UC'!$C:$C,'Infos Clientes'!$B8,'Detalhe Por UC'!$R:$R,'Infos Clientes'!AU$2) +SUMIFS('Detalhe Por UC'!$AC:$AC,'Detalhe Por UC'!$C:$C,'Infos Clientes'!$B8,'Detalhe Por UC'!$R:$R,'Infos Clientes'!AU$2))
B9: 10/1548741-6 | C9: =ROW(F9) -> 9 | D9: IGREJA DO EVANGELHO QUADRANGULAR | E9: 349 | F9: 62.955.505/0847-51 | G9: neivaldocastro@hotmail.com | H9: 10/1548741-6 | I9: BT | J9: monofasico | K9: GIROSSOL II | M9: 0.25 | Q9: =IF(_xlfn.MINIFS('Detalhe Por UC'!R:R,'Detalhe Por UC'!C:C,B9,'Detalhe Por UC'!AD:AD,">"&0)=0,"",_xlfn.MINIFS('Detalhe Por UC'!R:R,'Detalhe Por UC'!C:C,B9,'Detalhe Por UC'!AD:AD,">"&0)) -> 45627 | R9: =IF(P9<>"ATIVO",0, IF(OR(Q9="",Q9=0,O9=0),O9, O9-ROUND((MAX('Detalhe Por UC'!R:R) -Q9)/(365/12),0))) -> 0 | T9: 156.25 | U9: =IFERROR((SUMIFS(W9:CN9,$W$2:$CN$2,">"&$Q$1-365,$W$2:$CN$2,"<="&$Q$1)/COUNTIFS(W9:CN9,">="&0,$W$2:$CN$2,">"&$Q$1-365,$W$2:$CN$2,"<="&$Q$1)),"") -> 152.91667 | W9: 179 | X9: 221 | Y9: 202 | Z9: 159 | AA9: 173 | AB9: 154 | AC9: 151 | AD9: 144 | AE9: 136 | AF9: 128 | AG9: 155 | AH9: 146 | AI9: 156 | AJ9: =IF(SUMIFS('Detalhe Por UC'!$AB:$AB,'Detalhe Por UC'!$C:$C,'Infos Clientes'!$B9,'Detalhe Por UC'!$R:$R,'Infos Clientes'!AJ$2)=0,"", SUMIFS('Detalhe Por UC'!$AB:$AB,'Detalhe Por UC'!$C:$C,'Infos Clientes'!$B9,'Detalhe Por UC'!$R:$R,'Infos Clientes'!AJ$2) +SUMIFS('Detalhe Por UC'!$AC:$AC,'Detalhe Por UC'!$C:$C,'Infos Clientes'!$B9,'Detalhe Por UC'!$R:$R,'Infos Clientes'!AJ$2)) -> 171 | AK9: =IF(SUMIFS('Detalhe Por UC'!$AB:$AB,'Detalhe Por UC'!$C:$C,'Infos Clientes'!$B9,'Detalhe Por UC'!$R:$R,'Infos Clientes'!AK$2)=0,"", SUMIFS('Detalhe Por UC'!$AB:$AB,'Detalhe Por UC'!$C:$C,'Infos Clientes'!$B9,'Detalhe Por UC'!$R:$R,'Infos Clientes'!AK$2) +SUMIFS('Detalhe Por UC'!$AC:$AC,'Detalhe Por UC'!$C:$C,'Infos Clientes'!$B9,'Detalhe Por UC'!$R:$R,'Infos Clientes'!AK$2)) -> 172 | AL9: =IF(SUMIFS('Detalhe Por UC'!$AB:$AB,'Detalhe Por UC'!$C:$C,'Infos Clientes'!$B9,'Detalhe Por UC'!$R:$R,'Infos Clientes'!AL$2)=0,"", SUMIFS('Detalhe Por UC'!$AB:$AB,'Detalhe Por UC'!$C:$C,'Infos Clientes'!$B9,'Detalhe Por UC'!$R:$R,'Infos Clientes'!AL$2) +SUMIFS('Detalhe Por UC'!$AC:$AC,'Detalhe Por UC'!$C:$C,'Infos Clientes'!$B9,'Detalhe Por UC'!$R:$R,'Infos Clientes'!AL$2)) -> 153 | AM9: =IF(SUMIFS('Detalhe Por UC'!$AB:$AB,'Detalhe Por UC'!$C:$C,'Infos Clientes'!$B9,'Detalhe Por UC'!$R:$R,'Infos Clientes'!AM$2)=0,"", SUMIFS('Detalhe Por UC'!$AB:$AB,'Detalhe Por UC'!$C:$C,'Infos Clientes'!$B9,'Detalhe Por UC'!$R:$R,'Infos Clientes'!AM$2) +SUMIFS('Detalhe Por UC'!$AC:$AC,'Detalhe Por UC'!$C:$C,'Infos Clientes'!$B9,'Detalhe Por UC'!$R:$R,'Infos Clientes'!AM$2)) -> 179 | AN9: =IF(SUMIFS('Detalhe Por UC'!$AB:$AB,'Detalhe Por UC'!$C:$C,'Infos Clientes'!$B9,'Detalhe Por UC'!$R:$R,'Infos Clientes'!AN$2)=0,"", SUMIFS('Detalhe Por UC'!$AB:$AB,'Detalhe Por UC'!$C:$C,'Infos Clientes'!$B9,'Detalhe Por UC'!$R:$R,'Infos Clientes'!AN$2) +SUMIFS('Detalhe Por UC'!$AC:$AC,'Detalhe Por UC'!$C:$C,'Infos Clientes'!$B9,'Detalhe Por UC'!$R:$R,'Infos Clientes'!AN$2)) -> 153 | AO9: =IF(SUMIFS('Detalhe Por UC'!$AB:$AB,'Detalhe Por UC'!$C:$C,'Infos Clientes'!$B9,'Detalhe Por UC'!$R:$R,'Infos Clientes'!AO$2)=0,"", SUMIFS('Detalhe Por UC'!$AB:$AB,'Detalhe Por UC'!$C:$C,'Infos Clientes'!$B9,'Detalhe Por UC'!$R:$R,'Infos Clientes'!AO$2) +SUMIFS('Detalhe Por UC'!$AC:$AC,'Detalhe Por UC'!$C:$C,'Infos Clientes'!$B9,'Detalhe Por UC'!$R:$R,'Infos Clientes'!AO$2)) -> 126 | AP9: =IF(SUMIFS('Detalhe Por UC'!$AB:$AB,'Detalhe Por UC'!$C:$C,'Infos Clientes'!$B9,'Detalhe Por UC'!$R:$R,'Infos Clientes'!AP$2)=0,"", SUMIFS('Detalhe Por UC'!$AB:$AB,'Detalhe Por UC'!$C:$C,'Infos Clientes'!$B9,'Detalhe Por UC'!$R:$R,'Infos Clientes'!AP$2) +SUMIFS('Detalhe Por UC'!$AC:$AC,'Detalhe Por UC'!$C:$C,'Infos Clientes'!$B9,'Detalhe Por UC'!$R:$R,'Infos Clientes'!AP$2)) -> 116 | AQ9: =IF(SUMIFS('Detalhe Por UC'!$AB:$AB,'Detalhe Por UC'!$C:$C,'Infos Clientes'!$B9,'Detalhe Por UC'!$R:$R,'Infos Clientes'!AQ$2)=0,"", SUMIFS('Detalhe Por UC'!$AB:$AB,'Detalhe Por UC'!$C:$C,'Infos Clientes'!$B9,'Detalhe Por UC'!$R:$R,'Infos Clientes'!AQ$2) +SUMIFS('Detalhe Por UC'!$AC:$AC,'Detalhe Por UC'!$C:$C,'Infos Clientes'!$B9,'Detalhe Por UC'!$R:$R,'Infos Clientes'!AQ$2)) -> 98 | ... AU9: =IF(SUMIFS('Detalhe Por UC'!$AB:$AB,'Detalhe Por UC'!$C:$C,'Infos Clientes'!$B9,'Detalhe Por UC'!$R:$R,'Infos Clientes'!AU$2)=0,"", SUMIFS('Detalhe Por UC'!$AB:$AB,'Detalhe Por UC'!$C:$C,'Infos Clientes'!$B9,'Detalhe Por UC'!$R:$R,'Infos Clientes'!AU$2) +SUMIFS('Detalhe Por UC'!$AC:$AC,'Detalhe Por UC'!$C:$C,'Infos Clientes'!$B9,'Detalhe Por UC'!$R:$R,'Infos Clientes'!AU$2))
B10: 10/156956-5 | C10: =ROW(F10) -> 10 | D10: IGREJA DO EVANGELHO QUADRANGULAR | E10: 994 | F10: 62.955.505/0153-50 | G10: quadrangular994@gmail.com | H10: 10/156956-5 | I10: BT | J10: trifasico | K10: GIROSSOL II | M10: 0.25 | Q10: =IF(_xlfn.MINIFS('Detalhe Por UC'!R:R,'Detalhe Por UC'!C:C,B10,'Detalhe Por UC'!AD:AD,">"&0)=0,"",_xlfn.MINIFS('Detalhe Por UC'!R:R,'Detalhe Por UC'!C:C,B10,'Detalhe Por UC'!AD:AD,">"&0)) -> 45627 | R10: =IF(P10<>"ATIVO",0, IF(OR(Q10="",Q10=0,O10=0),O10, O10-ROUND((MAX('Detalhe Por UC'!R:R) -Q10)/(365/12),0))) -> 0 | T10: 362.41667 | U10: =IFERROR((SUMIFS(W10:CN10,$W$2:$CN$2,">"&$Q$1-365,$W$2:$CN$2,"<="&$Q$1)/COUNTIFS(W10:CN10,">="&0,$W$2:$CN$2,">"&$Q$1-365,$W$2:$CN$2,"<="&$Q$1)),"") -> 321.16667 | W10: 393 | X10: 453 | Y10: 419 | Z10: 472 | AA10: 554 | AB10: 456 | AC10: 201 | AD10: 168 | AE10: 172 | AF10: 305 | AG10: 370 | AH10: 345 | AI10: 491 | AJ10: =IF(SUMIFS('Detalhe Por UC'!$AB:$AB,'Detalhe Por UC'!$C:$C,'Infos Clientes'!$B10,'Detalhe Por UC'!$R:$R,'Infos Clientes'!AJ$2)=0,"", SUMIFS('Detalhe Por UC'!$AB:$AB,'Detalhe Por UC'!$C:$C,'Infos Clientes'!$B10,'Detalhe Por UC'!$R:$R,'Infos Clientes'!AJ$2) +SUMIFS('Detalhe Por UC'!$AC:$AC,'Detalhe Por UC'!$C:$C,'Infos Clientes'!$B10,'Detalhe Por UC'!$R:$R,'Infos Clientes'!AJ$2)) -> 396 | AK10: =IF(SUMIFS('Detalhe Por UC'!$AB:$AB,'Detalhe Por UC'!$C:$C,'Infos Clientes'!$B10,'Detalhe Por UC'!$R:$R,'Infos Clientes'!AK$2)=0,"", SUMIFS('Detalhe Por UC'!$AB:$AB,'Detalhe Por UC'!$C:$C,'Infos Clientes'!$B10,'Detalhe Por UC'!$R:$R,'Infos Clientes'!AK$2) +SUMIFS('Detalhe Por UC'!$AC:$AC,'Detalhe Por UC'!$C:$C,'Infos Clientes'!$B10,'Detalhe Por UC'!$R:$R,'Infos Clientes'!AK$2)) -> 490 | AL10: =IF(SUMIFS('Detalhe Por UC'!$AB:$AB,'Detalhe Por UC'!$C:$C,'Infos Clientes'!$B10,'Detalhe Por UC'!$R:$R,'Infos Clientes'!AL$2)=0,"", SUMIFS('Detalhe Por UC'!$AB:$AB,'Detalhe Por UC'!$C:$C,'Infos Clientes'!$B10,'Detalhe Por UC'!$R:$R,'Infos Clientes'!AL$2) +SUMIFS('Detalhe Por UC'!$AC:$AC,'Detalhe Por UC'!$C:$C,'Infos Clientes'!$B10,'Detalhe Por UC'!$R:$R,'Infos Clientes'!AL$2)) -> 489 | AM10: =IF(SUMIFS('Detalhe Por UC'!$AB:$AB,'Detalhe Por UC'!$C:$C,'Infos Clientes'!$B10,'Detalhe Por UC'!$R:$R,'Infos Clientes'!AM$2)=0,"", SUMIFS('Detalhe Por UC'!$AB:$AB,'Detalhe Por UC'!$C:$C,'Infos Clientes'!$B10,'Detalhe Por UC'!$R:$R,'Infos Clientes'!AM$2) +SUMIFS('Detalhe Por UC'!$AC:$AC,'Detalhe Por UC'!$C:$C,'Infos Clientes'!$B10,'Detalhe Por UC'!$R:$R,'Infos Clientes'!AM$2)) -> 312 | AN10: =IF(SUMIFS('Detalhe Por UC'!$AB:$AB,'Detalhe Por UC'!$C:$C,'Infos Clientes'!$B10,'Detalhe Por UC'!$R:$R,'Infos Clientes'!AN$2)=0,"", SUMIFS('Detalhe Por UC'!$AB:$AB,'Detalhe Por UC'!$C:$C,'Infos Clientes'!$B10,'Detalhe Por UC'!$R:$R,'Infos Clientes'!AN$2) +SUMIFS('Detalhe Por UC'!$AC:$AC,'Detalhe Por UC'!$C:$C,'Infos Clientes'!$B10,'Detalhe Por UC'!$R:$R,'Infos Clientes'!AN$2)) -> 276 | AO10: =IF(SUMIFS('Detalhe Por UC'!$AB:$AB,'Detalhe Por UC'!$C:$C,'Infos Clientes'!$B10,'Detalhe Por UC'!$R:$R,'Infos Clientes'!AO$2)=0,"", SUMIFS('Detalhe Por UC'!$AB:$AB,'Detalhe Por UC'!$C:$C,'Infos Clientes'!$B10,'Detalhe Por UC'!$R:$R,'Infos Clientes'!AO$2) +SUMIFS('Detalhe Por UC'!$AC:$AC,'Detalhe Por UC'!$C:$C,'Infos Clientes'!$B10,'Detalhe Por UC'!$R:$R,'Infos Clientes'!AO$2)) -> 189 | AP10: =IF(SUMIFS('Detalhe Por UC'!$AB:$AB,'Detalhe Por UC'!$C:$C,'Infos Clientes'!$B10,'Detalhe Por UC'!$R:$R,'Infos Clientes'!AP$2)=0,"", SUMIFS('Detalhe Por UC'!$AB:$AB,'Detalhe Por UC'!$C:$C,'Infos Clientes'!$B10,'Detalhe Por UC'!$R:$R,'Infos Clientes'!AP$2) +SUMIFS('Detalhe Por UC'!$AC:$AC,'Detalhe Por UC'!$C:$C,'Infos Clientes'!$B10,'Detalhe Por UC'!$R:$R,'Infos Clientes'!AP$2)) -> 154 | AQ10: =IF(SUMIFS('Detalhe Por UC'!$AB:$AB,'Detalhe Por UC'!$C:$C,'Infos Clientes'!$B10,'Detalhe Por UC'!$R:$R,'Infos Clientes'!AQ$2)=0,"", SUMIFS('Detalhe Por UC'!$AB:$AB,'Detalhe Por UC'!$C:$C,'Infos Clientes'!$B10,'Detalhe Por UC'!$R:$R,'Infos Clientes'!AQ$2) +SUMIFS('Detalhe Por UC'!$AC:$AC,'Detalhe Por UC'!$C:$C,'Infos Clientes'!$B10,'Detalhe Por UC'!$R:$R,'Infos Clientes'!AQ$2)) -> 200 | ... AU10: =IF(SUMIFS('Detalhe Por UC'!$AB:$AB,'Detalhe Por UC'!$C:$C,'Infos Clientes'!$B10,'Detalhe Por UC'!$R:$R,'Infos Clientes'!AU$2)=0,"", SUMIFS('Detalhe Por UC'!$AB:$AB,'Detalhe Por UC'!$C:$C,'Infos Clientes'!$B10,'Detalhe Por UC'!$R:$R,'Infos Clientes'!AU$2) +SUMIFS('Detalhe Por UC'!$AC:$AC,'Detalhe Por UC'!$C:$C,'Infos Clientes'!$B10,'Detalhe Por UC'!$R:$R,'Infos Clientes'!AU$2))
B11: 10/2794432-1 | C11: =ROW(F11) -> 11 | D11: IGREJA DO EVANGELHO QUADRANGULAR | E11: 306 | F11: 62.955.505/0151-99 | G11: carlaestreito@hotmail.com | H11: 10/2794432-1 | I11: BT | J11: trifasico | K11: GIROSSOL II | M11: 0.25 | Q11: =IF(_xlfn.MINIFS('Detalhe Por UC'!R:R,'Detalhe Por UC'!C:C,B11,'Detalhe Por UC'!AD:AD,">"&0)=0,"",_xlfn.MINIFS('Detalhe Por UC'!R:R,'Detalhe Por UC'!C:C,B11,'Detalhe Por UC'!AD:AD,">"&0)) -> 45658 | R11: =IF(P11<>"ATIVO",0, IF(OR(Q11="",Q11=0,O11=0),O11, O11-ROUND((MAX('Detalhe Por UC'!R:R) -Q11)/(365/12),0))) -> 0 | T11: 286.5 | U11: =IFERROR((SUMIFS(W11:CN11,$W$2:$CN$2,">"&$Q$1-365,$W$2:$CN$2,"<="&$Q$1)/COUNTIFS(W11:CN11,">="&0,$W$2:$CN$2,">"&$Q$1-365,$W$2:$CN$2,"<="&$Q$1)),"") -> 494.83333 | W11: 0 | X11: 0 | Y11: 0 | Z11: 132 | AA11: 131 | AB11: 160 | AC11: 136 | AD11: 88 | AE11: 221 | AF11: 390 | AG11: 551 | AH11: 533 | AI11: 601 | AJ11: =IF(SUMIFS('Detalhe Por UC'!$AB:$AB,'Detalhe Por UC'!$C:$C,'Infos Clientes'!$B11,'Detalhe Por UC'!$R:$R,'Infos Clientes'!AJ$2)=0,"", SUMIFS('Detalhe Por UC'!$AB:$AB,'Detalhe Por UC'!$C:$C,'Infos Clientes'!$B11,'Detalhe Por UC'!$R:$R,'Infos Clientes'!AJ$2) +SUMIFS('Detalhe Por UC'!$AC:$AC,'Detalhe Por UC'!$C:$C,'Infos Clientes'!$B11,'Detalhe Por UC'!$R:$R,'Infos Clientes'!AJ$2)) -> 495 | AK11: =IF(SUMIFS('Detalhe Por UC'!$AB:$AB,'Detalhe Por UC'!$C:$C,'Infos Clientes'!$B11,'Detalhe Por UC'!$R:$R,'Infos Clientes'!AK$2)=0,"", SUMIFS('Detalhe Por UC'!$AB:$AB,'Detalhe Por UC'!$C:$C,'Infos Clientes'!$B11,'Detalhe Por UC'!$R:$R,'Infos Clientes'!AK$2) +SUMIFS('Detalhe Por UC'!$AC:$AC,'Detalhe Por UC'!$C:$C,'Infos Clientes'!$B11,'Detalhe Por UC'!$R:$R,'Infos Clientes'!AK$2)) -> 479 | AL11: =IF(SUMIFS('Detalhe Por UC'!$AB:$AB,'Detalhe Por UC'!$C:$C,'Infos Clientes'!$B11,'Detalhe Por UC'!$R:$R,'Infos Clientes'!AL$2)=0,"", SUMIFS('Detalhe Por UC'!$AB:$AB,'Detalhe Por UC'!$C:$C,'Infos Clientes'!$B11,'Detalhe Por UC'!$R:$R,'Infos Clientes'!AL$2) +SUMIFS('Detalhe Por UC'!$AC:$AC,'Detalhe Por UC'!$C:$C,'Infos Clientes'!$B11,'Detalhe Por UC'!$R:$R,'Infos Clientes'!AL$2)) -> 713 | AM11: =IF(SUMIFS('Detalhe Por UC'!$AB:$AB,'Detalhe Por UC'!$C:$C,'Infos Clientes'!$B11,'Detalhe Por UC'!$R:$R,'Infos Clientes'!AM$2)=0,"", SUMIFS('Detalhe Por UC'!$AB:$AB,'Detalhe Por UC'!$C:$C,'Infos Clientes'!$B11,'Detalhe Por UC'!$R:$R,'Infos Clientes'!AM$2) +SUMIFS('Detalhe Por UC'!$AC:$AC,'Detalhe Por UC'!$C:$C,'Infos Clientes'!$B11,'Detalhe Por UC'!$R:$R,'Infos Clientes'!AM$2)) -> 385 | AN11: =IF(SUMIFS('Detalhe Por UC'!$AB:$AB,'Detalhe Por UC'!$C:$C,'Infos Clientes'!$B11,'Detalhe Por UC'!$R:$R,'Infos Clientes'!AN$2)=0,"", SUMIFS('Detalhe Por UC'!$AB:$AB,'Detalhe Por UC'!$C:$C,'Infos Clientes'!$B11,'Detalhe Por UC'!$R:$R,'Infos Clientes'!AN$2) +SUMIFS('Detalhe Por UC'!$AC:$AC,'Detalhe Por UC'!$C:$C,'Infos Clientes'!$B11,'Detalhe Por UC'!$R:$R,'Infos Clientes'!AN$2)) -> 484 | AO11: =IF(SUMIFS('Detalhe Por UC'!$AB:$AB,'Detalhe Por UC'!$C:$C,'Infos Clientes'!$B11,'Detalhe Por UC'!$R:$R,'Infos Clientes'!AO$2)=0,"", SUMIFS('Detalhe Por UC'!$AB:$AB,'Detalhe Por UC'!$C:$C,'Infos Clientes'!$B11,'Detalhe Por UC'!$R:$R,'Infos Clientes'!AO$2) +SUMIFS('Detalhe Por UC'!$AC:$AC,'Detalhe Por UC'!$C:$C,'Infos Clientes'!$B11,'Detalhe Por UC'!$R:$R,'Infos Clientes'!AO$2)) -> 592 | AP11: =IF(SUMIFS('Detalhe Por UC'!$AB:$AB,'Detalhe Por UC'!$C:$C,'Infos Clientes'!$B11,'Detalhe Por UC'!$R:$R,'Infos Clientes'!AP$2)=0,"", SUMIFS('Detalhe Por UC'!$AB:$AB,'Detalhe Por UC'!$C:$C,'Infos Clientes'!$B11,'Detalhe Por UC'!$R:$R,'Infos Clientes'!AP$2) +SUMIFS('Detalhe Por UC'!$AC:$AC,'Detalhe Por UC'!$C:$C,'Infos Clientes'!$B11,'Detalhe Por UC'!$R:$R,'Infos Clientes'!AP$2)) -> 299 | AQ11: =IF(SUMIFS('Detalhe Por UC'!$AB:$AB,'Detalhe Por UC'!$C:$C,'Infos Clientes'!$B11,'Detalhe Por UC'!$R:$R,'Infos Clientes'!AQ$2)=0,"", SUMIFS('Detalhe Por UC'!$AB:$AB,'Detalhe Por UC'!$C:$C,'Infos Clientes'!$B11,'Detalhe Por UC'!$R:$R,'Infos Clientes'!AQ$2) +SUMIFS('Detalhe Por UC'!$AC:$AC,'Detalhe Por UC'!$C:$C,'Infos Clientes'!$B11,'Detalhe Por UC'!$R:$R,'Infos Clientes'!AQ$2)) -> 491 | ... AU11: =IF(SUMIFS('Detalhe Por UC'!$AB:$AB,'Detalhe Por UC'!$C:$C,'Infos Clientes'!$B11,'Detalhe Por UC'!$R:$R,'Infos Clientes'!AU$2)=0,"", SUMIFS('Detalhe Por UC'!$AB:$AB,'Detalhe Por UC'!$C:$C,'Infos Clientes'!$B11,'Detalhe Por UC'!$R:$R,'Infos Clientes'!AU$2) +SUMIFS('Detalhe Por UC'!$AC:$AC,'Detalhe Por UC'!$C:$C,'Infos Clientes'!$B11,'Detalhe Por UC'!$R:$R,'Infos Clientes'!AU$2))
B12: 10/162736-3 | C12: =ROW(F12) -> 12 | D12: IGREJA DO EVANGELHO QUADRANGULAR | E12: 360 | F12: 62.955.505/1973-60 | G12: gelcimarsouza1220@gmail.com | H12: 10/162736-3 | I12: BT | J12: trifasico | K12: GIROSSOL II | M12: 0.25 | Q12: =IF(_xlfn.MINIFS('Detalhe Por UC'!R:R,'Detalhe Por UC'!C:C,B12,'Detalhe Por UC'!AD:AD,">"&0)=0,"",_xlfn.MINIFS('Detalhe Por UC'!R:R,'Detalhe Por UC'!C:C,B12,'Detalhe Por UC'!AD:AD,">"&0)) -> 45627 | R12: =IF(P12<>"ATIVO",0, IF(OR(Q12="",Q12=0,O12=0),O12, O12-ROUND((MAX('Detalhe Por UC'!R:R) -Q12)/(365/12),0))) -> 0 | T12: 185.66667 | U12: =IFERROR((SUMIFS(W12:CN12,$W$2:$CN$2,">"&$Q$1-365,$W$2:$CN$2,"<="&$Q$1)/COUNTIFS(W12:CN12,">="&0,$W$2:$CN$2,">"&$Q$1-365,$W$2:$CN$2,"<="&$Q$1)),"") -> 299.4 | W12: 166 | X12: 295 | Y12: 180 | Z12: 195 | AA12: 251 | AB12: 157 | AC12: 114 | AD12: 89 | AE12: 97 | AF12: 139 | AG12: 255 | AH12: 184 | AI12: 235 | AJ12: =IF(SUMIFS('Detalhe Por UC'!$AB:$AB,'Detalhe Por UC'!$C:$C,'Infos Clientes'!$B12,'Detalhe Por UC'!$R:$R,'Infos Clientes'!AJ$2)=0,"", SUMIFS('Detalhe Por UC'!$AB:$AB,'Detalhe Por UC'!$C:$C,'Infos Clientes'!$B12,'Detalhe Por UC'!$R:$R,'Infos Clientes'!AJ$2) +SUMIFS('Detalhe Por UC'!$AC:$AC,'Detalhe Por UC'!$C:$C,'Infos Clientes'!$B12,'Detalhe Por UC'!$R:$R,'Infos Clientes'!AJ$2)) -> 332 | AK12: =IF(SUMIFS('Detalhe Por UC'!$AB:$AB,'Detalhe Por UC'!$C:$C,'Infos Clientes'!$B12,'Detalhe Por UC'!$R:$R,'Infos Clientes'!AK$2)=0,"", SUMIFS('Detalhe Por UC'!$AB:$AB,'Detalhe Por UC'!$C:$C,'Infos Clientes'!$B12,'Detalhe Por UC'!$R:$R,'Infos Clientes'!AK$2) +SUMIFS('Detalhe Por UC'!$AC:$AC,'Detalhe Por UC'!$C:$C,'Infos Clientes'!$B12,'Detalhe Por UC'!$R:$R,'Infos Clientes'!AK$2)) -> 472 | AL12: =IF(SUMIFS('Detalhe Por UC'!$AB:$AB,'Detalhe Por UC'!$C:$C,'Infos Clientes'!$B12,'Detalhe Por UC'!$R:$R,'Infos Clientes'!AL$2)=0,"", SUMIFS('Detalhe Por UC'!$AB:$AB,'Detalhe Por UC'!$C:$C,'Infos Clientes'!$B12,'Detalhe Por UC'!$R:$R,'Infos Clientes'!AL$2) +SUMIFS('Detalhe Por UC'!$AC:$AC,'Detalhe Por UC'!$C:$C,'Infos Clientes'!$B12,'Detalhe Por UC'!$R:$R,'Infos Clientes'!AL$2)) -> 477 | AM12: =IF(SUMIFS('Detalhe Por UC'!$AB:$AB,'Detalhe Por UC'!$C:$C,'Infos Clientes'!$B12,'Detalhe Por UC'!$R:$R,'Infos Clientes'!AM$2)=0,"", SUMIFS('Detalhe Por UC'!$AB:$AB,'Detalhe Por UC'!$C:$C,'Infos Clientes'!$B12,'Detalhe Por UC'!$R:$R,'Infos Clientes'!AM$2) +SUMIFS('Detalhe Por UC'!$AC:$AC,'Detalhe Por UC'!$C:$C,'Infos Clientes'!$B12,'Detalhe Por UC'!$R:$R,'Infos Clientes'!AM$2)) -> 343 | AN12: =IF(SUMIFS('Detalhe Por UC'!$AB:$AB,'Detalhe Por UC'!$C:$C,'Infos Clientes'!$B12,'Detalhe Por UC'!$R:$R,'Infos Clientes'!AN$2)=0,"", SUMIFS('Detalhe Por UC'!$AB:$AB,'Detalhe Por UC'!$C:$C,'Infos Clientes'!$B12,'Detalhe Por UC'!$R:$R,'Infos Clientes'!AN$2) +SUMIFS('Detalhe Por UC'!$AC:$AC,'Detalhe Por UC'!$C:$C,'Infos Clientes'!$B12,'Detalhe Por UC'!$R:$R,'Infos Clientes'!AN$2)) -> 314 | AO12: =IF(SUMIFS('Detalhe Por UC'!$AB:$AB,'Detalhe Por UC'!$C:$C,'Infos Clientes'!$B12,'Detalhe Por UC'!$R:$R,'Infos Clientes'!AO$2)=0,"", SUMIFS('Detalhe Por UC'!$AB:$AB,'Detalhe Por UC'!$C:$C,'Infos Clientes'!$B12,'Detalhe Por UC'!$R:$R,'Infos Clientes'!AO$2) +SUMIFS('Detalhe Por UC'!$AC:$AC,'Detalhe Por UC'!$C:$C,'Infos Clientes'!$B12,'Detalhe Por UC'!$R:$R,'Infos Clientes'!AO$2)) -> 148 | AP12: =IF(SUMIFS('Detalhe Por UC'!$AB:$AB,'Detalhe Por UC'!$C:$C,'Infos Clientes'!$B12,'Detalhe Por UC'!$R:$R,'Infos Clientes'!AP$2)=0,"", SUMIFS('Detalhe Por UC'!$AB:$AB,'Detalhe Por UC'!$C:$C,'Infos Clientes'!$B12,'Detalhe Por UC'!$R:$R,'Infos Clientes'!AP$2) +SUMIFS('Detalhe Por UC'!$AC:$AC,'Detalhe Por UC'!$C:$C,'Infos Clientes'!$B12,'Detalhe Por UC'!$R:$R,'Infos Clientes'!AP$2)) | AQ12: =IF(SUMIFS('Detalhe Por UC'!$AB:$AB,'Detalhe Por UC'!$C:$C,'Infos Clientes'!$B12,'Detalhe Por UC'!$R:$R,'Infos Clientes'!AQ$2)=0,"", SUMIFS('Detalhe Por UC'!$AB:$AB,'Detalhe Por UC'!$C:$C,'Infos Clientes'!$B12,'Detalhe Por UC'!$R:$R,'Infos Clientes'!AQ$2) +SUMIFS('Detalhe Por UC'!$AC:$AC,'Detalhe Por UC'!$C:$C,'Infos Clientes'!$B12,'Detalhe Por UC'!$R:$R,'Infos Clientes'!AQ$2)) | ... AU12: =IF(SUMIFS('Detalhe Por UC'!$AB:$AB,'Detalhe Por UC'!$C:$C,'Infos Clientes'!$B12,'Detalhe Por UC'!$R:$R,'Infos Clientes'!AU$2)=0,"", SUMIFS('Detalhe Por UC'!$AB:$AB,'Detalhe Por UC'!$C:$C,'Infos Clientes'!$B12,'Detalhe Por UC'!$R:$R,'Infos Clientes'!AU$2) +SUMIFS('Detalhe Por UC'!$AC:$AC,'Detalhe Por UC'!$C:$C,'Infos Clientes'!$B12,'Detalhe Por UC'!$R:$R,'Infos Clientes'!AU$2))
B13: 10/1672452-8 | C13: =ROW(F13) -> 13 | D13: IGREJA DO EVANGELHO QUADRANGULAR | E13: 371 | F13: 62.955.505/0172-13 | G13: regiao371@gmail.com | H13: 10/1672452-8 | I13: BT | J13: trifasico | K13: GIROSSOL II | M13: 0.25 | Q13: =IF(_xlfn.MINIFS('Detalhe Por UC'!R:R,'Detalhe Por UC'!C:C,B13,'Detalhe Por UC'!AD:AD,">"&0)=0,"",_xlfn.MINIFS('Detalhe Por UC'!R:R,'Detalhe Por UC'!C:C,B13,'Detalhe Por UC'!AD:AD,">"&0)) -> 45627 | R13: =IF(P13<>"ATIVO",0, IF(OR(Q13="",Q13=0,O13=0),O13, O13-ROUND((MAX('Detalhe Por UC'!R:R) -Q13)/(365/12),0))) -> 0 | T13: 418.16667 | U13: =IFERROR((SUMIFS(W13:CN13,$W$2:$CN$2,">"&$Q$1-365,$W$2:$CN$2,"<="&$Q$1)/COUNTIFS(W13:CN13,">="&0,$W$2:$CN$2,">"&$Q$1-365,$W$2:$CN$2,"<="&$Q$1)),"") -> 379 | W13: 1396 | X13: 1383 | Y13: 864 | Z13: 558 | AA13: 592 | AB13: 554 | AC13: 290 | AD13: 251 | AE13: 291 | AF13: 263 | AG13: 358 | AH13: 301 | AI13: 377 | AJ13: =IF(SUMIFS('Detalhe Por UC'!$AB:$AB,'Detalhe Por UC'!$C:$C,'Infos Clientes'!$B13,'Detalhe Por UC'!$R:$R,'Infos Clientes'!AJ$2)=0,"", SUMIFS('Detalhe Por UC'!$AB:$AB,'Detalhe Por UC'!$C:$C,'Infos Clientes'!$B13,'Detalhe Por UC'!$R:$R,'Infos Clientes'!AJ$2) +SUMIFS('Detalhe Por UC'!$AC:$AC,'Detalhe Por UC'!$C:$C,'Infos Clientes'!$B13,'Detalhe Por UC'!$R:$R,'Infos Clientes'!AJ$2)) -> 319 | AK13: =IF(SUMIFS('Detalhe Por UC'!$AB:$AB,'Detalhe Por UC'!$C:$C,'Infos Clientes'!$B13,'Detalhe Por UC'!$R:$R,'Infos Clientes'!AK$2)=0,"", SUMIFS('Detalhe Por UC'!$AB:$AB,'Detalhe Por UC'!$C:$C,'Infos Clientes'!$B13,'Detalhe Por UC'!$R:$R,'Infos Clientes'!AK$2) +SUMIFS('Detalhe Por UC'!$AC:$AC,'Detalhe Por UC'!$C:$C,'Infos Clientes'!$B13,'Detalhe Por UC'!$R:$R,'Infos Clientes'!AK$2)) -> 564 | AL13: =IF(SUMIFS('Detalhe Por UC'!$AB:$AB,'Detalhe Por UC'!$C:$C,'Infos Clientes'!$B13,'Detalhe Por UC'!$R:$R,'Infos Clientes'!AL$2)=0,"", SUMIFS('Detalhe Por UC'!$AB:$AB,'Detalhe Por UC'!$C:$C,'Infos Clientes'!$B13,'Detalhe Por UC'!$R:$R,'Infos Clientes'!AL$2) +SUMIFS('Detalhe Por UC'!$AC:$AC,'Detalhe Por UC'!$C:$C,'Infos Clientes'!$B13,'Detalhe Por UC'!$R:$R,'Infos Clientes'!AL$2)) -> 476 | AM13: =IF(SUMIFS('Detalhe Por UC'!$AB:$AB,'Detalhe Por UC'!$C:$C,'Infos Clientes'!$B13,'Detalhe Por UC'!$R:$R,'Infos Clientes'!AM$2)=0,"", SUMIFS('Detalhe Por UC'!$AB:$AB,'Detalhe Por UC'!$C:$C,'Infos Clientes'!$B13,'Detalhe Por UC'!$R:$R,'Infos Clientes'!AM$2) +SUMIFS('Detalhe Por UC'!$AC:$AC,'Detalhe Por UC'!$C:$C,'Infos Clientes'!$B13,'Detalhe Por UC'!$R:$R,'Infos Clientes'!AM$2)) -> 523 | AN13: =IF(SUMIFS('Detalhe Por UC'!$AB:$AB,'Detalhe Por UC'!$C:$C,'Infos Clientes'!$B13,'Detalhe Por UC'!$R:$R,'Infos Clientes'!AN$2)=0,"", SUMIFS('Detalhe Por UC'!$AB:$AB,'Detalhe Por UC'!$C:$C,'Infos Clientes'!$B13,'Detalhe Por UC'!$R:$R,'Infos Clientes'!AN$2) +SUMIFS('Detalhe Por UC'!$AC:$AC,'Detalhe Por UC'!$C:$C,'Infos Clientes'!$B13,'Detalhe Por UC'!$R:$R,'Infos Clientes'!AN$2)) -> 456 | AO13: =IF(SUMIFS('Detalhe Por UC'!$AB:$AB,'Detalhe Por UC'!$C:$C,'Infos Clientes'!$B13,'Detalhe Por UC'!$R:$R,'Infos Clientes'!AO$2)=0,"", SUMIFS('Detalhe Por UC'!$AB:$AB,'Detalhe Por UC'!$C:$C,'Infos Clientes'!$B13,'Detalhe Por UC'!$R:$R,'Infos Clientes'!AO$2) +SUMIFS('Detalhe Por UC'!$AC:$AC,'Detalhe Por UC'!$C:$C,'Infos Clientes'!$B13,'Detalhe Por UC'!$R:$R,'Infos Clientes'!AO$2)) -> 283 | AP13: =IF(SUMIFS('Detalhe Por UC'!$AB:$AB,'Detalhe Por UC'!$C:$C,'Infos Clientes'!$B13,'Detalhe Por UC'!$R:$R,'Infos Clientes'!AP$2)=0,"", SUMIFS('Detalhe Por UC'!$AB:$AB,'Detalhe Por UC'!$C:$C,'Infos Clientes'!$B13,'Detalhe Por UC'!$R:$R,'Infos Clientes'!AP$2) +SUMIFS('Detalhe Por UC'!$AC:$AC,'Detalhe Por UC'!$C:$C,'Infos Clientes'!$B13,'Detalhe Por UC'!$R:$R,'Infos Clientes'!AP$2)) -> 164 | AQ13: =IF(SUMIFS('Detalhe Por UC'!$AB:$AB,'Detalhe Por UC'!$C:$C,'Infos Clientes'!$B13,'Detalhe Por UC'!$R:$R,'Infos Clientes'!AQ$2)=0,"", SUMIFS('Detalhe Por UC'!$AB:$AB,'Detalhe Por UC'!$C:$C,'Infos Clientes'!$B13,'Detalhe Por UC'!$R:$R,'Infos Clientes'!AQ$2) +SUMIFS('Detalhe Por UC'!$AC:$AC,'Detalhe Por UC'!$C:$C,'Infos Clientes'!$B13,'Detalhe Por UC'!$R:$R,'Infos Clientes'!AQ$2)) -> 197 | ... AU13: =IF(SUMIFS('Detalhe Por UC'!$AB:$AB,'Detalhe Por UC'!$C:$C,'Infos Clientes'!$B13,'Detalhe Por UC'!$R:$R,'Infos Clientes'!AU$2)=0,"", SUMIFS('Detalhe Por UC'!$AB:$AB,'Detalhe Por UC'!$C:$C,'Infos Clientes'!$B13,'Detalhe Por UC'!$R:$R,'Infos Clientes'!AU$2) +SUMIFS('Detalhe Por UC'!$AC:$AC,'Detalhe Por UC'!$C:$C,'Infos Clientes'!$B13,'Detalhe Por UC'!$R:$R,'Infos Clientes'!AU$2))
B14: 10/1695011-5 | C14: =ROW(F14) -> 14 | D14: IGREJA DO EVANGELHO QUADRANGULAR | E14: 306 | F14: 62.955.505/4612-10 | G14: prmarcelo.quadrangular@gmail.com | H14: 10/1695011-5 | I14: BT | J14: trifasico | K14: GIROSSOL II | M14: 0.25 | Q14: =IF(_xlfn.MINIFS('Detalhe Por UC'!R:R,'Detalhe Por UC'!C:C,B14,'Detalhe Por UC'!AD:AD,">"&0)=0,"",_xlfn.MINIFS('Detalhe Por UC'!R:R,'Detalhe Por UC'!C:C,B14,'Detalhe Por UC'!AD:AD,">"&0)) -> 45627 | R14: =IF(P14<>"ATIVO",0, IF(OR(Q14="",Q14=0,O14=0),O14, O14-ROUND((MAX('Detalhe Por UC'!R:R) -Q14)/(365/12),0))) -> 0 | T14: 511.41667 | U14: =IFERROR((SUMIFS(W14:CN14,$W$2:$CN$2,">"&$Q$1-365,$W$2:$CN$2,"<="&$Q$1)/COUNTIFS(W14:CN14,">="&0,$W$2:$CN$2,">"&$Q$1-365,$W$2:$CN$2,"<="&$Q$1)),"") -> 754.16667 | W14: 284 | X14: 290 | Y14: 169 | Z14: 340 | AA14: 274 | AB14: 260 | AC14: 283 | AD14: 441 | AE14: 428 | AF14: 565 | AG14: 866 | AH14: 786 | AI14: 892 | AJ14: =IF(SUMIFS('Detalhe Por UC'!$AB:$AB,'Detalhe Por UC'!$C:$C,'Infos Clientes'!$B14,'Detalhe Por UC'!$R:$R,'Infos Clientes'!AJ$2)=0,"", SUMIFS('Detalhe Por UC'!$AB:$AB,'Detalhe Por UC'!$C:$C,'Infos Clientes'!$B14,'Detalhe Por UC'!$R:$R,'Infos Clientes'!AJ$2) +SUMIFS('Detalhe Por UC'!$AC:$AC,'Detalhe Por UC'!$C:$C,'Infos Clientes'!$B14,'Detalhe Por UC'!$R:$R,'Infos Clientes'!AJ$2)) -> 833 | AK14: =IF(SUMIFS('Detalhe Por UC'!$AB:$AB,'Detalhe Por UC'!$C:$C,'Infos Clientes'!$B14,'Detalhe Por UC'!$R:$R,'Infos Clientes'!AK$2)=0,"", SUMIFS('Detalhe Por UC'!$AB:$AB,'Detalhe Por UC'!$C:$C,'Infos Clientes'!$B14,'Detalhe Por UC'!$R:$R,'Infos Clientes'!AK$2) +SUMIFS('Detalhe Por UC'!$AC:$AC,'Detalhe Por UC'!$C:$C,'Infos Clientes'!$B14,'Detalhe Por UC'!$R:$R,'Infos Clientes'!AK$2)) -> 930 | AL14: =IF(SUMIFS('Detalhe Por UC'!$AB:$AB,'Detalhe Por UC'!$C:$C,'Infos Clientes'!$B14,'Detalhe Por UC'!$R:$R,'Infos Clientes'!AL$2)=0,"", SUMIFS('Detalhe Por UC'!$AB:$AB,'Detalhe Por UC'!$C:$C,'Infos Clientes'!$B14,'Detalhe Por UC'!$R:$R,'Infos Clientes'!AL$2) +SUMIFS('Detalhe Por UC'!$AC:$AC,'Detalhe Por UC'!$C:$C,'Infos Clientes'!$B14,'Detalhe Por UC'!$R:$R,'Infos Clientes'!AL$2)) -> 873 | AM14: =IF(SUMIFS('Detalhe Por UC'!$AB:$AB,'Detalhe Por UC'!$C:$C,'Infos Clientes'!$B14,'Detalhe Por UC'!$R:$R,'Infos Clientes'!AM$2)=0,"", SUMIFS('Detalhe Por UC'!$AB:$AB,'Detalhe Por UC'!$C:$C,'Infos Clientes'!$B14,'Detalhe Por UC'!$R:$R,'Infos Clientes'!AM$2) +SUMIFS('Detalhe Por UC'!$AC:$AC,'Detalhe Por UC'!$C:$C,'Infos Clientes'!$B14,'Detalhe Por UC'!$R:$R,'Infos Clientes'!AM$2)) -> 885 | AN14: =IF(SUMIFS('Detalhe Por UC'!$AB:$AB,'Detalhe Por UC'!$C:$C,'Infos Clientes'!$B14,'Detalhe Por UC'!$R:$R,'Infos Clientes'!AN$2)=0,"", SUMIFS('Detalhe Por UC'!$AB:$AB,'Detalhe Por UC'!$C:$C,'Infos Clientes'!$B14,'Detalhe Por UC'!$R:$R,'Infos Clientes'!AN$2) +SUMIFS('Detalhe Por UC'!$AC:$AC,'Detalhe Por UC'!$C:$C,'Infos Clientes'!$B14,'Detalhe Por UC'!$R:$R,'Infos Clientes'!AN$2)) -> 758 | AO14: =IF(SUMIFS('Detalhe Por UC'!$AB:$AB,'Detalhe Por UC'!$C:$C,'Infos Clientes'!$B14,'Detalhe Por UC'!$R:$R,'Infos Clientes'!AO$2)=0,"", SUMIFS('Detalhe Por UC'!$AB:$AB,'Detalhe Por UC'!$C:$C,'Infos Clientes'!$B14,'Detalhe Por UC'!$R:$R,'Infos Clientes'!AO$2) +SUMIFS('Detalhe Por UC'!$AC:$AC,'Detalhe Por UC'!$C:$C,'Infos Clientes'!$B14,'Detalhe Por UC'!$R:$R,'Infos Clientes'!AO$2)) -> 599 | AP14: =IF(SUMIFS('Detalhe Por UC'!$AB:$AB,'Detalhe Por UC'!$C:$C,'Infos Clientes'!$B14,'Detalhe Por UC'!$R:$R,'Infos Clientes'!AP$2)=0,"", SUMIFS('Detalhe Por UC'!$AB:$AB,'Detalhe Por UC'!$C:$C,'Infos Clientes'!$B14,'Detalhe Por UC'!$R:$R,'Infos Clientes'!AP$2) +SUMIFS('Detalhe Por UC'!$AC:$AC,'Detalhe Por UC'!$C:$C,'Infos Clientes'!$B14,'Detalhe Por UC'!$R:$R,'Infos Clientes'!AP$2)) -> 548 | AQ14: =IF(SUMIFS('Detalhe Por UC'!$AB:$AB,'Detalhe Por UC'!$C:$C,'Infos Clientes'!$B14,'Detalhe Por UC'!$R:$R,'Infos Clientes'!AQ$2)=0,"", SUMIFS('Detalhe Por UC'!$AB:$AB,'Detalhe Por UC'!$C:$C,'Infos Clientes'!$B14,'Detalhe Por UC'!$R:$R,'Infos Clientes'!AQ$2) +SUMIFS('Detalhe Por UC'!$AC:$AC,'Detalhe Por UC'!$C:$C,'Infos Clientes'!$B14,'Detalhe Por UC'!$R:$R,'Infos Clientes'!AQ$2)) -> 538 | ... AU14: =IF(SUMIFS('Detalhe Por UC'!$AB:$AB,'Detalhe Por UC'!$C:$C,'Infos Clientes'!$B14,'Detalhe Por UC'!$R:$R,'Infos Clientes'!AU$2)=0,"", SUMIFS('Detalhe Por UC'!$AB:$AB,'Detalhe Por UC'!$C:$C,'Infos Clientes'!$B14,'Detalhe Por UC'!$R:$R,'Infos Clientes'!AU$2) +SUMIFS('Detalhe Por UC'!$AC:$AC,'Detalhe Por UC'!$C:$C,'Infos Clientes'!$B14,'Detalhe Por UC'!$R:$R,'Infos Clientes'!AU$2))
... B43: 10/987178-1 | C43: =ROW(F43) -> 43 | D43: IGREJA DO EVANGELHO QUADRANGULAR | E43: 358 | F43: 62.955.505/0155-12 | G43: lucianop.duarte@outlook.com | H43: 10/987178-1 | I43: BT | J43: trifasico | K43: GIROSSOL II | M43: 0.25 | Q43: =IF(_xlfn.MINIFS('Detalhe Por UC'!R:R,'Detalhe Por UC'!C:C,B43,'Detalhe Por UC'!AD:AD,">"&0)=0,"",_xlfn.MINIFS('Detalhe Por UC'!R:R,'Detalhe Por UC'!C:C,B43,'Detalhe Por UC'!AD:AD,">"&0)) -> 45627 | R43: =IF(P43<>"ATIVO",0, IF(OR(Q43="",Q43=0,O43=0),O43, O43-ROUND((MAX('Detalhe Por UC'!R:R) -Q43)/(365/12),0))) -> 0 | T43: 123.5 | U43: =IFERROR((SUMIFS(W43:CN43,$W$2:$CN$2,">"&$Q$1-365,$W$2:$CN$2,"<="&$Q$1)/COUNTIFS(W43:CN43,">="&0,$W$2:$CN$2,">"&$Q$1-365,$W$2:$CN$2,"<="&$Q$1)),"") -> 147.09091 | W43: 148 | X43: 145 | Y43: 151 | Z43: 176 | AA43: 185 | AB43: 144 | AC43: 88 | AD43: 83 | AE43: 116 | AF43: 75 | AG43: 97 | AH43: 120 | AI43: 135 | AJ43: =IF(SUMIFS('Detalhe Por UC'!$AB:$AB,'Detalhe Por UC'!$C:$C,'Infos Clientes'!$B43,'Detalhe Por UC'!$R:$R,'Infos Clientes'!AJ$2)=0,"", SUMIFS('Detalhe Por UC'!$AB:$AB,'Detalhe Por UC'!$C:$C,'Infos Clientes'!$B43,'Detalhe Por UC'!$R:$R,'Infos Clientes'!AJ$2) +SUMIFS('Detalhe Por UC'!$AC:$AC,'Detalhe Por UC'!$C:$C,'Infos Clientes'!$B43,'Detalhe Por UC'!$R:$R,'Infos Clientes'!AJ$2)) -> 112 | AK43: =IF(SUMIFS('Detalhe Por UC'!$AB:$AB,'Detalhe Por UC'!$C:$C,'Infos Clientes'!$B43,'Detalhe Por UC'!$R:$R,'Infos Clientes'!AK$2)=0,"", SUMIFS('Detalhe Por UC'!$AB:$AB,'Detalhe Por UC'!$C:$C,'Infos Clientes'!$B43,'Detalhe Por UC'!$R:$R,'Infos Clientes'!AK$2) +SUMIFS('Detalhe Por UC'!$AC:$AC,'Detalhe Por UC'!$C:$C,'Infos Clientes'!$B43,'Detalhe Por UC'!$R:$R,'Infos Clientes'!AK$2)) -> 110 | AL43: =IF(SUMIFS('Detalhe Por UC'!$AB:$AB,'Detalhe Por UC'!$C:$C,'Infos Clientes'!$B43,'Detalhe Por UC'!$R:$R,'Infos Clientes'!AL$2)=0,"", SUMIFS('Detalhe Por UC'!$AB:$AB,'Detalhe Por UC'!$C:$C,'Infos Clientes'!$B43,'Detalhe Por UC'!$R:$R,'Infos Clientes'!AL$2) +SUMIFS('Detalhe Por UC'!$AC:$AC,'Detalhe Por UC'!$C:$C,'Infos Clientes'!$B43,'Detalhe Por UC'!$R:$R,'Infos Clientes'!AL$2)) -> 137 | AM43: =IF(SUMIFS('Detalhe Por UC'!$AB:$AB,'Detalhe Por UC'!$C:$C,'Infos Clientes'!$B43,'Detalhe Por UC'!$R:$R,'Infos Clientes'!AM$2)=0,"", SUMIFS('Detalhe Por UC'!$AB:$AB,'Detalhe Por UC'!$C:$C,'Infos Clientes'!$B43,'Detalhe Por UC'!$R:$R,'Infos Clientes'!AM$2) +SUMIFS('Detalhe Por UC'!$AC:$AC,'Detalhe Por UC'!$C:$C,'Infos Clientes'!$B43,'Detalhe Por UC'!$R:$R,'Infos Clientes'!AM$2)) -> 113 | AN43: =IF(SUMIFS('Detalhe Por UC'!$AB:$AB,'Detalhe Por UC'!$C:$C,'Infos Clientes'!$B43,'Detalhe Por UC'!$R:$R,'Infos Clientes'!AN$2)=0,"", SUMIFS('Detalhe Por UC'!$AB:$AB,'Detalhe Por UC'!$C:$C,'Infos Clientes'!$B43,'Detalhe Por UC'!$R:$R,'Infos Clientes'!AN$2) +SUMIFS('Detalhe Por UC'!$AC:$AC,'Detalhe Por UC'!$C:$C,'Infos Clientes'!$B43,'Detalhe Por UC'!$R:$R,'Infos Clientes'!AN$2)) -> 121 | AO43: =IF(SUMIFS('Detalhe Por UC'!$AB:$AB,'Detalhe Por UC'!$C:$C,'Infos Clientes'!$B43,'Detalhe Por UC'!$R:$R,'Infos Clientes'!AO$2)=0,"", SUMIFS('Detalhe Por UC'!$AB:$AB,'Detalhe Por UC'!$C:$C,'Infos Clientes'!$B43,'Detalhe Por UC'!$R:$R,'Infos Clientes'!AO$2) +SUMIFS('Detalhe Por UC'!$AC:$AC,'Detalhe Por UC'!$C:$C,'Infos Clientes'!$B43,'Detalhe Por UC'!$R:$R,'Infos Clientes'!AO$2)) | AP43: =IF(SUMIFS('Detalhe Por UC'!$AB:$AB,'Detalhe Por UC'!$C:$C,'Infos Clientes'!$B43,'Detalhe Por UC'!$R:$R,'Infos Clientes'!AP$2)=0,"", SUMIFS('Detalhe Por UC'!$AB:$AB,'Detalhe Por UC'!$C:$C,'Infos Clientes'!$B43,'Detalhe Por UC'!$R:$R,'Infos Clientes'!AP$2) +SUMIFS('Detalhe Por UC'!$AC:$AC,'Detalhe Por UC'!$C:$C,'Infos Clientes'!$B43,'Detalhe Por UC'!$R:$R,'Infos Clientes'!AP$2)) -> 181 | AQ43: =IF(SUMIFS('Detalhe Por UC'!$AB:$AB,'Detalhe Por UC'!$C:$C,'Infos Clientes'!$B43,'Detalhe Por UC'!$R:$R,'Infos Clientes'!AQ$2)=0,"", SUMIFS('Detalhe Por UC'!$AB:$AB,'Detalhe Por UC'!$C:$C,'Infos Clientes'!$B43,'Detalhe Por UC'!$R:$R,'Infos Clientes'!AQ$2) +SUMIFS('Detalhe Por UC'!$AC:$AC,'Detalhe Por UC'!$C:$C,'Infos Clientes'!$B43,'Detalhe Por UC'!$R:$R,'Infos Clientes'!AQ$2)) -> 212 | ... AU43: =IF(SUMIFS('Detalhe Por UC'!$AB:$AB,'Detalhe Por UC'!$C:$C,'Infos Clientes'!$B43,'Detalhe Por UC'!$R:$R,'Infos Clientes'!AU$2)=0,"", SUMIFS('Detalhe Por UC'!$AB:$AB,'Detalhe Por UC'!$C:$C,'Infos Clientes'!$B43,'Detalhe Por UC'!$R:$R,'Infos Clientes'!AU$2) +SUMIFS('Detalhe Por UC'!$AC:$AC,'Detalhe Por UC'!$C:$C,'Infos Clientes'!$B43,'Detalhe Por UC'!$R:$R,'Infos Clientes'!AU$2))
B44: 10/104720-8 | C44: =ROW(F44) -> 44 | D44: IGREJA DO EVANGELHO QUADRANGULAR | E44: 0 | F44: 62.955.505/0914-56 | H44: 10/104720-8 | K44: GIROSSOL II | Q44: =IF(_xlfn.MINIFS('Detalhe Por UC'!R:R,'Detalhe Por UC'!C:C,B44,'Detalhe Por UC'!AD:AD,">"&0)=0,"",_xlfn.MINIFS('Detalhe Por UC'!R:R,'Detalhe Por UC'!C:C,B44,'Detalhe Por UC'!AD:AD,">"&0)) | R44: =IF(P44<>"ATIVO",0, IF(OR(Q44="",Q44=0,O44=0),O44, O44-ROUND((MAX('Detalhe Por UC'!R:R) -Q44)/(365/12),0))) -> 0 | U44: =IFERROR((SUMIFS(W44:CN44,$W$2:$CN$2,">"&$Q$1-365,$W$2:$CN$2,"<="&$Q$1)/COUNTIFS(W44:CN44,">="&0,$W$2:$CN$2,">"&$Q$1-365,$W$2:$CN$2,"<="&$Q$1)),"") -> 136 | AI44: 136 | AJ44: =IF(SUMIFS('Detalhe Por UC'!$AB:$AB,'Detalhe Por UC'!$C:$C,'Infos Clientes'!$B44,'Detalhe Por UC'!$R:$R,'Infos Clientes'!AJ$2)=0,"", SUMIFS('Detalhe Por UC'!$AB:$AB,'Detalhe Por UC'!$C:$C,'Infos Clientes'!$B44,'Detalhe Por UC'!$R:$R,'Infos Clientes'!AJ$2) +SUMIFS('Detalhe Por UC'!$AC:$AC,'Detalhe Por UC'!$C:$C,'Infos Clientes'!$B44,'Detalhe Por UC'!$R:$R,'Infos Clientes'!AJ$2)) | AK44: =IF(SUMIFS('Detalhe Por UC'!$AB:$AB,'Detalhe Por UC'!$C:$C,'Infos Clientes'!$B44,'Detalhe Por UC'!$R:$R,'Infos Clientes'!AK$2)=0,"", SUMIFS('Detalhe Por UC'!$AB:$AB,'Detalhe Por UC'!$C:$C,'Infos Clientes'!$B44,'Detalhe Por UC'!$R:$R,'Infos Clientes'!AK$2) +SUMIFS('Detalhe Por UC'!$AC:$AC,'Detalhe Por UC'!$C:$C,'Infos Clientes'!$B44,'Detalhe Por UC'!$R:$R,'Infos Clientes'!AK$2)) | AL44: =IF(SUMIFS('Detalhe Por UC'!$AB:$AB,'Detalhe Por UC'!$C:$C,'Infos Clientes'!$B44,'Detalhe Por UC'!$R:$R,'Infos Clientes'!AL$2)=0,"", SUMIFS('Detalhe Por UC'!$AB:$AB,'Detalhe Por UC'!$C:$C,'Infos Clientes'!$B44,'Detalhe Por UC'!$R:$R,'Infos Clientes'!AL$2) +SUMIFS('Detalhe Por UC'!$AC:$AC,'Detalhe Por UC'!$C:$C,'Infos Clientes'!$B44,'Detalhe Por UC'!$R:$R,'Infos Clientes'!AL$2)) | AM44: =IF(SUMIFS('Detalhe Por UC'!$AB:$AB,'Detalhe Por UC'!$C:$C,'Infos Clientes'!$B44,'Detalhe Por UC'!$R:$R,'Infos Clientes'!AM$2)=0,"", SUMIFS('Detalhe Por UC'!$AB:$AB,'Detalhe Por UC'!$C:$C,'Infos Clientes'!$B44,'Detalhe Por UC'!$R:$R,'Infos Clientes'!AM$2) +SUMIFS('Detalhe Por UC'!$AC:$AC,'Detalhe Por UC'!$C:$C,'Infos Clientes'!$B44,'Detalhe Por UC'!$R:$R,'Infos Clientes'!AM$2)) | AN44: =IF(SUMIFS('Detalhe Por UC'!$AB:$AB,'Detalhe Por UC'!$C:$C,'Infos Clientes'!$B44,'Detalhe Por UC'!$R:$R,'Infos Clientes'!AN$2)=0,"", SUMIFS('Detalhe Por UC'!$AB:$AB,'Detalhe Por UC'!$C:$C,'Infos Clientes'!$B44,'Detalhe Por UC'!$R:$R,'Infos Clientes'!AN$2) +SUMIFS('Detalhe Por UC'!$AC:$AC,'Detalhe Por UC'!$C:$C,'Infos Clientes'!$B44,'Detalhe Por UC'!$R:$R,'Infos Clientes'!AN$2)) | AO44: =IF(SUMIFS('Detalhe Por UC'!$AB:$AB,'Detalhe Por UC'!$C:$C,'Infos Clientes'!$B44,'Detalhe Por UC'!$R:$R,'Infos Clientes'!AO$2)=0,"", SUMIFS('Detalhe Por UC'!$AB:$AB,'Detalhe Por UC'!$C:$C,'Infos Clientes'!$B44,'Detalhe Por UC'!$R:$R,'Infos Clientes'!AO$2) +SUMIFS('Detalhe Por UC'!$AC:$AC,'Detalhe Por UC'!$C:$C,'Infos Clientes'!$B44,'Detalhe Por UC'!$R:$R,'Infos Clientes'!AO$2)) | AP44: =IF(SUMIFS('Detalhe Por UC'!$AB:$AB,'Detalhe Por UC'!$C:$C,'Infos Clientes'!$B44,'Detalhe Por UC'!$R:$R,'Infos Clientes'!AP$2)=0,"", SUMIFS('Detalhe Por UC'!$AB:$AB,'Detalhe Por UC'!$C:$C,'Infos Clientes'!$B44,'Detalhe Por UC'!$R:$R,'Infos Clientes'!AP$2) +SUMIFS('Detalhe Por UC'!$AC:$AC,'Detalhe Por UC'!$C:$C,'Infos Clientes'!$B44,'Detalhe Por UC'!$R:$R,'Infos Clientes'!AP$2)) | AQ44: =IF(SUMIFS('Detalhe Por UC'!$AB:$AB,'Detalhe Por UC'!$C:$C,'Infos Clientes'!$B44,'Detalhe Por UC'!$R:$R,'Infos Clientes'!AQ$2)=0,"", SUMIFS('Detalhe Por UC'!$AB:$AB,'Detalhe Por UC'!$C:$C,'Infos Clientes'!$B44,'Detalhe Por UC'!$R:$R,'Infos Clientes'!AQ$2) +SUMIFS('Detalhe Por UC'!$AC:$AC,'Detalhe Por UC'!$C:$C,'Infos Clientes'!$B44,'Detalhe Por UC'!$R:$R,'Infos Clientes'!AQ$2)) | ... AU44: =IF(SUMIFS('Detalhe Por UC'!$AB:$AB,'Detalhe Por UC'!$C:$C,'Infos Clientes'!$B44,'Detalhe Por UC'!$R:$R,'Infos Clientes'!AU$2)=0,"", SUMIFS('Detalhe Por UC'!$AB:$AB,'Detalhe Por UC'!$C:$C,'Infos Clientes'!$B44,'Detalhe Por UC'!$R:$R,'Infos Clientes'!AU$2) +SUMIFS('Detalhe Por UC'!$AC:$AC,'Detalhe Por UC'!$C:$C,'Infos Clientes'!$B44,'Detalhe Por UC'!$R:$R,'Infos Clientes'!AU$2))
B45: 10/150263-2 | C45: =ROW(F45) -> 45 | D45: IGREJA DO EVANGELHO QUADRANGULAR | E45: 0 | F45: 62.955.505/0914-56 | H45: 10/150263-2 | I45: BT | J45: monofasico | K45: GIROSSOL II | M45: 0.25 | Q45: =IF(_xlfn.MINIFS('Detalhe Por UC'!R:R,'Detalhe Por UC'!C:C,B45,'Detalhe Por UC'!AD:AD,">"&0)=0,"",_xlfn.MINIFS('Detalhe Por UC'!R:R,'Detalhe Por UC'!C:C,B45,'Detalhe Por UC'!AD:AD,">"&0)) -> 45658 | R45: =IF(P45<>"ATIVO",0, IF(OR(Q45="",Q45=0,O45=0),O45, O45-ROUND((MAX('Detalhe Por UC'!R:R) -Q45)/(365/12),0))) -> 0 | U45: =IFERROR((SUMIFS(W45:CN45,$W$2:$CN$2,">"&$Q$1-365,$W$2:$CN$2,"<="&$Q$1)/COUNTIFS(W45:CN45,">="&0,$W$2:$CN$2,">"&$Q$1-365,$W$2:$CN$2,"<="&$Q$1)),"") -> 139.72727 | AI45: 137 | AJ45: =IF(SUMIFS('Detalhe Por UC'!$AB:$AB,'Detalhe Por UC'!$C:$C,'Infos Clientes'!$B45,'Detalhe Por UC'!$R:$R,'Infos Clientes'!AJ$2)=0,"", SUMIFS('Detalhe Por UC'!$AB:$AB,'Detalhe Por UC'!$C:$C,'Infos Clientes'!$B45,'Detalhe Por UC'!$R:$R,'Infos Clientes'!AJ$2) +SUMIFS('Detalhe Por UC'!$AC:$AC,'Detalhe Por UC'!$C:$C,'Infos Clientes'!$B45,'Detalhe Por UC'!$R:$R,'Infos Clientes'!AJ$2)) -> 187 | AK45: =IF(SUMIFS('Detalhe Por UC'!$AB:$AB,'Detalhe Por UC'!$C:$C,'Infos Clientes'!$B45,'Detalhe Por UC'!$R:$R,'Infos Clientes'!AK$2)=0,"", SUMIFS('Detalhe Por UC'!$AB:$AB,'Detalhe Por UC'!$C:$C,'Infos Clientes'!$B45,'Detalhe Por UC'!$R:$R,'Infos Clientes'!AK$2) +SUMIFS('Detalhe Por UC'!$AC:$AC,'Detalhe Por UC'!$C:$C,'Infos Clientes'!$B45,'Detalhe Por UC'!$R:$R,'Infos Clientes'!AK$2)) | AL45: =IF(SUMIFS('Detalhe Por UC'!$AB:$AB,'Detalhe Por UC'!$C:$C,'Infos Clientes'!$B45,'Detalhe Por UC'!$R:$R,'Infos Clientes'!AL$2)=0,"", SUMIFS('Detalhe Por UC'!$AB:$AB,'Detalhe Por UC'!$C:$C,'Infos Clientes'!$B45,'Detalhe Por UC'!$R:$R,'Infos Clientes'!AL$2) +SUMIFS('Detalhe Por UC'!$AC:$AC,'Detalhe Por UC'!$C:$C,'Infos Clientes'!$B45,'Detalhe Por UC'!$R:$R,'Infos Clientes'!AL$2)) -> 202 | AM45: =IF(SUMIFS('Detalhe Por UC'!$AB:$AB,'Detalhe Por UC'!$C:$C,'Infos Clientes'!$B45,'Detalhe Por UC'!$R:$R,'Infos Clientes'!AM$2)=0,"", SUMIFS('Detalhe Por UC'!$AB:$AB,'Detalhe Por UC'!$C:$C,'Infos Clientes'!$B45,'Detalhe Por UC'!$R:$R,'Infos Clientes'!AM$2) +SUMIFS('Detalhe Por UC'!$AC:$AC,'Detalhe Por UC'!$C:$C,'Infos Clientes'!$B45,'Detalhe Por UC'!$R:$R,'Infos Clientes'!AM$2)) -> 156 | AN45: =IF(SUMIFS('Detalhe Por UC'!$AB:$AB,'Detalhe Por UC'!$C:$C,'Infos Clientes'!$B45,'Detalhe Por UC'!$R:$R,'Infos Clientes'!AN$2)=0,"", SUMIFS('Detalhe Por UC'!$AB:$AB,'Detalhe Por UC'!$C:$C,'Infos Clientes'!$B45,'Detalhe Por UC'!$R:$R,'Infos Clientes'!AN$2) +SUMIFS('Detalhe Por UC'!$AC:$AC,'Detalhe Por UC'!$C:$C,'Infos Clientes'!$B45,'Detalhe Por UC'!$R:$R,'Infos Clientes'!AN$2)) -> 139 | AO45: =IF(SUMIFS('Detalhe Por UC'!$AB:$AB,'Detalhe Por UC'!$C:$C,'Infos Clientes'!$B45,'Detalhe Por UC'!$R:$R,'Infos Clientes'!AO$2)=0,"", SUMIFS('Detalhe Por UC'!$AB:$AB,'Detalhe Por UC'!$C:$C,'Infos Clientes'!$B45,'Detalhe Por UC'!$R:$R,'Infos Clientes'!AO$2) +SUMIFS('Detalhe Por UC'!$AC:$AC,'Detalhe Por UC'!$C:$C,'Infos Clientes'!$B45,'Detalhe Por UC'!$R:$R,'Infos Clientes'!AO$2)) -> 122 | AP45: =IF(SUMIFS('Detalhe Por UC'!$AB:$AB,'Detalhe Por UC'!$C:$C,'Infos Clientes'!$B45,'Detalhe Por UC'!$R:$R,'Infos Clientes'!AP$2)=0,"", SUMIFS('Detalhe Por UC'!$AB:$AB,'Detalhe Por UC'!$C:$C,'Infos Clientes'!$B45,'Detalhe Por UC'!$R:$R,'Infos Clientes'!AP$2) +SUMIFS('Detalhe Por UC'!$AC:$AC,'Detalhe Por UC'!$C:$C,'Infos Clientes'!$B45,'Detalhe Por UC'!$R:$R,'Infos Clientes'!AP$2)) -> 97 | AQ45: =IF(SUMIFS('Detalhe Por UC'!$AB:$AB,'Detalhe Por UC'!$C:$C,'Infos Clientes'!$B45,'Detalhe Por UC'!$R:$R,'Infos Clientes'!AQ$2)=0,"", SUMIFS('Detalhe Por UC'!$AB:$AB,'Detalhe Por UC'!$C:$C,'Infos Clientes'!$B45,'Detalhe Por UC'!$R:$R,'Infos Clientes'!AQ$2) +SUMIFS('Detalhe Por UC'!$AC:$AC,'Detalhe Por UC'!$C:$C,'Infos Clientes'!$B45,'Detalhe Por UC'!$R:$R,'Infos Clientes'!AQ$2)) -> 100 | ... AU45: =IF(SUMIFS('Detalhe Por UC'!$AB:$AB,'Detalhe Por UC'!$C:$C,'Infos Clientes'!$B45,'Detalhe Por UC'!$R:$R,'Infos Clientes'!AU$2)=0,"", SUMIFS('Detalhe Por UC'!$AB:$AB,'Detalhe Por UC'!$C:$C,'Infos Clientes'!$B45,'Detalhe Por UC'!$R:$R,'Infos Clientes'!AU$2) +SUMIFS('Detalhe Por UC'!$AC:$AC,'Detalhe Por UC'!$C:$C,'Infos Clientes'!$B45,'Detalhe Por UC'!$R:$R,'Infos Clientes'!AU$2))
B46: 10/1433087-2 | C46: 49 | D46: IGREJA DO EVANGELHO QUADRANGULAR | E46: 0 | F46: 62.955.505/4194-43 | H46: 10/1433087-2 | I46: BT | J46: trifasico | K46: GIROSSOL II | M46: 0.25 | Q46: =IF(_xlfn.MINIFS('Detalhe Por UC'!R:R,'Detalhe Por UC'!C:C,B46,'Detalhe Por UC'!AD:AD,">"&0)=0,"",_xlfn.MINIFS('Detalhe Por UC'!R:R,'Detalhe Por UC'!C:C,B46,'Detalhe Por UC'!AD:AD,">"&0)) -> 45689 | R46: =IF(P46<>"ATIVO",0, IF(OR(Q46="",Q46=0,O46=0),O46, O46-ROUND((MAX('Detalhe Por UC'!R:R) -Q46)/(365/12),0))) -> 0 | U46: =IFERROR((SUMIFS(W46:CN46,$W$2:$CN$2,">"&$Q$1-365,$W$2:$CN$2,"<="&$Q$1)/COUNTIFS(W46:CN46,">="&0,$W$2:$CN$2,">"&$Q$1-365,$W$2:$CN$2,"<="&$Q$1)),"") -> 213.22222 | AJ46: =IF(SUMIFS('Detalhe Por UC'!$AB:$AB,'Detalhe Por UC'!$C:$C,'Infos Clientes'!$B46,'Detalhe Por UC'!$R:$R,'Infos Clientes'!AJ$2)=0,"", SUMIFS('Detalhe Por UC'!$AB:$AB,'Detalhe Por UC'!$C:$C,'Infos Clientes'!$B46,'Detalhe Por UC'!$R:$R,'Infos Clientes'!AJ$2) +SUMIFS('Detalhe Por UC'!$AC:$AC,'Detalhe Por UC'!$C:$C,'Infos Clientes'!$B46,'Detalhe Por UC'!$R:$R,'Infos Clientes'!AJ$2)) | AK46: =IF(SUMIFS('Detalhe Por UC'!$AB:$AB,'Detalhe Por UC'!$C:$C,'Infos Clientes'!$B46,'Detalhe Por UC'!$R:$R,'Infos Clientes'!AK$2)=0,"", SUMIFS('Detalhe Por UC'!$AB:$AB,'Detalhe Por UC'!$C:$C,'Infos Clientes'!$B46,'Detalhe Por UC'!$R:$R,'Infos Clientes'!AK$2) +SUMIFS('Detalhe Por UC'!$AC:$AC,'Detalhe Por UC'!$C:$C,'Infos Clientes'!$B46,'Detalhe Por UC'!$R:$R,'Infos Clientes'!AK$2)) -> 279 | AL46: =IF(SUMIFS('Detalhe Por UC'!$AB:$AB,'Detalhe Por UC'!$C:$C,'Infos Clientes'!$B46,'Detalhe Por UC'!$R:$R,'Infos Clientes'!AL$2)=0,"", SUMIFS('Detalhe Por UC'!$AB:$AB,'Detalhe Por UC'!$C:$C,'Infos Clientes'!$B46,'Detalhe Por UC'!$R:$R,'Infos Clientes'!AL$2) +SUMIFS('Detalhe Por UC'!$AC:$AC,'Detalhe Por UC'!$C:$C,'Infos Clientes'!$B46,'Detalhe Por UC'!$R:$R,'Infos Clientes'!AL$2)) -> 334 | AM46: =IF(SUMIFS('Detalhe Por UC'!$AB:$AB,'Detalhe Por UC'!$C:$C,'Infos Clientes'!$B46,'Detalhe Por UC'!$R:$R,'Infos Clientes'!AM$2)=0,"", SUMIFS('Detalhe Por UC'!$AB:$AB,'Detalhe Por UC'!$C:$C,'Infos Clientes'!$B46,'Detalhe Por UC'!$R:$R,'Infos Clientes'!AM$2) +SUMIFS('Detalhe Por UC'!$AC:$AC,'Detalhe Por UC'!$C:$C,'Infos Clientes'!$B46,'Detalhe Por UC'!$R:$R,'Infos Clientes'!AM$2)) -> 289 | AN46: =IF(SUMIFS('Detalhe Por UC'!$AB:$AB,'Detalhe Por UC'!$C:$C,'Infos Clientes'!$B46,'Detalhe Por UC'!$R:$R,'Infos Clientes'!AN$2)=0,"", SUMIFS('Detalhe Por UC'!$AB:$AB,'Detalhe Por UC'!$C:$C,'Infos Clientes'!$B46,'Detalhe Por UC'!$R:$R,'Infos Clientes'!AN$2) +SUMIFS('Detalhe Por UC'!$AC:$AC,'Detalhe Por UC'!$C:$C,'Infos Clientes'!$B46,'Detalhe Por UC'!$R:$R,'Infos Clientes'!AN$2)) -> 156 | AO46: =IF(SUMIFS('Detalhe Por UC'!$AB:$AB,'Detalhe Por UC'!$C:$C,'Infos Clientes'!$B46,'Detalhe Por UC'!$R:$R,'Infos Clientes'!AO$2)=0,"", SUMIFS('Detalhe Por UC'!$AB:$AB,'Detalhe Por UC'!$C:$C,'Infos Clientes'!$B46,'Detalhe Por UC'!$R:$R,'Infos Clientes'!AO$2) +SUMIFS('Detalhe Por UC'!$AC:$AC,'Detalhe Por UC'!$C:$C,'Infos Clientes'!$B46,'Detalhe Por UC'!$R:$R,'Infos Clientes'!AO$2)) -> 135 | AP46: =IF(SUMIFS('Detalhe Por UC'!$AB:$AB,'Detalhe Por UC'!$C:$C,'Infos Clientes'!$B46,'Detalhe Por UC'!$R:$R,'Infos Clientes'!AP$2)=0,"", SUMIFS('Detalhe Por UC'!$AB:$AB,'Detalhe Por UC'!$C:$C,'Infos Clientes'!$B46,'Detalhe Por UC'!$R:$R,'Infos Clientes'!AP$2) +SUMIFS('Detalhe Por UC'!$AC:$AC,'Detalhe Por UC'!$C:$C,'Infos Clientes'!$B46,'Detalhe Por UC'!$R:$R,'Infos Clientes'!AP$2)) | AQ46: =IF(SUMIFS('Detalhe Por UC'!$AB:$AB,'Detalhe Por UC'!$C:$C,'Infos Clientes'!$B46,'Detalhe Por UC'!$R:$R,'Infos Clientes'!AQ$2)=0,"", SUMIFS('Detalhe Por UC'!$AB:$AB,'Detalhe Por UC'!$C:$C,'Infos Clientes'!$B46,'Detalhe Por UC'!$R:$R,'Infos Clientes'!AQ$2) +SUMIFS('Detalhe Por UC'!$AC:$AC,'Detalhe Por UC'!$C:$C,'Infos Clientes'!$B46,'Detalhe Por UC'!$R:$R,'Infos Clientes'!AQ$2)) -> 106 | ... AU46: =IF(SUMIFS('Detalhe Por UC'!$AB:$AB,'Detalhe Por UC'!$C:$C,'Infos Clientes'!$B46,'Detalhe Por UC'!$R:$R,'Infos Clientes'!AU$2)=0,"", SUMIFS('Detalhe Por UC'!$AB:$AB,'Detalhe Por UC'!$C:$C,'Infos Clientes'!$B46,'Detalhe Por UC'!$R:$R,'Infos Clientes'!AU$2) +SUMIFS('Detalhe Por UC'!$AC:$AC,'Detalhe Por UC'!$C:$C,'Infos Clientes'!$B46,'Detalhe Por UC'!$R:$R,'Infos Clientes'!AU$2))
B47: 10/10731-8 | C47: =ROW(F47) -> 47 | D47: IGREJA DO EVANGELHO QUADRANGULAR | E47: 302 | F47: 62.955.505/3932-07 | G47: pastor.renato@gmail.com; israelregiao302@gmail.com | H47: =B47 -> 10/10731-8 | I47: BT | K47: GIROSSOL III | M47: 0.25 | Q47: =IF(_xlfn.MINIFS('Detalhe Por UC'!R:R,'Detalhe Por UC'!C:C,B47,'Detalhe Por UC'!AD:AD,">"&0)=0,"",_xlfn.MINIFS('Detalhe Por UC'!R:R,'Detalhe Por UC'!C:C,B47,'Detalhe Por UC'!AD:AD,">"&0)) | R47: =IF(P47<>"ATIVO",0, IF(OR(Q47="",Q47=0,O47=0),O47, O47-ROUND((MAX('Detalhe Por UC'!R:R) -Q47)/(365/12),0))) -> 0 | U47: =IFERROR((SUMIFS(W47:CN47,$W$2:$CN$2,">"&$Q$1-365,$W$2:$CN$2,"<="&$Q$1)/COUNTIFS(W47:CN47,">="&0,$W$2:$CN$2,">"&$Q$1-365,$W$2:$CN$2,"<="&$Q$1)),"") | AJ47: =IF(SUMIFS('Detalhe Por UC'!$AB:$AB,'Detalhe Por UC'!$C:$C,'Infos Clientes'!$B47,'Detalhe Por UC'!$R:$R,'Infos Clientes'!AJ$2)=0,"", SUMIFS('Detalhe Por UC'!$AB:$AB,'Detalhe Por UC'!$C:$C,'Infos Clientes'!$B47,'Detalhe Por UC'!$R:$R,'Infos Clientes'!AJ$2) +SUMIFS('Detalhe Por UC'!$AC:$AC,'Detalhe Por UC'!$C:$C,'Infos Clientes'!$B47,'Detalhe Por UC'!$R:$R,'Infos Clientes'!AJ$2)) | AK47: =IF(SUMIFS('Detalhe Por UC'!$AB:$AB,'Detalhe Por UC'!$C:$C,'Infos Clientes'!$B47,'Detalhe Por UC'!$R:$R,'Infos Clientes'!AK$2)=0,"", SUMIFS('Detalhe Por UC'!$AB:$AB,'Detalhe Por UC'!$C:$C,'Infos Clientes'!$B47,'Detalhe Por UC'!$R:$R,'Infos Clientes'!AK$2) +SUMIFS('Detalhe Por UC'!$AC:$AC,'Detalhe Por UC'!$C:$C,'Infos Clientes'!$B47,'Detalhe Por UC'!$R:$R,'Infos Clientes'!AK$2)) | AL47: =IF(SUMIFS('Detalhe Por UC'!$AB:$AB,'Detalhe Por UC'!$C:$C,'Infos Clientes'!$B47,'Detalhe Por UC'!$R:$R,'Infos Clientes'!AL$2)=0,"", SUMIFS('Detalhe Por UC'!$AB:$AB,'Detalhe Por UC'!$C:$C,'Infos Clientes'!$B47,'Detalhe Por UC'!$R:$R,'Infos Clientes'!AL$2) +SUMIFS('Detalhe Por UC'!$AC:$AC,'Detalhe Por UC'!$C:$C,'Infos Clientes'!$B47,'Detalhe Por UC'!$R:$R,'Infos Clientes'!AL$2)) | AM47: =IF(SUMIFS('Detalhe Por UC'!$AB:$AB,'Detalhe Por UC'!$C:$C,'Infos Clientes'!$B47,'Detalhe Por UC'!$R:$R,'Infos Clientes'!AM$2)=0,"", SUMIFS('Detalhe Por UC'!$AB:$AB,'Detalhe Por UC'!$C:$C,'Infos Clientes'!$B47,'Detalhe Por UC'!$R:$R,'Infos Clientes'!AM$2) +SUMIFS('Detalhe Por UC'!$AC:$AC,'Detalhe Por UC'!$C:$C,'Infos Clientes'!$B47,'Detalhe Por UC'!$R:$R,'Infos Clientes'!AM$2)) | AN47: =IF(SUMIFS('Detalhe Por UC'!$AB:$AB,'Detalhe Por UC'!$C:$C,'Infos Clientes'!$B47,'Detalhe Por UC'!$R:$R,'Infos Clientes'!AN$2)=0,"", SUMIFS('Detalhe Por UC'!$AB:$AB,'Detalhe Por UC'!$C:$C,'Infos Clientes'!$B47,'Detalhe Por UC'!$R:$R,'Infos Clientes'!AN$2) +SUMIFS('Detalhe Por UC'!$AC:$AC,'Detalhe Por UC'!$C:$C,'Infos Clientes'!$B47,'Detalhe Por UC'!$R:$R,'Infos Clientes'!AN$2)) | AO47: =IF(SUMIFS('Detalhe Por UC'!$AB:$AB,'Detalhe Por UC'!$C:$C,'Infos Clientes'!$B47,'Detalhe Por UC'!$R:$R,'Infos Clientes'!AO$2)=0,"", SUMIFS('Detalhe Por UC'!$AB:$AB,'Detalhe Por UC'!$C:$C,'Infos Clientes'!$B47,'Detalhe Por UC'!$R:$R,'Infos Clientes'!AO$2) +SUMIFS('Detalhe Por UC'!$AC:$AC,'Detalhe Por UC'!$C:$C,'Infos Clientes'!$B47,'Detalhe Por UC'!$R:$R,'Infos Clientes'!AO$2)) | AP47: =IF(SUMIFS('Detalhe Por UC'!$AB:$AB,'Detalhe Por UC'!$C:$C,'Infos Clientes'!$B47,'Detalhe Por UC'!$R:$R,'Infos Clientes'!AP$2)=0,"", SUMIFS('Detalhe Por UC'!$AB:$AB,'Detalhe Por UC'!$C:$C,'Infos Clientes'!$B47,'Detalhe Por UC'!$R:$R,'Infos Clientes'!AP$2) +SUMIFS('Detalhe Por UC'!$AC:$AC,'Detalhe Por UC'!$C:$C,'Infos Clientes'!$B47,'Detalhe Por UC'!$R:$R,'Infos Clientes'!AP$2)) | AQ47: =IF(SUMIFS('Detalhe Por UC'!$AB:$AB,'Detalhe Por UC'!$C:$C,'Infos Clientes'!$B47,'Detalhe Por UC'!$R:$R,'Infos Clientes'!AQ$2)=0,"", SUMIFS('Detalhe Por UC'!$AB:$AB,'Detalhe Por UC'!$C:$C,'Infos Clientes'!$B47,'Detalhe Por UC'!$R:$R,'Infos Clientes'!AQ$2) +SUMIFS('Detalhe Por UC'!$AC:$AC,'Detalhe Por UC'!$C:$C,'Infos Clientes'!$B47,'Detalhe Por UC'!$R:$R,'Infos Clientes'!AQ$2)) | ... AU47: =IF(SUMIFS('Detalhe Por UC'!$AB:$AB,'Detalhe Por UC'!$C:$C,'Infos Clientes'!$B47,'Detalhe Por UC'!$R:$R,'Infos Clientes'!AU$2)=0,"", SUMIFS('Detalhe Por UC'!$AB:$AB,'Detalhe Por UC'!$C:$C,'Infos Clientes'!$B47,'Detalhe Por UC'!$R:$R,'Infos Clientes'!AU$2) +SUMIFS('Detalhe Por UC'!$AC:$AC,'Detalhe Por UC'!$C:$C,'Infos Clientes'!$B47,'Detalhe Por UC'!$R:$R,'Infos Clientes'!AU$2))
B48: 10/1081489-5 | C48: =ROW(F48) -> 48 | D48: IGREJA DO EVANGELHO QUADRANGULAR | E48: 351 | F48: 62.955.505/0169-18 | G48: regiao351@bol.com.b | H48: =B48 -> 10/1081489-5 | I48: BT | J48: bifasico | K48: GIROSSOL III | M48: 0.25 | Q48: =IF(_xlfn.MINIFS('Detalhe Por UC'!R:R,'Detalhe Por UC'!C:C,B48,'Detalhe Por UC'!AD:AD,">"&0)=0,"",_xlfn.MINIFS('Detalhe Por UC'!R:R,'Detalhe Por UC'!C:C,B48,'Detalhe Por UC'!AD:AD,">"&0)) -> 45658 | R48: =IF(P48<>"ATIVO",0, IF(OR(Q48="",Q48=0,O48=0),O48, O48-ROUND((MAX('Detalhe Por UC'!R:R) -Q48)/(365/12),0))) -> 0 | T48: 547.45455 | U48: =IFERROR((SUMIFS(W48:CN48,$W$2:$CN$2,">"&$Q$1-365,$W$2:$CN$2,"<="&$Q$1)/COUNTIFS(W48:CN48,">="&0,$W$2:$CN$2,">"&$Q$1-365,$W$2:$CN$2,"<="&$Q$1)),"") -> 533.66667 | X48: 549 | Y48: 629 | Z48: 609 | AA48: 672 | AB48: 0 | AC48: 449 | AD48: 456 | AE48: 400 | AF48: 403 | AG48: 541 | AH48: 546 | AI48: 683 | AJ48: =IF(SUMIFS('Detalhe Por UC'!$AB:$AB,'Detalhe Por UC'!$C:$C,'Infos Clientes'!$B48,'Detalhe Por UC'!$R:$R,'Infos Clientes'!AJ$2)=0,"", SUMIFS('Detalhe Por UC'!$AB:$AB,'Detalhe Por UC'!$C:$C,'Infos Clientes'!$B48,'Detalhe Por UC'!$R:$R,'Infos Clientes'!AJ$2) +SUMIFS('Detalhe Por UC'!$AC:$AC,'Detalhe Por UC'!$C:$C,'Infos Clientes'!$B48,'Detalhe Por UC'!$R:$R,'Infos Clientes'!AJ$2)) -> 634 | AK48: =IF(SUMIFS('Detalhe Por UC'!$AB:$AB,'Detalhe Por UC'!$C:$C,'Infos Clientes'!$B48,'Detalhe Por UC'!$R:$R,'Infos Clientes'!AK$2)=0,"", SUMIFS('Detalhe Por UC'!$AB:$AB,'Detalhe Por UC'!$C:$C,'Infos Clientes'!$B48,'Detalhe Por UC'!$R:$R,'Infos Clientes'!AK$2) +SUMIFS('Detalhe Por UC'!$AC:$AC,'Detalhe Por UC'!$C:$C,'Infos Clientes'!$B48,'Detalhe Por UC'!$R:$R,'Infos Clientes'!AK$2)) -> 785 | AL48: =IF(SUMIFS('Detalhe Por UC'!$AB:$AB,'Detalhe Por UC'!$C:$C,'Infos Clientes'!$B48,'Detalhe Por UC'!$R:$R,'Infos Clientes'!AL$2)=0,"", SUMIFS('Detalhe Por UC'!$AB:$AB,'Detalhe Por UC'!$C:$C,'Infos Clientes'!$B48,'Detalhe Por UC'!$R:$R,'Infos Clientes'!AL$2) +SUMIFS('Detalhe Por UC'!$AC:$AC,'Detalhe Por UC'!$C:$C,'Infos Clientes'!$B48,'Detalhe Por UC'!$R:$R,'Infos Clientes'!AL$2)) -> 651 | AM48: =IF(SUMIFS('Detalhe Por UC'!$AB:$AB,'Detalhe Por UC'!$C:$C,'Infos Clientes'!$B48,'Detalhe Por UC'!$R:$R,'Infos Clientes'!AM$2)=0,"", SUMIFS('Detalhe Por UC'!$AB:$AB,'Detalhe Por UC'!$C:$C,'Infos Clientes'!$B48,'Detalhe Por UC'!$R:$R,'Infos Clientes'!AM$2) +SUMIFS('Detalhe Por UC'!$AC:$AC,'Detalhe Por UC'!$C:$C,'Infos Clientes'!$B48,'Detalhe Por UC'!$R:$R,'Infos Clientes'!AM$2)) -> 495 | AN48: =IF(SUMIFS('Detalhe Por UC'!$AB:$AB,'Detalhe Por UC'!$C:$C,'Infos Clientes'!$B48,'Detalhe Por UC'!$R:$R,'Infos Clientes'!AN$2)=0,"", SUMIFS('Detalhe Por UC'!$AB:$AB,'Detalhe Por UC'!$C:$C,'Infos Clientes'!$B48,'Detalhe Por UC'!$R:$R,'Infos Clientes'!AN$2) +SUMIFS('Detalhe Por UC'!$AC:$AC,'Detalhe Por UC'!$C:$C,'Infos Clientes'!$B48,'Detalhe Por UC'!$R:$R,'Infos Clientes'!AN$2)) -> 543 | AO48: =IF(SUMIFS('Detalhe Por UC'!$AB:$AB,'Detalhe Por UC'!$C:$C,'Infos Clientes'!$B48,'Detalhe Por UC'!$R:$R,'Infos Clientes'!AO$2)=0,"", SUMIFS('Detalhe Por UC'!$AB:$AB,'Detalhe Por UC'!$C:$C,'Infos Clientes'!$B48,'Detalhe Por UC'!$R:$R,'Infos Clientes'!AO$2) +SUMIFS('Detalhe Por UC'!$AC:$AC,'Detalhe Por UC'!$C:$C,'Infos Clientes'!$B48,'Detalhe Por UC'!$R:$R,'Infos Clientes'!AO$2)) -> 427 | AP48: =IF(SUMIFS('Detalhe Por UC'!$AB:$AB,'Detalhe Por UC'!$C:$C,'Infos Clientes'!$B48,'Detalhe Por UC'!$R:$R,'Infos Clientes'!AP$2)=0,"", SUMIFS('Detalhe Por UC'!$AB:$AB,'Detalhe Por UC'!$C:$C,'Infos Clientes'!$B48,'Detalhe Por UC'!$R:$R,'Infos Clientes'!AP$2) +SUMIFS('Detalhe Por UC'!$AC:$AC,'Detalhe Por UC'!$C:$C,'Infos Clientes'!$B48,'Detalhe Por UC'!$R:$R,'Infos Clientes'!AP$2)) -> 379 | AQ48: =IF(SUMIFS('Detalhe Por UC'!$AB:$AB,'Detalhe Por UC'!$C:$C,'Infos Clientes'!$B48,'Detalhe Por UC'!$R:$R,'Infos Clientes'!AQ$2)=0,"", SUMIFS('Detalhe Por UC'!$AB:$AB,'Detalhe Por UC'!$C:$C,'Infos Clientes'!$B48,'Detalhe Por UC'!$R:$R,'Infos Clientes'!AQ$2) +SUMIFS('Detalhe Por UC'!$AC:$AC,'Detalhe Por UC'!$C:$C,'Infos Clientes'!$B48,'Detalhe Por UC'!$R:$R,'Infos Clientes'!AQ$2)) -> 412 | ... AU48: =IF(SUMIFS('Detalhe Por UC'!$AB:$AB,'Detalhe Por UC'!$C:$C,'Infos Clientes'!$B48,'Detalhe Por UC'!$R:$R,'Infos Clientes'!AU$2)=0,"", SUMIFS('Detalhe Por UC'!$AB:$AB,'Detalhe Por UC'!$C:$C,'Infos Clientes'!$B48,'Detalhe Por UC'!$R:$R,'Infos Clientes'!AU$2) +SUMIFS('Detalhe Por UC'!$AC:$AC,'Detalhe Por UC'!$C:$C,'Infos Clientes'!$B48,'Detalhe Por UC'!$R:$R,'Infos Clientes'!AU$2))
B49: 10/109074-5 | C49: =ROW(F49) -> 49 | D49: IGREJA DO EVANGELHO QUADRANGULAR | E49: 319 | F49: 62.955.505/0001-67 | G49: auxiliar.cedms@gmail.com | H49: =B49 -> 10/109074-5 | I49: BT | J49: bifasico | K49: GIROSSOL III | M49: 0.25 | Q49: =IF(_xlfn.MINIFS('Detalhe Por UC'!R:R,'Detalhe Por UC'!C:C,B49,'Detalhe Por UC'!AD:AD,">"&0)=0,"",_xlfn.MINIFS('Detalhe Por UC'!R:R,'Detalhe Por UC'!C:C,B49,'Detalhe Por UC'!AD:AD,">"&0)) -> 45658 | R49: =IF(P49<>"ATIVO",0, IF(OR(Q49="",Q49=0,O49=0),O49, O49-ROUND((MAX('Detalhe Por UC'!R:R) -Q49)/(365/12),0))) -> 0 | T49: 244.81818 | U49: =IFERROR((SUMIFS(W49:CN49,$W$2:$CN$2,">"&$Q$1-365,$W$2:$CN$2,"<="&$Q$1)/COUNTIFS(W49:CN49,">="&0,$W$2:$CN$2,">"&$Q$1-365,$W$2:$CN$2,"<="&$Q$1)),"") -> 309.33333 | X49: 129 | Y49: 126 | Z49: 133 | AA49: 121 | AB49: 0 | AC49: 246 | AD49: 291 | AE49: 302 | AF49: 309 | AG49: 279 | AH49: 297 | AI49: 369 | AJ49: =IF(SUMIFS('Detalhe Por UC'!$AB:$AB,'Detalhe Por UC'!$C:$C,'Infos Clientes'!$B49,'Detalhe Por UC'!$R:$R,'Infos Clientes'!AJ$2)=0,"", SUMIFS('Detalhe Por UC'!$AB:$AB,'Detalhe Por UC'!$C:$C,'Infos Clientes'!$B49,'Detalhe Por UC'!$R:$R,'Infos Clientes'!AJ$2) +SUMIFS('Detalhe Por UC'!$AC:$AC,'Detalhe Por UC'!$C:$C,'Infos Clientes'!$B49,'Detalhe Por UC'!$R:$R,'Infos Clientes'!AJ$2)) -> 220 | AK49: =IF(SUMIFS('Detalhe Por UC'!$AB:$AB,'Detalhe Por UC'!$C:$C,'Infos Clientes'!$B49,'Detalhe Por UC'!$R:$R,'Infos Clientes'!AK$2)=0,"", SUMIFS('Detalhe Por UC'!$AB:$AB,'Detalhe Por UC'!$C:$C,'Infos Clientes'!$B49,'Detalhe Por UC'!$R:$R,'Infos Clientes'!AK$2) +SUMIFS('Detalhe Por UC'!$AC:$AC,'Detalhe Por UC'!$C:$C,'Infos Clientes'!$B49,'Detalhe Por UC'!$R:$R,'Infos Clientes'!AK$2)) -> 254 | AL49: =IF(SUMIFS('Detalhe Por UC'!$AB:$AB,'Detalhe Por UC'!$C:$C,'Infos Clientes'!$B49,'Detalhe Por UC'!$R:$R,'Infos Clientes'!AL$2)=0,"", SUMIFS('Detalhe Por UC'!$AB:$AB,'Detalhe Por UC'!$C:$C,'Infos Clientes'!$B49,'Detalhe Por UC'!$R:$R,'Infos Clientes'!AL$2) +SUMIFS('Detalhe Por UC'!$AC:$AC,'Detalhe Por UC'!$C:$C,'Infos Clientes'!$B49,'Detalhe Por UC'!$R:$R,'Infos Clientes'!AL$2)) -> 320 | AM49: =IF(SUMIFS('Detalhe Por UC'!$AB:$AB,'Detalhe Por UC'!$C:$C,'Infos Clientes'!$B49,'Detalhe Por UC'!$R:$R,'Infos Clientes'!AM$2)=0,"", SUMIFS('Detalhe Por UC'!$AB:$AB,'Detalhe Por UC'!$C:$C,'Infos Clientes'!$B49,'Detalhe Por UC'!$R:$R,'Infos Clientes'!AM$2) +SUMIFS('Detalhe Por UC'!$AC:$AC,'Detalhe Por UC'!$C:$C,'Infos Clientes'!$B49,'Detalhe Por UC'!$R:$R,'Infos Clientes'!AM$2)) -> 351 | AN49: =IF(SUMIFS('Detalhe Por UC'!$AB:$AB,'Detalhe Por UC'!$C:$C,'Infos Clientes'!$B49,'Detalhe Por UC'!$R:$R,'Infos Clientes'!AN$2)=0,"", SUMIFS('Detalhe Por UC'!$AB:$AB,'Detalhe Por UC'!$C:$C,'Infos Clientes'!$B49,'Detalhe Por UC'!$R:$R,'Infos Clientes'!AN$2) +SUMIFS('Detalhe Por UC'!$AC:$AC,'Detalhe Por UC'!$C:$C,'Infos Clientes'!$B49,'Detalhe Por UC'!$R:$R,'Infos Clientes'!AN$2)) -> 320 | AO49: =IF(SUMIFS('Detalhe Por UC'!$AB:$AB,'Detalhe Por UC'!$C:$C,'Infos Clientes'!$B49,'Detalhe Por UC'!$R:$R,'Infos Clientes'!AO$2)=0,"", SUMIFS('Detalhe Por UC'!$AB:$AB,'Detalhe Por UC'!$C:$C,'Infos Clientes'!$B49,'Detalhe Por UC'!$R:$R,'Infos Clientes'!AO$2) +SUMIFS('Detalhe Por UC'!$AC:$AC,'Detalhe Por UC'!$C:$C,'Infos Clientes'!$B49,'Detalhe Por UC'!$R:$R,'Infos Clientes'!AO$2)) -> 271 | AP49: =IF(SUMIFS('Detalhe Por UC'!$AB:$AB,'Detalhe Por UC'!$C:$C,'Infos Clientes'!$B49,'Detalhe Por UC'!$R:$R,'Infos Clientes'!AP$2)=0,"", SUMIFS('Detalhe Por UC'!$AB:$AB,'Detalhe Por UC'!$C:$C,'Infos Clientes'!$B49,'Detalhe Por UC'!$R:$R,'Infos Clientes'!AP$2) +SUMIFS('Detalhe Por UC'!$AC:$AC,'Detalhe Por UC'!$C:$C,'Infos Clientes'!$B49,'Detalhe Por UC'!$R:$R,'Infos Clientes'!AP$2)) -> 239 | AQ49: =IF(SUMIFS('Detalhe Por UC'!$AB:$AB,'Detalhe Por UC'!$C:$C,'Infos Clientes'!$B49,'Detalhe Por UC'!$R:$R,'Infos Clientes'!AQ$2)=0,"", SUMIFS('Detalhe Por UC'!$AB:$AB,'Detalhe Por UC'!$C:$C,'Infos Clientes'!$B49,'Detalhe Por UC'!$R:$R,'Infos Clientes'!AQ$2) +SUMIFS('Detalhe Por UC'!$AC:$AC,'Detalhe Por UC'!$C:$C,'Infos Clientes'!$B49,'Detalhe Por UC'!$R:$R,'Infos Clientes'!AQ$2)) -> 292 | ... AU49: =IF(SUMIFS('Detalhe Por UC'!$AB:$AB,'Detalhe Por UC'!$C:$C,'Infos Clientes'!$B49,'Detalhe Por UC'!$R:$R,'Infos Clientes'!AU$2)=0,"", SUMIFS('Detalhe Por UC'!$AB:$AB,'Detalhe Por UC'!$C:$C,'Infos Clientes'!$B49,'Detalhe Por UC'!$R:$R,'Infos Clientes'!AU$2) +SUMIFS('Detalhe Por UC'!$AC:$AC,'Detalhe Por UC'!$C:$C,'Infos Clientes'!$B49,'Detalhe Por UC'!$R:$R,'Infos Clientes'!AU$2))
B50: 10/1130988-7 | C50: =ROW(F50) -> 50 | D50: IGREJA DO EVANGELHO QUADRANGULAR | E50: 371 | F50: 62.955.505/0408-94 | G50: iequadrangular.pm@gmail.com | H50: =B50 -> 10/1130988-7 | I50: BT | J50: bifasico | K50: GIROSSOL III | M50: 0.25 | Q50: =IF(_xlfn.MINIFS('Detalhe Por UC'!R:R,'Detalhe Por UC'!C:C,B50,'Detalhe Por UC'!AD:AD,">"&0)=0,"",_xlfn.MINIFS('Detalhe Por UC'!R:R,'Detalhe Por UC'!C:C,B50,'Detalhe Por UC'!AD:AD,">"&0)) -> 45658 | R50: =IF(P50<>"ATIVO",0, IF(OR(Q50="",Q50=0,O50=0),O50, O50-ROUND((MAX('Detalhe Por UC'!R:R) -Q50)/(365/12),0))) -> 0 | T50: 238.54545 | U50: =IFERROR((SUMIFS(W50:CN50,$W$2:$CN$2,">"&$Q$1-365,$W$2:$CN$2,"<="&$Q$1)/COUNTIFS(W50:CN50,">="&0,$W$2:$CN$2,">"&$Q$1-365,$W$2:$CN$2,"<="&$Q$1)),"") -> 238.33333 | X50: 305 | Y50: 296 | Z50: 297 | AA50: 302 | AB50: 0 | AC50: 243 | AD50: 134 | AE50: 140 | AF50: 142 | AG50: 187 | AH50: 234 | AI50: 299 | AJ50: =IF(SUMIFS('Detalhe Por UC'!$AB:$AB,'Detalhe Por UC'!$C:$C,'Infos Clientes'!$B50,'Detalhe Por UC'!$R:$R,'Infos Clientes'!AJ$2)=0,"", SUMIFS('Detalhe Por UC'!$AB:$AB,'Detalhe Por UC'!$C:$C,'Infos Clientes'!$B50,'Detalhe Por UC'!$R:$R,'Infos Clientes'!AJ$2) +SUMIFS('Detalhe Por UC'!$AC:$AC,'Detalhe Por UC'!$C:$C,'Infos Clientes'!$B50,'Detalhe Por UC'!$R:$R,'Infos Clientes'!AJ$2)) -> 350 | AK50: =IF(SUMIFS('Detalhe Por UC'!$AB:$AB,'Detalhe Por UC'!$C:$C,'Infos Clientes'!$B50,'Detalhe Por UC'!$R:$R,'Infos Clientes'!AK$2)=0,"", SUMIFS('Detalhe Por UC'!$AB:$AB,'Detalhe Por UC'!$C:$C,'Infos Clientes'!$B50,'Detalhe Por UC'!$R:$R,'Infos Clientes'!AK$2) +SUMIFS('Detalhe Por UC'!$AC:$AC,'Detalhe Por UC'!$C:$C,'Infos Clientes'!$B50,'Detalhe Por UC'!$R:$R,'Infos Clientes'!AK$2)) -> 321 | AL50: =IF(SUMIFS('Detalhe Por UC'!$AB:$AB,'Detalhe Por UC'!$C:$C,'Infos Clientes'!$B50,'Detalhe Por UC'!$R:$R,'Infos Clientes'!AL$2)=0,"", SUMIFS('Detalhe Por UC'!$AB:$AB,'Detalhe Por UC'!$C:$C,'Infos Clientes'!$B50,'Detalhe Por UC'!$R:$R,'Infos Clientes'!AL$2) +SUMIFS('Detalhe Por UC'!$AC:$AC,'Detalhe Por UC'!$C:$C,'Infos Clientes'!$B50,'Detalhe Por UC'!$R:$R,'Infos Clientes'!AL$2)) -> 331 | AM50: =IF(SUMIFS('Detalhe Por UC'!$AB:$AB,'Detalhe Por UC'!$C:$C,'Infos Clientes'!$B50,'Detalhe Por UC'!$R:$R,'Infos Clientes'!AM$2)=0,"", SUMIFS('Detalhe Por UC'!$AB:$AB,'Detalhe Por UC'!$C:$C,'Infos Clientes'!$B50,'Detalhe Por UC'!$R:$R,'Infos Clientes'!AM$2) +SUMIFS('Detalhe Por UC'!$AC:$AC,'Detalhe Por UC'!$C:$C,'Infos Clientes'!$B50,'Detalhe Por UC'!$R:$R,'Infos Clientes'!AM$2)) -> 235 | AN50: =IF(SUMIFS('Detalhe Por UC'!$AB:$AB,'Detalhe Por UC'!$C:$C,'Infos Clientes'!$B50,'Detalhe Por UC'!$R:$R,'Infos Clientes'!AN$2)=0,"", SUMIFS('Detalhe Por UC'!$AB:$AB,'Detalhe Por UC'!$C:$C,'Infos Clientes'!$B50,'Detalhe Por UC'!$R:$R,'Infos Clientes'!AN$2) +SUMIFS('Detalhe Por UC'!$AC:$AC,'Detalhe Por UC'!$C:$C,'Infos Clientes'!$B50,'Detalhe Por UC'!$R:$R,'Infos Clientes'!AN$2)) -> 290 | AO50: =IF(SUMIFS('Detalhe Por UC'!$AB:$AB,'Detalhe Por UC'!$C:$C,'Infos Clientes'!$B50,'Detalhe Por UC'!$R:$R,'Infos Clientes'!AO$2)=0,"", SUMIFS('Detalhe Por UC'!$AB:$AB,'Detalhe Por UC'!$C:$C,'Infos Clientes'!$B50,'Detalhe Por UC'!$R:$R,'Infos Clientes'!AO$2) +SUMIFS('Detalhe Por UC'!$AC:$AC,'Detalhe Por UC'!$C:$C,'Infos Clientes'!$B50,'Detalhe Por UC'!$R:$R,'Infos Clientes'!AO$2)) -> 89 | AP50: =IF(SUMIFS('Detalhe Por UC'!$AB:$AB,'Detalhe Por UC'!$C:$C,'Infos Clientes'!$B50,'Detalhe Por UC'!$R:$R,'Infos Clientes'!AP$2)=0,"", SUMIFS('Detalhe Por UC'!$AB:$AB,'Detalhe Por UC'!$C:$C,'Infos Clientes'!$B50,'Detalhe Por UC'!$R:$R,'Infos Clientes'!AP$2) +SUMIFS('Detalhe Por UC'!$AC:$AC,'Detalhe Por UC'!$C:$C,'Infos Clientes'!$B50,'Detalhe Por UC'!$R:$R,'Infos Clientes'!AP$2)) -> 93 | AQ50: =IF(SUMIFS('Detalhe Por UC'!$AB:$AB,'Detalhe Por UC'!$C:$C,'Infos Clientes'!$B50,'Detalhe Por UC'!$R:$R,'Infos Clientes'!AQ$2)=0,"", SUMIFS('Detalhe Por UC'!$AB:$AB,'Detalhe Por UC'!$C:$C,'Infos Clientes'!$B50,'Detalhe Por UC'!$R:$R,'Infos Clientes'!AQ$2) +SUMIFS('Detalhe Por UC'!$AC:$AC,'Detalhe Por UC'!$C:$C,'Infos Clientes'!$B50,'Detalhe Por UC'!$R:$R,'Infos Clientes'!AQ$2)) -> 150 | ... AU50: =IF(SUMIFS('Detalhe Por UC'!$AB:$AB,'Detalhe Por UC'!$C:$C,'Infos Clientes'!$B50,'Detalhe Por UC'!$R:$R,'Infos Clientes'!AU$2)=0,"", SUMIFS('Detalhe Por UC'!$AB:$AB,'Detalhe Por UC'!$C:$C,'Infos Clientes'!$B50,'Detalhe Por UC'!$R:$R,'Infos Clientes'!AU$2) +SUMIFS('Detalhe Por UC'!$AC:$AC,'Detalhe Por UC'!$C:$C,'Infos Clientes'!$B50,'Detalhe Por UC'!$R:$R,'Infos Clientes'!AU$2))
B51: 10/1266128-6 | C51: =ROW(F51) -> 51 | D51: IGREJA DO EVANGELHO QUADRANGULAR | E51: 306 | F51: 62.955.505/3793-95 | G51: auxiliar.cedms@gmail.com | H51: =B51 -> 10/1266128-6 | I51: BT | J51: trifasico | K51: GIROSSOL III | M51: 0.25 | Q51: =IF(_xlfn.MINIFS('Detalhe Por UC'!R:R,'Detalhe Por UC'!C:C,B51,'Detalhe Por UC'!AD:AD,">"&0)=0,"",_xlfn.MINIFS('Detalhe Por UC'!R:R,'Detalhe Por UC'!C:C,B51,'Detalhe Por UC'!AD:AD,">"&0)) -> 45658 | R51: =IF(P51<>"ATIVO",0, IF(OR(Q51="",Q51=0,O51=0),O51, O51-ROUND((MAX('Detalhe Por UC'!R:R) -Q51)/(365/12),0))) -> 0 | T51: 398.18182 | U51: =IFERROR((SUMIFS(W51:CN51,$W$2:$CN$2,">"&$Q$1-365,$W$2:$CN$2,"<="&$Q$1)/COUNTIFS(W51:CN51,">="&0,$W$2:$CN$2,">"&$Q$1-365,$W$2:$CN$2,"<="&$Q$1)),"") -> 368.83333 | X51: 420 | Y51: 540 | Z51: 510 | AA51: 450 | AB51: 0 | AC51: 290 | AD51: 230 | AE51: 250 | AF51: 330 | AG51: 450 | AH51: 370 | AI51: 440 | AJ51: =IF(SUMIFS('Detalhe Por UC'!$AB:$AB,'Detalhe Por UC'!$C:$C,'Infos Clientes'!$B51,'Detalhe Por UC'!$R:$R,'Infos Clientes'!AJ$2)=0,"", SUMIFS('Detalhe Por UC'!$AB:$AB,'Detalhe Por UC'!$C:$C,'Infos Clientes'!$B51,'Detalhe Por UC'!$R:$R,'Infos Clientes'!AJ$2) +SUMIFS('Detalhe Por UC'!$AC:$AC,'Detalhe Por UC'!$C:$C,'Infos Clientes'!$B51,'Detalhe Por UC'!$R:$R,'Infos Clientes'!AJ$2)) -> 520 | AK51: =IF(SUMIFS('Detalhe Por UC'!$AB:$AB,'Detalhe Por UC'!$C:$C,'Infos Clientes'!$B51,'Detalhe Por UC'!$R:$R,'Infos Clientes'!AK$2)=0,"", SUMIFS('Detalhe Por UC'!$AB:$AB,'Detalhe Por UC'!$C:$C,'Infos Clientes'!$B51,'Detalhe Por UC'!$R:$R,'Infos Clientes'!AK$2) +SUMIFS('Detalhe Por UC'!$AC:$AC,'Detalhe Por UC'!$C:$C,'Infos Clientes'!$B51,'Detalhe Por UC'!$R:$R,'Infos Clientes'!AK$2)) -> 510 | AL51: =IF(SUMIFS('Detalhe Por UC'!$AB:$AB,'Detalhe Por UC'!$C:$C,'Infos Clientes'!$B51,'Detalhe Por UC'!$R:$R,'Infos Clientes'!AL$2)=0,"", SUMIFS('Detalhe Por UC'!$AB:$AB,'Detalhe Por UC'!$C:$C,'Infos Clientes'!$B51,'Detalhe Por UC'!$R:$R,'Infos Clientes'!AL$2) +SUMIFS('Detalhe Por UC'!$AC:$AC,'Detalhe Por UC'!$C:$C,'Infos Clientes'!$B51,'Detalhe Por UC'!$R:$R,'Infos Clientes'!AL$2)) -> 460 | AM51: =IF(SUMIFS('Detalhe Por UC'!$AB:$AB,'Detalhe Por UC'!$C:$C,'Infos Clientes'!$B51,'Detalhe Por UC'!$R:$R,'Infos Clientes'!AM$2)=0,"", SUMIFS('Detalhe Por UC'!$AB:$AB,'Detalhe Por UC'!$C:$C,'Infos Clientes'!$B51,'Detalhe Por UC'!$R:$R,'Infos Clientes'!AM$2) +SUMIFS('Detalhe Por UC'!$AC:$AC,'Detalhe Por UC'!$C:$C,'Infos Clientes'!$B51,'Detalhe Por UC'!$R:$R,'Infos Clientes'!AM$2)) -> 410 | AN51: =IF(SUMIFS('Detalhe Por UC'!$AB:$AB,'Detalhe Por UC'!$C:$C,'Infos Clientes'!$B51,'Detalhe Por UC'!$R:$R,'Infos Clientes'!AN$2)=0,"", SUMIFS('Detalhe Por UC'!$AB:$AB,'Detalhe Por UC'!$C:$C,'Infos Clientes'!$B51,'Detalhe Por UC'!$R:$R,'Infos Clientes'!AN$2) +SUMIFS('Detalhe Por UC'!$AC:$AC,'Detalhe Por UC'!$C:$C,'Infos Clientes'!$B51,'Detalhe Por UC'!$R:$R,'Infos Clientes'!AN$2)) -> 290 | AO51: =IF(SUMIFS('Detalhe Por UC'!$AB:$AB,'Detalhe Por UC'!$C:$C,'Infos Clientes'!$B51,'Detalhe Por UC'!$R:$R,'Infos Clientes'!AO$2)=0,"", SUMIFS('Detalhe Por UC'!$AB:$AB,'Detalhe Por UC'!$C:$C,'Infos Clientes'!$B51,'Detalhe Por UC'!$R:$R,'Infos Clientes'!AO$2) +SUMIFS('Detalhe Por UC'!$AC:$AC,'Detalhe Por UC'!$C:$C,'Infos Clientes'!$B51,'Detalhe Por UC'!$R:$R,'Infos Clientes'!AO$2)) -> 396 | AP51: =IF(SUMIFS('Detalhe Por UC'!$AB:$AB,'Detalhe Por UC'!$C:$C,'Infos Clientes'!$B51,'Detalhe Por UC'!$R:$R,'Infos Clientes'!AP$2)=0,"", SUMIFS('Detalhe Por UC'!$AB:$AB,'Detalhe Por UC'!$C:$C,'Infos Clientes'!$B51,'Detalhe Por UC'!$R:$R,'Infos Clientes'!AP$2) +SUMIFS('Detalhe Por UC'!$AC:$AC,'Detalhe Por UC'!$C:$C,'Infos Clientes'!$B51,'Detalhe Por UC'!$R:$R,'Infos Clientes'!AP$2)) -> 150 | AQ51: =IF(SUMIFS('Detalhe Por UC'!$AB:$AB,'Detalhe Por UC'!$C:$C,'Infos Clientes'!$B51,'Detalhe Por UC'!$R:$R,'Infos Clientes'!AQ$2)=0,"", SUMIFS('Detalhe Por UC'!$AB:$AB,'Detalhe Por UC'!$C:$C,'Infos Clientes'!$B51,'Detalhe Por UC'!$R:$R,'Infos Clientes'!AQ$2) +SUMIFS('Detalhe Por UC'!$AC:$AC,'Detalhe Por UC'!$C:$C,'Infos Clientes'!$B51,'Detalhe Por UC'!$R:$R,'Infos Clientes'!AQ$2)) -> 190 | ... AU51: =IF(SUMIFS('Detalhe Por UC'!$AB:$AB,'Detalhe Por UC'!$C:$C,'Infos Clientes'!$B51,'Detalhe Por UC'!$R:$R,'Infos Clientes'!AU$2)=0,"", SUMIFS('Detalhe Por UC'!$AB:$AB,'Detalhe Por UC'!$C:$C,'Infos Clientes'!$B51,'Detalhe Por UC'!$R:$R,'Infos Clientes'!AU$2) +SUMIFS('Detalhe Por UC'!$AC:$AC,'Detalhe Por UC'!$C:$C,'Infos Clientes'!$B51,'Detalhe Por UC'!$R:$R,'Infos Clientes'!AU$2))
B52: 10/127464-6 | C52: =ROW(F52) -> 52 | D52: IGREJA DO EVANGELHO QUADRANGULAR | E52: 360 | F52: 62.955.505/3311-98 | G52: silvio.fonseca@masonagro.com.br | H52: =B52 -> 10/127464-6 | I52: BT | J52: trifasico | K52: GIROSSOL III | M52: 0.25 | Q52: =IF(_xlfn.MINIFS('Detalhe Por UC'!R:R,'Detalhe Por UC'!C:C,B52,'Detalhe Por UC'!AD:AD,">"&0)=0,"",_xlfn.MINIFS('Detalhe Por UC'!R:R,'Detalhe Por UC'!C:C,B52,'Detalhe Por UC'!AD:AD,">"&0)) -> 45658 | R52: =IF(P52<>"ATIVO",0, IF(OR(Q52="",Q52=0,O52=0),O52, O52-ROUND((MAX('Detalhe Por UC'!R:R) -Q52)/(365/12),0))) -> 0 | T52: 471.63636 | U52: =IFERROR((SUMIFS(W52:CN52,$W$2:$CN$2,">"&$Q$1-365,$W$2:$CN$2,"<="&$Q$1)/COUNTIFS(W52:CN52,">="&0,$W$2:$CN$2,">"&$Q$1-365,$W$2:$CN$2,"<="&$Q$1)),"") -> 486.41667 | X52: 399 | Y52: 533 | Z52: 437 | AA52: 574 | AB52: 0 | AC52: 261 | AD52: 385 | AE52: 433 | AF52: 439 | AG52: 528 | AH52: 584 | AI52: 468 | AJ52: =IF(SUMIFS('Detalhe Por UC'!$AB:$AB,'Detalhe Por UC'!$C:$C,'Infos Clientes'!$B52,'Detalhe Por UC'!$R:$R,'Infos Clientes'!AJ$2)=0,"", SUMIFS('Detalhe Por UC'!$AB:$AB,'Detalhe Por UC'!$C:$C,'Infos Clientes'!$B52,'Detalhe Por UC'!$R:$R,'Infos Clientes'!AJ$2) +SUMIFS('Detalhe Por UC'!$AC:$AC,'Detalhe Por UC'!$C:$C,'Infos Clientes'!$B52,'Detalhe Por UC'!$R:$R,'Infos Clientes'!AJ$2)) -> 546 | AK52: =IF(SUMIFS('Detalhe Por UC'!$AB:$AB,'Detalhe Por UC'!$C:$C,'Infos Clientes'!$B52,'Detalhe Por UC'!$R:$R,'Infos Clientes'!AK$2)=0,"", SUMIFS('Detalhe Por UC'!$AB:$AB,'Detalhe Por UC'!$C:$C,'Infos Clientes'!$B52,'Detalhe Por UC'!$R:$R,'Infos Clientes'!AK$2) +SUMIFS('Detalhe Por UC'!$AC:$AC,'Detalhe Por UC'!$C:$C,'Infos Clientes'!$B52,'Detalhe Por UC'!$R:$R,'Infos Clientes'!AK$2)) -> 531 | AL52: =IF(SUMIFS('Detalhe Por UC'!$AB:$AB,'Detalhe Por UC'!$C:$C,'Infos Clientes'!$B52,'Detalhe Por UC'!$R:$R,'Infos Clientes'!AL$2)=0,"", SUMIFS('Detalhe Por UC'!$AB:$AB,'Detalhe Por UC'!$C:$C,'Infos Clientes'!$B52,'Detalhe Por UC'!$R:$R,'Infos Clientes'!AL$2) +SUMIFS('Detalhe Por UC'!$AC:$AC,'Detalhe Por UC'!$C:$C,'Infos Clientes'!$B52,'Detalhe Por UC'!$R:$R,'Infos Clientes'!AL$2)) -> 537 | AM52: =IF(SUMIFS('Detalhe Por UC'!$AB:$AB,'Detalhe Por UC'!$C:$C,'Infos Clientes'!$B52,'Detalhe Por UC'!$R:$R,'Infos Clientes'!AM$2)=0,"", SUMIFS('Detalhe Por UC'!$AB:$AB,'Detalhe Por UC'!$C:$C,'Infos Clientes'!$B52,'Detalhe Por UC'!$R:$R,'Infos Clientes'!AM$2) +SUMIFS('Detalhe Por UC'!$AC:$AC,'Detalhe Por UC'!$C:$C,'Infos Clientes'!$B52,'Detalhe Por UC'!$R:$R,'Infos Clientes'!AM$2)) -> 472 | AN52: =IF(SUMIFS('Detalhe Por UC'!$AB:$AB,'Detalhe Por UC'!$C:$C,'Infos Clientes'!$B52,'Detalhe Por UC'!$R:$R,'Infos Clientes'!AN$2)=0,"", SUMIFS('Detalhe Por UC'!$AB:$AB,'Detalhe Por UC'!$C:$C,'Infos Clientes'!$B52,'Detalhe Por UC'!$R:$R,'Infos Clientes'!AN$2) +SUMIFS('Detalhe Por UC'!$AC:$AC,'Detalhe Por UC'!$C:$C,'Infos Clientes'!$B52,'Detalhe Por UC'!$R:$R,'Infos Clientes'!AN$2)) -> 594 | AO52: =IF(SUMIFS('Detalhe Por UC'!$AB:$AB,'Detalhe Por UC'!$C:$C,'Infos Clientes'!$B52,'Detalhe Por UC'!$R:$R,'Infos Clientes'!AO$2)=0,"", SUMIFS('Detalhe Por UC'!$AB:$AB,'Detalhe Por UC'!$C:$C,'Infos Clientes'!$B52,'Detalhe Por UC'!$R:$R,'Infos Clientes'!AO$2) +SUMIFS('Detalhe Por UC'!$AC:$AC,'Detalhe Por UC'!$C:$C,'Infos Clientes'!$B52,'Detalhe Por UC'!$R:$R,'Infos Clientes'!AO$2)) -> 376 | AP52: =IF(SUMIFS('Detalhe Por UC'!$AB:$AB,'Detalhe Por UC'!$C:$C,'Infos Clientes'!$B52,'Detalhe Por UC'!$R:$R,'Infos Clientes'!AP$2)=0,"", SUMIFS('Detalhe Por UC'!$AB:$AB,'Detalhe Por UC'!$C:$C,'Infos Clientes'!$B52,'Detalhe Por UC'!$R:$R,'Infos Clientes'!AP$2) +SUMIFS('Detalhe Por UC'!$AC:$AC,'Detalhe Por UC'!$C:$C,'Infos Clientes'!$B52,'Detalhe Por UC'!$R:$R,'Infos Clientes'!AP$2)) -> 345 | AQ52: =IF(SUMIFS('Detalhe Por UC'!$AB:$AB,'Detalhe Por UC'!$C:$C,'Infos Clientes'!$B52,'Detalhe Por UC'!$R:$R,'Infos Clientes'!AQ$2)=0,"", SUMIFS('Detalhe Por UC'!$AB:$AB,'Detalhe Por UC'!$C:$C,'Infos Clientes'!$B52,'Detalhe Por UC'!$R:$R,'Infos Clientes'!AQ$2) +SUMIFS('Detalhe Por UC'!$AC:$AC,'Detalhe Por UC'!$C:$C,'Infos Clientes'!$B52,'Detalhe Por UC'!$R:$R,'Infos Clientes'!AQ$2)) -> 320 | ... AU52: =IF(SUMIFS('Detalhe Por UC'!$AB:$AB,'Detalhe Por UC'!$C:$C,'Infos Clientes'!$B52,'Detalhe Por UC'!$R:$R,'Infos Clientes'!AU$2)=0,"", SUMIFS('Detalhe Por UC'!$AB:$AB,'Detalhe Por UC'!$C:$C,'Infos Clientes'!$B52,'Detalhe Por UC'!$R:$R,'Infos Clientes'!AU$2) +SUMIFS('Detalhe Por UC'!$AC:$AC,'Detalhe Por UC'!$C:$C,'Infos Clientes'!$B52,'Detalhe Por UC'!$R:$R,'Infos Clientes'!AU$2))
B53: 10/1288241-1 | C53: =ROW(F53) -> 53 | D53: IGREJA DO EVANGELHO QUADRANGULAR | E53: 306 | F53: 62.955.505/3358-51 | G53: auxiliar.cedms@gmail.com | H53: =B53 -> 10/1288241-1 | I53: BT | J53: trifasico | K53: GIROSSOL III | M53: 0.25 | Q53: =IF(_xlfn.MINIFS('Detalhe Por UC'!R:R,'Detalhe Por UC'!C:C,B53,'Detalhe Por UC'!AD:AD,">"&0)=0,"",_xlfn.MINIFS('Detalhe Por UC'!R:R,'Detalhe Por UC'!C:C,B53,'Detalhe Por UC'!AD:AD,">"&0)) -> 45658 | R53: =IF(P53<>"ATIVO",0, IF(OR(Q53="",Q53=0,O53=0),O53, O53-ROUND((MAX('Detalhe Por UC'!R:R) -Q53)/(365/12),0))) -> 0 | T53: 209.54545 | U53: =IFERROR((SUMIFS(W53:CN53,$W$2:$CN$2,">"&$Q$1-365,$W$2:$CN$2,"<="&$Q$1)/COUNTIFS(W53:CN53,">="&0,$W$2:$CN$2,">"&$Q$1-365,$W$2:$CN$2,"<="&$Q$1)),"") -> 237.16667 | X53: 168 | Y53: 234 | Z53: 238 | AA53: 231 | AB53: 0 | AC53: 187 | AD53: 162 | AE53: 159 | AF53: 187 | AG53: 219 | AH53: 257 | AI53: 226 | AJ53: =IF(SUMIFS('Detalhe Por UC'!$AB:$AB,'Detalhe Por UC'!$C:$C,'Infos Clientes'!$B53,'Detalhe Por UC'!$R:$R,'Infos Clientes'!AJ$2)=0,"", SUMIFS('Detalhe Por UC'!$AB:$AB,'Detalhe Por UC'!$C:$C,'Infos Clientes'!$B53,'Detalhe Por UC'!$R:$R,'Infos Clientes'!AJ$2) +SUMIFS('Detalhe Por UC'!$AC:$AC,'Detalhe Por UC'!$C:$C,'Infos Clientes'!$B53,'Detalhe Por UC'!$R:$R,'Infos Clientes'!AJ$2)) -> 205 | AK53: =IF(SUMIFS('Detalhe Por UC'!$AB:$AB,'Detalhe Por UC'!$C:$C,'Infos Clientes'!$B53,'Detalhe Por UC'!$R:$R,'Infos Clientes'!AK$2)=0,"", SUMIFS('Detalhe Por UC'!$AB:$AB,'Detalhe Por UC'!$C:$C,'Infos Clientes'!$B53,'Detalhe Por UC'!$R:$R,'Infos Clientes'!AK$2) +SUMIFS('Detalhe Por UC'!$AC:$AC,'Detalhe Por UC'!$C:$C,'Infos Clientes'!$B53,'Detalhe Por UC'!$R:$R,'Infos Clientes'!AK$2)) -> 253 | AL53: =IF(SUMIFS('Detalhe Por UC'!$AB:$AB,'Detalhe Por UC'!$C:$C,'Infos Clientes'!$B53,'Detalhe Por UC'!$R:$R,'Infos Clientes'!AL$2)=0,"", SUMIFS('Detalhe Por UC'!$AB:$AB,'Detalhe Por UC'!$C:$C,'Infos Clientes'!$B53,'Detalhe Por UC'!$R:$R,'Infos Clientes'!AL$2) +SUMIFS('Detalhe Por UC'!$AC:$AC,'Detalhe Por UC'!$C:$C,'Infos Clientes'!$B53,'Detalhe Por UC'!$R:$R,'Infos Clientes'!AL$2)) -> 248 | AM53: =IF(SUMIFS('Detalhe Por UC'!$AB:$AB,'Detalhe Por UC'!$C:$C,'Infos Clientes'!$B53,'Detalhe Por UC'!$R:$R,'Infos Clientes'!AM$2)=0,"", SUMIFS('Detalhe Por UC'!$AB:$AB,'Detalhe Por UC'!$C:$C,'Infos Clientes'!$B53,'Detalhe Por UC'!$R:$R,'Infos Clientes'!AM$2) +SUMIFS('Detalhe Por UC'!$AC:$AC,'Detalhe Por UC'!$C:$C,'Infos Clientes'!$B53,'Detalhe Por UC'!$R:$R,'Infos Clientes'!AM$2)) -> 252 | AN53: =IF(SUMIFS('Detalhe Por UC'!$AB:$AB,'Detalhe Por UC'!$C:$C,'Infos Clientes'!$B53,'Detalhe Por UC'!$R:$R,'Infos Clientes'!AN$2)=0,"", SUMIFS('Detalhe Por UC'!$AB:$AB,'Detalhe Por UC'!$C:$C,'Infos Clientes'!$B53,'Detalhe Por UC'!$R:$R,'Infos Clientes'!AN$2) +SUMIFS('Detalhe Por UC'!$AC:$AC,'Detalhe Por UC'!$C:$C,'Infos Clientes'!$B53,'Detalhe Por UC'!$R:$R,'Infos Clientes'!AN$2)) -> 250 | AO53: =IF(SUMIFS('Detalhe Por UC'!$AB:$AB,'Detalhe Por UC'!$C:$C,'Infos Clientes'!$B53,'Detalhe Por UC'!$R:$R,'Infos Clientes'!AO$2)=0,"", SUMIFS('Detalhe Por UC'!$AB:$AB,'Detalhe Por UC'!$C:$C,'Infos Clientes'!$B53,'Detalhe Por UC'!$R:$R,'Infos Clientes'!AO$2) +SUMIFS('Detalhe Por UC'!$AC:$AC,'Detalhe Por UC'!$C:$C,'Infos Clientes'!$B53,'Detalhe Por UC'!$R:$R,'Infos Clientes'!AO$2)) -> 203 | AP53: =IF(SUMIFS('Detalhe Por UC'!$AB:$AB,'Detalhe Por UC'!$C:$C,'Infos Clientes'!$B53,'Detalhe Por UC'!$R:$R,'Infos Clientes'!AP$2)=0,"", SUMIFS('Detalhe Por UC'!$AB:$AB,'Detalhe Por UC'!$C:$C,'Infos Clientes'!$B53,'Detalhe Por UC'!$R:$R,'Infos Clientes'!AP$2) +SUMIFS('Detalhe Por UC'!$AC:$AC,'Detalhe Por UC'!$C:$C,'Infos Clientes'!$B53,'Detalhe Por UC'!$R:$R,'Infos Clientes'!AP$2)) -> 175 | AQ53: =IF(SUMIFS('Detalhe Por UC'!$AB:$AB,'Detalhe Por UC'!$C:$C,'Infos Clientes'!$B53,'Detalhe Por UC'!$R:$R,'Infos Clientes'!AQ$2)=0,"", SUMIFS('Detalhe Por UC'!$AB:$AB,'Detalhe Por UC'!$C:$C,'Infos Clientes'!$B53,'Detalhe Por UC'!$R:$R,'Infos Clientes'!AQ$2) +SUMIFS('Detalhe Por UC'!$AC:$AC,'Detalhe Por UC'!$C:$C,'Infos Clientes'!$B53,'Detalhe Por UC'!$R:$R,'Infos Clientes'!AQ$2)) -> 230 | ... AU53: =IF(SUMIFS('Detalhe Por UC'!$AB:$AB,'Detalhe Por UC'!$C:$C,'Infos Clientes'!$B53,'Detalhe Por UC'!$R:$R,'Infos Clientes'!AU$2)=0,"", SUMIFS('Detalhe Por UC'!$AB:$AB,'Detalhe Por UC'!$C:$C,'Infos Clientes'!$B53,'Detalhe Por UC'!$R:$R,'Infos Clientes'!AU$2) +SUMIFS('Detalhe Por UC'!$AC:$AC,'Detalhe Por UC'!$C:$C,'Infos Clientes'!$B53,'Detalhe Por UC'!$R:$R,'Infos Clientes'!AU$2))
B54: 10/129490-9 | C54: =ROW(F54) -> 54 | D54: IGREJA DO EVANGELHO QUADRANGULAR | E54: 351 | F54: 62.955.505/4051-40 | G54: regiao351@bol.com.b | H54: =B54 -> 10/129490-9 | I54: BT | J54: bifasico | K54: GIROSSOL III | M54: 0.25 | Q54: =IF(_xlfn.MINIFS('Detalhe Por UC'!R:R,'Detalhe Por UC'!C:C,B54,'Detalhe Por UC'!AD:AD,">"&0)=0,"",_xlfn.MINIFS('Detalhe Por UC'!R:R,'Detalhe Por UC'!C:C,B54,'Detalhe Por UC'!AD:AD,">"&0)) -> 45658 | R54: =IF(P54<>"ATIVO",0, IF(OR(Q54="",Q54=0,O54=0),O54, O54-ROUND((MAX('Detalhe Por UC'!R:R) -Q54)/(365/12),0))) -> 0 | T54: 246.72727 | U54: =IFERROR((SUMIFS(W54:CN54,$W$2:$CN$2,">"&$Q$1-365,$W$2:$CN$2,"<="&$Q$1)/COUNTIFS(W54:CN54,">="&0,$W$2:$CN$2,">"&$Q$1-365,$W$2:$CN$2,"<="&$Q$1)),"") -> 273.33333 | X54: 174 | Y54: 220 | Z54: 253 | AA54: 233 | AB54: 0 | AC54: 206 | AD54: 147 | AE54: 203 | AF54: 265 | AG54: 294 | AH54: 306 | AI54: 301 | AJ54: =IF(SUMIFS('Detalhe Por UC'!$AB:$AB,'Detalhe Por UC'!$C:$C,'Infos Clientes'!$B54,'Detalhe Por UC'!$R:$R,'Infos Clientes'!AJ$2)=0,"", SUMIFS('Detalhe Por UC'!$AB:$AB,'Detalhe Por UC'!$C:$C,'Infos Clientes'!$B54,'Detalhe Por UC'!$R:$R,'Infos Clientes'!AJ$2) +SUMIFS('Detalhe Por UC'!$AC:$AC,'Detalhe Por UC'!$C:$C,'Infos Clientes'!$B54,'Detalhe Por UC'!$R:$R,'Infos Clientes'!AJ$2)) -> 286 | AK54: =IF(SUMIFS('Detalhe Por UC'!$AB:$AB,'Detalhe Por UC'!$C:$C,'Infos Clientes'!$B54,'Detalhe Por UC'!$R:$R,'Infos Clientes'!AK$2)=0,"", SUMIFS('Detalhe Por UC'!$AB:$AB,'Detalhe Por UC'!$C:$C,'Infos Clientes'!$B54,'Detalhe Por UC'!$R:$R,'Infos Clientes'!AK$2) +SUMIFS('Detalhe Por UC'!$AC:$AC,'Detalhe Por UC'!$C:$C,'Infos Clientes'!$B54,'Detalhe Por UC'!$R:$R,'Infos Clientes'!AK$2)) -> 324 | AL54: =IF(SUMIFS('Detalhe Por UC'!$AB:$AB,'Detalhe Por UC'!$C:$C,'Infos Clientes'!$B54,'Detalhe Por UC'!$R:$R,'Infos Clientes'!AL$2)=0,"", SUMIFS('Detalhe Por UC'!$AB:$AB,'Detalhe Por UC'!$C:$C,'Infos Clientes'!$B54,'Detalhe Por UC'!$R:$R,'Infos Clientes'!AL$2) +SUMIFS('Detalhe Por UC'!$AC:$AC,'Detalhe Por UC'!$C:$C,'Infos Clientes'!$B54,'Detalhe Por UC'!$R:$R,'Infos Clientes'!AL$2)) -> 315 | AM54: =IF(SUMIFS('Detalhe Por UC'!$AB:$AB,'Detalhe Por UC'!$C:$C,'Infos Clientes'!$B54,'Detalhe Por UC'!$R:$R,'Infos Clientes'!AM$2)=0,"", SUMIFS('Detalhe Por UC'!$AB:$AB,'Detalhe Por UC'!$C:$C,'Infos Clientes'!$B54,'Detalhe Por UC'!$R:$R,'Infos Clientes'!AM$2) +SUMIFS('Detalhe Por UC'!$AC:$AC,'Detalhe Por UC'!$C:$C,'Infos Clientes'!$B54,'Detalhe Por UC'!$R:$R,'Infos Clientes'!AM$2)) -> 287 | AN54: =IF(SUMIFS('Detalhe Por UC'!$AB:$AB,'Detalhe Por UC'!$C:$C,'Infos Clientes'!$B54,'Detalhe Por UC'!$R:$R,'Infos Clientes'!AN$2)=0,"", SUMIFS('Detalhe Por UC'!$AB:$AB,'Detalhe Por UC'!$C:$C,'Infos Clientes'!$B54,'Detalhe Por UC'!$R:$R,'Infos Clientes'!AN$2) +SUMIFS('Detalhe Por UC'!$AC:$AC,'Detalhe Por UC'!$C:$C,'Infos Clientes'!$B54,'Detalhe Por UC'!$R:$R,'Infos Clientes'!AN$2)) -> 252 | AO54: =IF(SUMIFS('Detalhe Por UC'!$AB:$AB,'Detalhe Por UC'!$C:$C,'Infos Clientes'!$B54,'Detalhe Por UC'!$R:$R,'Infos Clientes'!AO$2)=0,"", SUMIFS('Detalhe Por UC'!$AB:$AB,'Detalhe Por UC'!$C:$C,'Infos Clientes'!$B54,'Detalhe Por UC'!$R:$R,'Infos Clientes'!AO$2) +SUMIFS('Detalhe Por UC'!$AC:$AC,'Detalhe Por UC'!$C:$C,'Infos Clientes'!$B54,'Detalhe Por UC'!$R:$R,'Infos Clientes'!AO$2)) -> 268 | AP54: =IF(SUMIFS('Detalhe Por UC'!$AB:$AB,'Detalhe Por UC'!$C:$C,'Infos Clientes'!$B54,'Detalhe Por UC'!$R:$R,'Infos Clientes'!AP$2)=0,"", SUMIFS('Detalhe Por UC'!$AB:$AB,'Detalhe Por UC'!$C:$C,'Infos Clientes'!$B54,'Detalhe Por UC'!$R:$R,'Infos Clientes'!AP$2) +SUMIFS('Detalhe Por UC'!$AC:$AC,'Detalhe Por UC'!$C:$C,'Infos Clientes'!$B54,'Detalhe Por UC'!$R:$R,'Infos Clientes'!AP$2)) -> 218 | AQ54: =IF(SUMIFS('Detalhe Por UC'!$AB:$AB,'Detalhe Por UC'!$C:$C,'Infos Clientes'!$B54,'Detalhe Por UC'!$R:$R,'Infos Clientes'!AQ$2)=0,"", SUMIFS('Detalhe Por UC'!$AB:$AB,'Detalhe Por UC'!$C:$C,'Infos Clientes'!$B54,'Detalhe Por UC'!$R:$R,'Infos Clientes'!AQ$2) +SUMIFS('Detalhe Por UC'!$AC:$AC,'Detalhe Por UC'!$C:$C,'Infos Clientes'!$B54,'Detalhe Por UC'!$R:$R,'Infos Clientes'!AQ$2)) -> 225 | ... AU54: =IF(SUMIFS('Detalhe Por UC'!$AB:$AB,'Detalhe Por UC'!$C:$C,'Infos Clientes'!$B54,'Detalhe Por UC'!$R:$R,'Infos Clientes'!AU$2)=0,"", SUMIFS('Detalhe Por UC'!$AB:$AB,'Detalhe Por UC'!$C:$C,'Infos Clientes'!$B54,'Detalhe Por UC'!$R:$R,'Infos Clientes'!AU$2) +SUMIFS('Detalhe Por UC'!$AC:$AC,'Detalhe Por UC'!$C:$C,'Infos Clientes'!$B54,'Detalhe Por UC'!$R:$R,'Infos Clientes'!AU$2))
B55: 10/13786-9 | C55: =ROW(F55) -> 55 | D55: IGREJA DO EVANGELHO QUADRANGULAR | E55: 357 | F55: 62.955.505/1975-21 | G55: lilia-nlopes@hotmail.com; regiao.357@hotmail.com | H55: =B55 -> 10/13786-9 | I55: BT | J55: bifasico | K55: GIROSSOL III | M55: 0.25 | Q55: =IF(_xlfn.MINIFS('Detalhe Por UC'!R:R,'Detalhe Por UC'!C:C,B55,'Detalhe Por UC'!AD:AD,">"&0)=0,"",_xlfn.MINIFS('Detalhe Por UC'!R:R,'Detalhe Por UC'!C:C,B55,'Detalhe Por UC'!AD:AD,">"&0)) -> 45658 | R55: =IF(P55<>"ATIVO",0, IF(OR(Q55="",Q55=0,O55=0),O55, O55-ROUND((MAX('Detalhe Por UC'!R:R) -Q55)/(365/12),0))) -> 0 | T55: 278.36364 | U55: =IFERROR((SUMIFS(W55:CN55,$W$2:$CN$2,">"&$Q$1-365,$W$2:$CN$2,"<="&$Q$1)/COUNTIFS(W55:CN55,">="&0,$W$2:$CN$2,">"&$Q$1-365,$W$2:$CN$2,"<="&$Q$1)),"") -> 282.66667 | X55: 231 | Y55: 297 | Z55: 285 | AA55: 442 | AB55: 0 | AC55: 208 | AD55: 160 | AE55: 214 | AF55: 185 | AG55: 294 | AH55: 282 | AI55: 380 | AJ55: =IF(SUMIFS('Detalhe Por UC'!$AB:$AB,'Detalhe Por UC'!$C:$C,'Infos Clientes'!$B55,'Detalhe Por UC'!$R:$R,'Infos Clientes'!AJ$2)=0,"", SUMIFS('Detalhe Por UC'!$AB:$AB,'Detalhe Por UC'!$C:$C,'Infos Clientes'!$B55,'Detalhe Por UC'!$R:$R,'Infos Clientes'!AJ$2) +SUMIFS('Detalhe Por UC'!$AC:$AC,'Detalhe Por UC'!$C:$C,'Infos Clientes'!$B55,'Detalhe Por UC'!$R:$R,'Infos Clientes'!AJ$2)) -> 315 | AK55: =IF(SUMIFS('Detalhe Por UC'!$AB:$AB,'Detalhe Por UC'!$C:$C,'Infos Clientes'!$B55,'Detalhe Por UC'!$R:$R,'Infos Clientes'!AK$2)=0,"", SUMIFS('Detalhe Por UC'!$AB:$AB,'Detalhe Por UC'!$C:$C,'Infos Clientes'!$B55,'Detalhe Por UC'!$R:$R,'Infos Clientes'!AK$2) +SUMIFS('Detalhe Por UC'!$AC:$AC,'Detalhe Por UC'!$C:$C,'Infos Clientes'!$B55,'Detalhe Por UC'!$R:$R,'Infos Clientes'!AK$2)) -> 271 | AL55: =IF(SUMIFS('Detalhe Por UC'!$AB:$AB,'Detalhe Por UC'!$C:$C,'Infos Clientes'!$B55,'Detalhe Por UC'!$R:$R,'Infos Clientes'!AL$2)=0,"", SUMIFS('Detalhe Por UC'!$AB:$AB,'Detalhe Por UC'!$C:$C,'Infos Clientes'!$B55,'Detalhe Por UC'!$R:$R,'Infos Clientes'!AL$2) +SUMIFS('Detalhe Por UC'!$AC:$AC,'Detalhe Por UC'!$C:$C,'Infos Clientes'!$B55,'Detalhe Por UC'!$R:$R,'Infos Clientes'!AL$2)) -> 410 | AM55: =IF(SUMIFS('Detalhe Por UC'!$AB:$AB,'Detalhe Por UC'!$C:$C,'Infos Clientes'!$B55,'Detalhe Por UC'!$R:$R,'Infos Clientes'!AM$2)=0,"", SUMIFS('Detalhe Por UC'!$AB:$AB,'Detalhe Por UC'!$C:$C,'Infos Clientes'!$B55,'Detalhe Por UC'!$R:$R,'Infos Clientes'!AM$2) +SUMIFS('Detalhe Por UC'!$AC:$AC,'Detalhe Por UC'!$C:$C,'Infos Clientes'!$B55,'Detalhe Por UC'!$R:$R,'Infos Clientes'!AM$2)) -> 280 | AN55: =IF(SUMIFS('Detalhe Por UC'!$AB:$AB,'Detalhe Por UC'!$C:$C,'Infos Clientes'!$B55,'Detalhe Por UC'!$R:$R,'Infos Clientes'!AN$2)=0,"", SUMIFS('Detalhe Por UC'!$AB:$AB,'Detalhe Por UC'!$C:$C,'Infos Clientes'!$B55,'Detalhe Por UC'!$R:$R,'Infos Clientes'!AN$2) +SUMIFS('Detalhe Por UC'!$AC:$AC,'Detalhe Por UC'!$C:$C,'Infos Clientes'!$B55,'Detalhe Por UC'!$R:$R,'Infos Clientes'!AN$2)) -> 294 | AO55: =IF(SUMIFS('Detalhe Por UC'!$AB:$AB,'Detalhe Por UC'!$C:$C,'Infos Clientes'!$B55,'Detalhe Por UC'!$R:$R,'Infos Clientes'!AO$2)=0,"", SUMIFS('Detalhe Por UC'!$AB:$AB,'Detalhe Por UC'!$C:$C,'Infos Clientes'!$B55,'Detalhe Por UC'!$R:$R,'Infos Clientes'!AO$2) +SUMIFS('Detalhe Por UC'!$AC:$AC,'Detalhe Por UC'!$C:$C,'Infos Clientes'!$B55,'Detalhe Por UC'!$R:$R,'Infos Clientes'!AO$2)) -> 227 | AP55: =IF(SUMIFS('Detalhe Por UC'!$AB:$AB,'Detalhe Por UC'!$C:$C,'Infos Clientes'!$B55,'Detalhe Por UC'!$R:$R,'Infos Clientes'!AP$2)=0,"", SUMIFS('Detalhe Por UC'!$AB:$AB,'Detalhe Por UC'!$C:$C,'Infos Clientes'!$B55,'Detalhe Por UC'!$R:$R,'Infos Clientes'!AP$2) +SUMIFS('Detalhe Por UC'!$AC:$AC,'Detalhe Por UC'!$C:$C,'Infos Clientes'!$B55,'Detalhe Por UC'!$R:$R,'Infos Clientes'!AP$2)) -> 195 | AQ55: =IF(SUMIFS('Detalhe Por UC'!$AB:$AB,'Detalhe Por UC'!$C:$C,'Infos Clientes'!$B55,'Detalhe Por UC'!$R:$R,'Infos Clientes'!AQ$2)=0,"", SUMIFS('Detalhe Por UC'!$AB:$AB,'Detalhe Por UC'!$C:$C,'Infos Clientes'!$B55,'Detalhe Por UC'!$R:$R,'Infos Clientes'!AQ$2) +SUMIFS('Detalhe Por UC'!$AC:$AC,'Detalhe Por UC'!$C:$C,'Infos Clientes'!$B55,'Detalhe Por UC'!$R:$R,'Infos Clientes'!AQ$2)) -> 212 | ... AU55: =IF(SUMIFS('Detalhe Por UC'!$AB:$AB,'Detalhe Por UC'!$C:$C,'Infos Clientes'!$B55,'Detalhe Por UC'!$R:$R,'Infos Clientes'!AU$2)=0,"", SUMIFS('Detalhe Por UC'!$AB:$AB,'Detalhe Por UC'!$C:$C,'Infos Clientes'!$B55,'Detalhe Por UC'!$R:$R,'Infos Clientes'!AU$2) +SUMIFS('Detalhe Por UC'!$AC:$AC,'Detalhe Por UC'!$C:$C,'Infos Clientes'!$B55,'Detalhe Por UC'!$R:$R,'Infos Clientes'!AU$2))
B56: 10/142353-2 | C56: =ROW(F56) -> 56 | D56: IGREJA DO EVANGELHO QUADRANGULAR | E56: 358 | F56: 62.955.505/1138-75 | G56: regiao358ms@gmail.com | H56: =B56 -> 10/142353-2 | I56: BT | J56: bifasico | K56: GIROSSOL III | M56: 0.25 | Q56: =IF(_xlfn.MINIFS('Detalhe Por UC'!R:R,'Detalhe Por UC'!C:C,B56,'Detalhe Por UC'!AD:AD,">"&0)=0,"",_xlfn.MINIFS('Detalhe Por UC'!R:R,'Detalhe Por UC'!C:C,B56,'Detalhe Por UC'!AD:AD,">"&0)) -> 45658 | R56: =IF(P56<>"ATIVO",0, IF(OR(Q56="",Q56=0,O56=0),O56, O56-ROUND((MAX('Detalhe Por UC'!R:R) -Q56)/(365/12),0))) -> 0 | T56: 449.81818 | U56: =IFERROR((SUMIFS(W56:CN56,$W$2:$CN$2,">"&$Q$1-365,$W$2:$CN$2,"<="&$Q$1)/COUNTIFS(W56:CN56,">="&0,$W$2:$CN$2,">"&$Q$1-365,$W$2:$CN$2,"<="&$Q$1)),"") -> 431.75 | X56: 468 | Y56: 532 | Z56: 467 | AA56: 554 | AB56: 0 | AC56: 323 | AD56: 252 | AE56: 350 | AF56: 364 | AG56: 479 | AH56: 489 | AI56: 457 | AJ56: =IF(SUMIFS('Detalhe Por UC'!$AB:$AB,'Detalhe Por UC'!$C:$C,'Infos Clientes'!$B56,'Detalhe Por UC'!$R:$R,'Infos Clientes'!AJ$2)=0,"", SUMIFS('Detalhe Por UC'!$AB:$AB,'Detalhe Por UC'!$C:$C,'Infos Clientes'!$B56,'Detalhe Por UC'!$R:$R,'Infos Clientes'!AJ$2) +SUMIFS('Detalhe Por UC'!$AC:$AC,'Detalhe Por UC'!$C:$C,'Infos Clientes'!$B56,'Detalhe Por UC'!$R:$R,'Infos Clientes'!AJ$2)) -> 681 | AK56: =IF(SUMIFS('Detalhe Por UC'!$AB:$AB,'Detalhe Por UC'!$C:$C,'Infos Clientes'!$B56,'Detalhe Por UC'!$R:$R,'Infos Clientes'!AK$2)=0,"", SUMIFS('Detalhe Por UC'!$AB:$AB,'Detalhe Por UC'!$C:$C,'Infos Clientes'!$B56,'Detalhe Por UC'!$R:$R,'Infos Clientes'!AK$2) +SUMIFS('Detalhe Por UC'!$AC:$AC,'Detalhe Por UC'!$C:$C,'Infos Clientes'!$B56,'Detalhe Por UC'!$R:$R,'Infos Clientes'!AK$2)) -> 681 | AL56: =IF(SUMIFS('Detalhe Por UC'!$AB:$AB,'Detalhe Por UC'!$C:$C,'Infos Clientes'!$B56,'Detalhe Por UC'!$R:$R,'Infos Clientes'!AL$2)=0,"", SUMIFS('Detalhe Por UC'!$AB:$AB,'Detalhe Por UC'!$C:$C,'Infos Clientes'!$B56,'Detalhe Por UC'!$R:$R,'Infos Clientes'!AL$2) +SUMIFS('Detalhe Por UC'!$AC:$AC,'Detalhe Por UC'!$C:$C,'Infos Clientes'!$B56,'Detalhe Por UC'!$R:$R,'Infos Clientes'!AL$2)) -> 681 | AM56: =IF(SUMIFS('Detalhe Por UC'!$AB:$AB,'Detalhe Por UC'!$C:$C,'Infos Clientes'!$B56,'Detalhe Por UC'!$R:$R,'Infos Clientes'!AM$2)=0,"", SUMIFS('Detalhe Por UC'!$AB:$AB,'Detalhe Por UC'!$C:$C,'Infos Clientes'!$B56,'Detalhe Por UC'!$R:$R,'Infos Clientes'!AM$2) +SUMIFS('Detalhe Por UC'!$AC:$AC,'Detalhe Por UC'!$C:$C,'Infos Clientes'!$B56,'Detalhe Por UC'!$R:$R,'Infos Clientes'!AM$2)) -> 421 | AN56: =IF(SUMIFS('Detalhe Por UC'!$AB:$AB,'Detalhe Por UC'!$C:$C,'Infos Clientes'!$B56,'Detalhe Por UC'!$R:$R,'Infos Clientes'!AN$2)=0,"", SUMIFS('Detalhe Por UC'!$AB:$AB,'Detalhe Por UC'!$C:$C,'Infos Clientes'!$B56,'Detalhe Por UC'!$R:$R,'Infos Clientes'!AN$2) +SUMIFS('Detalhe Por UC'!$AC:$AC,'Detalhe Por UC'!$C:$C,'Infos Clientes'!$B56,'Detalhe Por UC'!$R:$R,'Infos Clientes'!AN$2)) -> 330 | AO56: =IF(SUMIFS('Detalhe Por UC'!$AB:$AB,'Detalhe Por UC'!$C:$C,'Infos Clientes'!$B56,'Detalhe Por UC'!$R:$R,'Infos Clientes'!AO$2)=0,"", SUMIFS('Detalhe Por UC'!$AB:$AB,'Detalhe Por UC'!$C:$C,'Infos Clientes'!$B56,'Detalhe Por UC'!$R:$R,'Infos Clientes'!AO$2) +SUMIFS('Detalhe Por UC'!$AC:$AC,'Detalhe Por UC'!$C:$C,'Infos Clientes'!$B56,'Detalhe Por UC'!$R:$R,'Infos Clientes'!AO$2)) -> 323 | AP56: =IF(SUMIFS('Detalhe Por UC'!$AB:$AB,'Detalhe Por UC'!$C:$C,'Infos Clientes'!$B56,'Detalhe Por UC'!$R:$R,'Infos Clientes'!AP$2)=0,"", SUMIFS('Detalhe Por UC'!$AB:$AB,'Detalhe Por UC'!$C:$C,'Infos Clientes'!$B56,'Detalhe Por UC'!$R:$R,'Infos Clientes'!AP$2) +SUMIFS('Detalhe Por UC'!$AC:$AC,'Detalhe Por UC'!$C:$C,'Infos Clientes'!$B56,'Detalhe Por UC'!$R:$R,'Infos Clientes'!AP$2)) -> 281 | AQ56: =IF(SUMIFS('Detalhe Por UC'!$AB:$AB,'Detalhe Por UC'!$C:$C,'Infos Clientes'!$B56,'Detalhe Por UC'!$R:$R,'Infos Clientes'!AQ$2)=0,"", SUMIFS('Detalhe Por UC'!$AB:$AB,'Detalhe Por UC'!$C:$C,'Infos Clientes'!$B56,'Detalhe Por UC'!$R:$R,'Infos Clientes'!AQ$2) +SUMIFS('Detalhe Por UC'!$AC:$AC,'Detalhe Por UC'!$C:$C,'Infos Clientes'!$B56,'Detalhe Por UC'!$R:$R,'Infos Clientes'!AQ$2)) -> 276 | ... AU56: =IF(SUMIFS('Detalhe Por UC'!$AB:$AB,'Detalhe Por UC'!$C:$C,'Infos Clientes'!$B56,'Detalhe Por UC'!$R:$R,'Infos Clientes'!AU$2)=0,"", SUMIFS('Detalhe Por UC'!$AB:$AB,'Detalhe Por UC'!$C:$C,'Infos Clientes'!$B56,'Detalhe Por UC'!$R:$R,'Infos Clientes'!AU$2) +SUMIFS('Detalhe Por UC'!$AC:$AC,'Detalhe Por UC'!$C:$C,'Infos Clientes'!$B56,'Detalhe Por UC'!$R:$R,'Infos Clientes'!AU$2))
B57: 10/15297-5 | C57: =ROW(F57) -> 57 | D57: IGREJA DO EVANGELHO QUADRANGULAR | E57: 357 | F57: 62.955.505/3124-87 | G57: pr-nilsoncastro@hotmail.com; regiao.357@hotmail.com | H57: =B57 -> 10/15297-5 | I57: BT | J57: trifasico | K57: GIROSSOL III | M57: 0.25 | Q57: =IF(_xlfn.MINIFS('Detalhe Por UC'!R:R,'Detalhe Por UC'!C:C,B57,'Detalhe Por UC'!AD:AD,">"&0)=0,"",_xlfn.MINIFS('Detalhe Por UC'!R:R,'Detalhe Por UC'!C:C,B57,'Detalhe Por UC'!AD:AD,">"&0)) -> 45658 | R57: =IF(P57<>"ATIVO",0, IF(OR(Q57="",Q57=0,O57=0),O57, O57-ROUND((MAX('Detalhe Por UC'!R:R) -Q57)/(365/12),0))) -> 0 | T57: 495.18182 | U57: =IFERROR((SUMIFS(W57:CN57,$W$2:$CN$2,">"&$Q$1-365,$W$2:$CN$2,"<="&$Q$1)/COUNTIFS(W57:CN57,">="&0,$W$2:$CN$2,">"&$Q$1-365,$W$2:$CN$2,"<="&$Q$1)),"") -> 528.58333 | X57: 909 | Y57: 592 | Z57: 554 | AA57: 645 | AB57: 0 | AC57: 306 | AD57: 244 | AE57: 469 | AF57: 304 | AG57: 496 | AH57: 499 | AI57: 850 | AJ57: =IF(SUMIFS('Detalhe Por UC'!$AB:$AB,'Detalhe Por UC'!$C:$C,'Infos Clientes'!$B57,'Detalhe Por UC'!$R:$R,'Infos Clientes'!AJ$2)=0,"", SUMIFS('Detalhe Por UC'!$AB:$AB,'Detalhe Por UC'!$C:$C,'Infos Clientes'!$B57,'Detalhe Por UC'!$R:$R,'Infos Clientes'!AJ$2) +SUMIFS('Detalhe Por UC'!$AC:$AC,'Detalhe Por UC'!$C:$C,'Infos Clientes'!$B57,'Detalhe Por UC'!$R:$R,'Infos Clientes'!AJ$2)) -> 488 | AK57: =IF(SUMIFS('Detalhe Por UC'!$AB:$AB,'Detalhe Por UC'!$C:$C,'Infos Clientes'!$B57,'Detalhe Por UC'!$R:$R,'Infos Clientes'!AK$2)=0,"", SUMIFS('Detalhe Por UC'!$AB:$AB,'Detalhe Por UC'!$C:$C,'Infos Clientes'!$B57,'Detalhe Por UC'!$R:$R,'Infos Clientes'!AK$2) +SUMIFS('Detalhe Por UC'!$AC:$AC,'Detalhe Por UC'!$C:$C,'Infos Clientes'!$B57,'Detalhe Por UC'!$R:$R,'Infos Clientes'!AK$2)) -> 692 | AL57: =IF(SUMIFS('Detalhe Por UC'!$AB:$AB,'Detalhe Por UC'!$C:$C,'Infos Clientes'!$B57,'Detalhe Por UC'!$R:$R,'Infos Clientes'!AL$2)=0,"", SUMIFS('Detalhe Por UC'!$AB:$AB,'Detalhe Por UC'!$C:$C,'Infos Clientes'!$B57,'Detalhe Por UC'!$R:$R,'Infos Clientes'!AL$2) +SUMIFS('Detalhe Por UC'!$AC:$AC,'Detalhe Por UC'!$C:$C,'Infos Clientes'!$B57,'Detalhe Por UC'!$R:$R,'Infos Clientes'!AL$2)) -> 706 | AM57: =IF(SUMIFS('Detalhe Por UC'!$AB:$AB,'Detalhe Por UC'!$C:$C,'Infos Clientes'!$B57,'Detalhe Por UC'!$R:$R,'Infos Clientes'!AM$2)=0,"", SUMIFS('Detalhe Por UC'!$AB:$AB,'Detalhe Por UC'!$C:$C,'Infos Clientes'!$B57,'Detalhe Por UC'!$R:$R,'Infos Clientes'!AM$2) +SUMIFS('Detalhe Por UC'!$AC:$AC,'Detalhe Por UC'!$C:$C,'Infos Clientes'!$B57,'Detalhe Por UC'!$R:$R,'Infos Clientes'!AM$2)) -> 387 | AN57: =IF(SUMIFS('Detalhe Por UC'!$AB:$AB,'Detalhe Por UC'!$C:$C,'Infos Clientes'!$B57,'Detalhe Por UC'!$R:$R,'Infos Clientes'!AN$2)=0,"", SUMIFS('Detalhe Por UC'!$AB:$AB,'Detalhe Por UC'!$C:$C,'Infos Clientes'!$B57,'Detalhe Por UC'!$R:$R,'Infos Clientes'!AN$2) +SUMIFS('Detalhe Por UC'!$AC:$AC,'Detalhe Por UC'!$C:$C,'Infos Clientes'!$B57,'Detalhe Por UC'!$R:$R,'Infos Clientes'!AN$2)) -> 545 | AO57: =IF(SUMIFS('Detalhe Por UC'!$AB:$AB,'Detalhe Por UC'!$C:$C,'Infos Clientes'!$B57,'Detalhe Por UC'!$R:$R,'Infos Clientes'!AO$2)=0,"", SUMIFS('Detalhe Por UC'!$AB:$AB,'Detalhe Por UC'!$C:$C,'Infos Clientes'!$B57,'Detalhe Por UC'!$R:$R,'Infos Clientes'!AO$2) +SUMIFS('Detalhe Por UC'!$AC:$AC,'Detalhe Por UC'!$C:$C,'Infos Clientes'!$B57,'Detalhe Por UC'!$R:$R,'Infos Clientes'!AO$2)) -> 380 | AP57: =IF(SUMIFS('Detalhe Por UC'!$AB:$AB,'Detalhe Por UC'!$C:$C,'Infos Clientes'!$B57,'Detalhe Por UC'!$R:$R,'Infos Clientes'!AP$2)=0,"", SUMIFS('Detalhe Por UC'!$AB:$AB,'Detalhe Por UC'!$C:$C,'Infos Clientes'!$B57,'Detalhe Por UC'!$R:$R,'Infos Clientes'!AP$2) +SUMIFS('Detalhe Por UC'!$AC:$AC,'Detalhe Por UC'!$C:$C,'Infos Clientes'!$B57,'Detalhe Por UC'!$R:$R,'Infos Clientes'!AP$2)) -> 305 | AQ57: =IF(SUMIFS('Detalhe Por UC'!$AB:$AB,'Detalhe Por UC'!$C:$C,'Infos Clientes'!$B57,'Detalhe Por UC'!$R:$R,'Infos Clientes'!AQ$2)=0,"", SUMIFS('Detalhe Por UC'!$AB:$AB,'Detalhe Por UC'!$C:$C,'Infos Clientes'!$B57,'Detalhe Por UC'!$R:$R,'Infos Clientes'!AQ$2) +SUMIFS('Detalhe Por UC'!$AC:$AC,'Detalhe Por UC'!$C:$C,'Infos Clientes'!$B57,'Detalhe Por UC'!$R:$R,'Infos Clientes'!AQ$2)) -> 353 | ... AU57: =IF(SUMIFS('Detalhe Por UC'!$AB:$AB,'Detalhe Por UC'!$C:$C,'Infos Clientes'!$B57,'Detalhe Por UC'!$R:$R,'Infos Clientes'!AU$2)=0,"", SUMIFS('Detalhe Por UC'!$AB:$AB,'Detalhe Por UC'!$C:$C,'Infos Clientes'!$B57,'Detalhe Por UC'!$R:$R,'Infos Clientes'!AU$2) +SUMIFS('Detalhe Por UC'!$AC:$AC,'Detalhe Por UC'!$C:$C,'Infos Clientes'!$B57,'Detalhe Por UC'!$R:$R,'Infos Clientes'!AU$2))
B58: 10/1674177-9 | C58: 50 | D58: IGREJA DO EVANGELHO QUADRANGULAR | E58: 302 | F58: 62.955.505/0161-60 | G58: 3ieqant302@gmail; israelregiao302@gmail.com | H58: =B58 -> 10/1674177-9 | I58: BT | J58: trifasico | K58: GIROSSOL III | M58: 0.25 | Q58: =IF(_xlfn.MINIFS('Detalhe Por UC'!R:R,'Detalhe Por UC'!C:C,B58,'Detalhe Por UC'!AD:AD,">"&0)=0,"",_xlfn.MINIFS('Detalhe Por UC'!R:R,'Detalhe Por UC'!C:C,B58,'Detalhe Por UC'!AD:AD,">"&0)) -> 45658 | R58: =IF(P58<>"ATIVO",0, IF(OR(Q58="",Q58=0,O58=0),O58, O58-ROUND((MAX('Detalhe Por UC'!R:R) -Q58)/(365/12),0))) -> 0 | T58: 393 | U58: =IFERROR((SUMIFS(W58:CN58,$W$2:$CN$2,">"&$Q$1-365,$W$2:$CN$2,"<="&$Q$1)/COUNTIFS(W58:CN58,">="&0,$W$2:$CN$2,">"&$Q$1-365,$W$2:$CN$2,"<="&$Q$1)),"") -> 511.91667 | X58: 456 | Y58: 464 | Z58: 461 | AA58: 600 | AB58: 0 | AC58: 205 | AD58: 192 | AE58: 195 | AF58: 302 | AG58: 446 | AH58: 410 | AI58: 564 | AJ58: =IF(SUMIFS('Detalhe Por UC'!$AB:$AB,'Detalhe Por UC'!$C:$C,'Infos Clientes'!$B58,'Detalhe Por UC'!$R:$R,'Infos Clientes'!AJ$2)=0,"", SUMIFS('Detalhe Por UC'!$AB:$AB,'Detalhe Por UC'!$C:$C,'Infos Clientes'!$B58,'Detalhe Por UC'!$R:$R,'Infos Clientes'!AJ$2) +SUMIFS('Detalhe Por UC'!$AC:$AC,'Detalhe Por UC'!$C:$C,'Infos Clientes'!$B58,'Detalhe Por UC'!$R:$R,'Infos Clientes'!AJ$2)) -> 484 | AK58: =IF(SUMIFS('Detalhe Por UC'!$AB:$AB,'Detalhe Por UC'!$C:$C,'Infos Clientes'!$B58,'Detalhe Por UC'!$R:$R,'Infos Clientes'!AK$2)=0,"", SUMIFS('Detalhe Por UC'!$AB:$AB,'Detalhe Por UC'!$C:$C,'Infos Clientes'!$B58,'Detalhe Por UC'!$R:$R,'Infos Clientes'!AK$2) +SUMIFS('Detalhe Por UC'!$AC:$AC,'Detalhe Por UC'!$C:$C,'Infos Clientes'!$B58,'Detalhe Por UC'!$R:$R,'Infos Clientes'!AK$2)) -> 507 | AL58: =IF(SUMIFS('Detalhe Por UC'!$AB:$AB,'Detalhe Por UC'!$C:$C,'Infos Clientes'!$B58,'Detalhe Por UC'!$R:$R,'Infos Clientes'!AL$2)=0,"", SUMIFS('Detalhe Por UC'!$AB:$AB,'Detalhe Por UC'!$C:$C,'Infos Clientes'!$B58,'Detalhe Por UC'!$R:$R,'Infos Clientes'!AL$2) +SUMIFS('Detalhe Por UC'!$AC:$AC,'Detalhe Por UC'!$C:$C,'Infos Clientes'!$B58,'Detalhe Por UC'!$R:$R,'Infos Clientes'!AL$2)) -> 754 | AM58: =IF(SUMIFS('Detalhe Por UC'!$AB:$AB,'Detalhe Por UC'!$C:$C,'Infos Clientes'!$B58,'Detalhe Por UC'!$R:$R,'Infos Clientes'!AM$2)=0,"", SUMIFS('Detalhe Por UC'!$AB:$AB,'Detalhe Por UC'!$C:$C,'Infos Clientes'!$B58,'Detalhe Por UC'!$R:$R,'Infos Clientes'!AM$2) +SUMIFS('Detalhe Por UC'!$AC:$AC,'Detalhe Por UC'!$C:$C,'Infos Clientes'!$B58,'Detalhe Por UC'!$R:$R,'Infos Clientes'!AM$2)) -> 540 | AN58: =IF(SUMIFS('Detalhe Por UC'!$AB:$AB,'Detalhe Por UC'!$C:$C,'Infos Clientes'!$B58,'Detalhe Por UC'!$R:$R,'Infos Clientes'!AN$2)=0,"", SUMIFS('Detalhe Por UC'!$AB:$AB,'Detalhe Por UC'!$C:$C,'Infos Clientes'!$B58,'Detalhe Por UC'!$R:$R,'Infos Clientes'!AN$2) +SUMIFS('Detalhe Por UC'!$AC:$AC,'Detalhe Por UC'!$C:$C,'Infos Clientes'!$B58,'Detalhe Por UC'!$R:$R,'Infos Clientes'!AN$2)) -> 377 | AO58: =IF(SUMIFS('Detalhe Por UC'!$AB:$AB,'Detalhe Por UC'!$C:$C,'Infos Clientes'!$B58,'Detalhe Por UC'!$R:$R,'Infos Clientes'!AO$2)=0,"", SUMIFS('Detalhe Por UC'!$AB:$AB,'Detalhe Por UC'!$C:$C,'Infos Clientes'!$B58,'Detalhe Por UC'!$R:$R,'Infos Clientes'!AO$2) +SUMIFS('Detalhe Por UC'!$AC:$AC,'Detalhe Por UC'!$C:$C,'Infos Clientes'!$B58,'Detalhe Por UC'!$R:$R,'Infos Clientes'!AO$2)) -> 375 | AP58: =IF(SUMIFS('Detalhe Por UC'!$AB:$AB,'Detalhe Por UC'!$C:$C,'Infos Clientes'!$B58,'Detalhe Por UC'!$R:$R,'Infos Clientes'!AP$2)=0,"", SUMIFS('Detalhe Por UC'!$AB:$AB,'Detalhe Por UC'!$C:$C,'Infos Clientes'!$B58,'Detalhe Por UC'!$R:$R,'Infos Clientes'!AP$2) +SUMIFS('Detalhe Por UC'!$AC:$AC,'Detalhe Por UC'!$C:$C,'Infos Clientes'!$B58,'Detalhe Por UC'!$R:$R,'Infos Clientes'!AP$2)) -> 202 | AQ58: =IF(SUMIFS('Detalhe Por UC'!$AB:$AB,'Detalhe Por UC'!$C:$C,'Infos Clientes'!$B58,'Detalhe Por UC'!$R:$R,'Infos Clientes'!AQ$2)=0,"", SUMIFS('Detalhe Por UC'!$AB:$AB,'Detalhe Por UC'!$C:$C,'Infos Clientes'!$B58,'Detalhe Por UC'!$R:$R,'Infos Clientes'!AQ$2) +SUMIFS('Detalhe Por UC'!$AC:$AC,'Detalhe Por UC'!$C:$C,'Infos Clientes'!$B58,'Detalhe Por UC'!$R:$R,'Infos Clientes'!AQ$2)) -> 259 | ... AU58: =IF(SUMIFS('Detalhe Por UC'!$AB:$AB,'Detalhe Por UC'!$C:$C,'Infos Clientes'!$B58,'Detalhe Por UC'!$R:$R,'Infos Clientes'!AU$2)=0,"", SUMIFS('Detalhe Por UC'!$AB:$AB,'Detalhe Por UC'!$C:$C,'Infos Clientes'!$B58,'Detalhe Por UC'!$R:$R,'Infos Clientes'!AU$2) +SUMIFS('Detalhe Por UC'!$AC:$AC,'Detalhe Por UC'!$C:$C,'Infos Clientes'!$B58,'Detalhe Por UC'!$R:$R,'Infos Clientes'!AU$2))
B59: 10/175073-6 | C59: =ROW(F59) -> 59 | D59: IGREJA DO EVANGELHO QUADRANGULAR | E59: 362 | F59: 62.955.505/1344-49 | G59: pastoreliasmn@hotmail.com | H59: =B59 -> 10/175073-6 | I59: BT | J59: bifasico | K59: GIROSSOL III | M59: 0.25 | Q59: =IF(_xlfn.MINIFS('Detalhe Por UC'!R:R,'Detalhe Por UC'!C:C,B59,'Detalhe Por UC'!AD:AD,">"&0)=0,"",_xlfn.MINIFS('Detalhe Por UC'!R:R,'Detalhe Por UC'!C:C,B59,'Detalhe Por UC'!AD:AD,">"&0)) -> 45658 | R59: =IF(P59<>"ATIVO",0, IF(OR(Q59="",Q59=0,O59=0),O59, O59-ROUND((MAX('Detalhe Por UC'!R:R) -Q59)/(365/12),0))) -> 0 | T59: 140.81818 | U59: =IFERROR((SUMIFS(W59:CN59,$W$2:$CN$2,">"&$Q$1-365,$W$2:$CN$2,"<="&$Q$1)/COUNTIFS(W59:CN59,">="&0,$W$2:$CN$2,">"&$Q$1-365,$W$2:$CN$2,"<="&$Q$1)),"") -> 88.5 | X59: 361 | Y59: 376 | Z59: 424 | AA59: 92 | AB59: 0 | AC59: 70 | AD59: 70 | AE59: 120 | AF59: 52 | AG59: 80 | AH59: 101 | AI59: 107 | AJ59: =IF(SUMIFS('Detalhe Por UC'!$AB:$AB,'Detalhe Por UC'!$C:$C,'Infos Clientes'!$B59,'Detalhe Por UC'!$R:$R,'Infos Clientes'!AJ$2)=0,"", SUMIFS('Detalhe Por UC'!$AB:$AB,'Detalhe Por UC'!$C:$C,'Infos Clientes'!$B59,'Detalhe Por UC'!$R:$R,'Infos Clientes'!AJ$2) +SUMIFS('Detalhe Por UC'!$AC:$AC,'Detalhe Por UC'!$C:$C,'Infos Clientes'!$B59,'Detalhe Por UC'!$R:$R,'Infos Clientes'!AJ$2)) -> 57 | AK59: =IF(SUMIFS('Detalhe Por UC'!$AB:$AB,'Detalhe Por UC'!$C:$C,'Infos Clientes'!$B59,'Detalhe Por UC'!$R:$R,'Infos Clientes'!AK$2)=0,"", SUMIFS('Detalhe Por UC'!$AB:$AB,'Detalhe Por UC'!$C:$C,'Infos Clientes'!$B59,'Detalhe Por UC'!$R:$R,'Infos Clientes'!AK$2) +SUMIFS('Detalhe Por UC'!$AC:$AC,'Detalhe Por UC'!$C:$C,'Infos Clientes'!$B59,'Detalhe Por UC'!$R:$R,'Infos Clientes'!AK$2)) -> 82 | AL59: =IF(SUMIFS('Detalhe Por UC'!$AB:$AB,'Detalhe Por UC'!$C:$C,'Infos Clientes'!$B59,'Detalhe Por UC'!$R:$R,'Infos Clientes'!AL$2)=0,"", SUMIFS('Detalhe Por UC'!$AB:$AB,'Detalhe Por UC'!$C:$C,'Infos Clientes'!$B59,'Detalhe Por UC'!$R:$R,'Infos Clientes'!AL$2) +SUMIFS('Detalhe Por UC'!$AC:$AC,'Detalhe Por UC'!$C:$C,'Infos Clientes'!$B59,'Detalhe Por UC'!$R:$R,'Infos Clientes'!AL$2)) -> 70 | AM59: =IF(SUMIFS('Detalhe Por UC'!$AB:$AB,'Detalhe Por UC'!$C:$C,'Infos Clientes'!$B59,'Detalhe Por UC'!$R:$R,'Infos Clientes'!AM$2)=0,"", SUMIFS('Detalhe Por UC'!$AB:$AB,'Detalhe Por UC'!$C:$C,'Infos Clientes'!$B59,'Detalhe Por UC'!$R:$R,'Infos Clientes'!AM$2) +SUMIFS('Detalhe Por UC'!$AC:$AC,'Detalhe Por UC'!$C:$C,'Infos Clientes'!$B59,'Detalhe Por UC'!$R:$R,'Infos Clientes'!AM$2)) -> 84 | AN59: =IF(SUMIFS('Detalhe Por UC'!$AB:$AB,'Detalhe Por UC'!$C:$C,'Infos Clientes'!$B59,'Detalhe Por UC'!$R:$R,'Infos Clientes'!AN$2)=0,"", SUMIFS('Detalhe Por UC'!$AB:$AB,'Detalhe Por UC'!$C:$C,'Infos Clientes'!$B59,'Detalhe Por UC'!$R:$R,'Infos Clientes'!AN$2) +SUMIFS('Detalhe Por UC'!$AC:$AC,'Detalhe Por UC'!$C:$C,'Infos Clientes'!$B59,'Detalhe Por UC'!$R:$R,'Infos Clientes'!AN$2)) -> 93 | AO59: =IF(SUMIFS('Detalhe Por UC'!$AB:$AB,'Detalhe Por UC'!$C:$C,'Infos Clientes'!$B59,'Detalhe Por UC'!$R:$R,'Infos Clientes'!AO$2)=0,"", SUMIFS('Detalhe Por UC'!$AB:$AB,'Detalhe Por UC'!$C:$C,'Infos Clientes'!$B59,'Detalhe Por UC'!$R:$R,'Infos Clientes'!AO$2) +SUMIFS('Detalhe Por UC'!$AC:$AC,'Detalhe Por UC'!$C:$C,'Infos Clientes'!$B59,'Detalhe Por UC'!$R:$R,'Infos Clientes'!AO$2)) -> 129 | AP59: =IF(SUMIFS('Detalhe Por UC'!$AB:$AB,'Detalhe Por UC'!$C:$C,'Infos Clientes'!$B59,'Detalhe Por UC'!$R:$R,'Infos Clientes'!AP$2)=0,"", SUMIFS('Detalhe Por UC'!$AB:$AB,'Detalhe Por UC'!$C:$C,'Infos Clientes'!$B59,'Detalhe Por UC'!$R:$R,'Infos Clientes'!AP$2) +SUMIFS('Detalhe Por UC'!$AC:$AC,'Detalhe Por UC'!$C:$C,'Infos Clientes'!$B59,'Detalhe Por UC'!$R:$R,'Infos Clientes'!AP$2)) -> 78 | AQ59: =IF(SUMIFS('Detalhe Por UC'!$AB:$AB,'Detalhe Por UC'!$C:$C,'Infos Clientes'!$B59,'Detalhe Por UC'!$R:$R,'Infos Clientes'!AQ$2)=0,"", SUMIFS('Detalhe Por UC'!$AB:$AB,'Detalhe Por UC'!$C:$C,'Infos Clientes'!$B59,'Detalhe Por UC'!$R:$R,'Infos Clientes'!AQ$2) +SUMIFS('Detalhe Por UC'!$AC:$AC,'Detalhe Por UC'!$C:$C,'Infos Clientes'!$B59,'Detalhe Por UC'!$R:$R,'Infos Clientes'!AQ$2)) -> 95 | ... AU59: =IF(SUMIFS('Detalhe Por UC'!$AB:$AB,'Detalhe Por UC'!$C:$C,'Infos Clientes'!$B59,'Detalhe Por UC'!$R:$R,'Infos Clientes'!AU$2)=0,"", SUMIFS('Detalhe Por UC'!$AB:$AB,'Detalhe Por UC'!$C:$C,'Infos Clientes'!$B59,'Detalhe Por UC'!$R:$R,'Infos Clientes'!AU$2) +SUMIFS('Detalhe Por UC'!$AC:$AC,'Detalhe Por UC'!$C:$C,'Infos Clientes'!$B59,'Detalhe Por UC'!$R:$R,'Infos Clientes'!AU$2))
B60: 10/2247256-7 | C60: =ROW(F60) -> 60 | D60: IGREJA DO EVANGELHO QUADRANGULAR | E60: 306 | F60: 62.955.505/0151-99 | G60: carlaestreito@hotmail.com | H60: =B60 -> 10/2247256-7 | I60: BT | J60: trifasico | K60: GIROSSOL III | M60: 0.25 | Q60: =IF(_xlfn.MINIFS('Detalhe Por UC'!R:R,'Detalhe Por UC'!C:C,B60,'Detalhe Por UC'!AD:AD,">"&0)=0,"",_xlfn.MINIFS('Detalhe Por UC'!R:R,'Detalhe Por UC'!C:C,B60,'Detalhe Por UC'!AD:AD,">"&0)) -> 45658 | R60: =IF(P60<>"ATIVO",0, IF(OR(Q60="",Q60=0,O60=0),O60, O60-ROUND((MAX('Detalhe Por UC'!R:R) -Q60)/(365/12),0))) -> 0 | T60: 718.45455 | U60: =IFERROR((SUMIFS(W60:CN60,$W$2:$CN$2,">"&$Q$1-365,$W$2:$CN$2,"<="&$Q$1)/COUNTIFS(W60:CN60,">="&0,$W$2:$CN$2,">"&$Q$1-365,$W$2:$CN$2,"<="&$Q$1)),"") -> 579.45455 | X60: 1311 | Y60: 1518 | Z60: 891 | AA60: 929 | AB60: 0 | AC60: 589 | AD60: 323 | AE60: 594 | AF60: 482 | AG60: 516 | AH60: 842 | AI60: 626 | AJ60: =IF(SUMIFS('Detalhe Por UC'!$AB:$AB,'Detalhe Por UC'!$C:$C,'Infos Clientes'!$B60,'Detalhe Por UC'!$R:$R,'Infos Clientes'!AJ$2)=0,"", SUMIFS('Detalhe Por UC'!$AB:$AB,'Detalhe Por UC'!$C:$C,'Infos Clientes'!$B60,'Detalhe Por UC'!$R:$R,'Infos Clientes'!AJ$2) +SUMIFS('Detalhe Por UC'!$AC:$AC,'Detalhe Por UC'!$C:$C,'Infos Clientes'!$B60,'Detalhe Por UC'!$R:$R,'Infos Clientes'!AJ$2)) -> 593 | AK60: =IF(SUMIFS('Detalhe Por UC'!$AB:$AB,'Detalhe Por UC'!$C:$C,'Infos Clientes'!$B60,'Detalhe Por UC'!$R:$R,'Infos Clientes'!AK$2)=0,"", SUMIFS('Detalhe Por UC'!$AB:$AB,'Detalhe Por UC'!$C:$C,'Infos Clientes'!$B60,'Detalhe Por UC'!$R:$R,'Infos Clientes'!AK$2) +SUMIFS('Detalhe Por UC'!$AC:$AC,'Detalhe Por UC'!$C:$C,'Infos Clientes'!$B60,'Detalhe Por UC'!$R:$R,'Infos Clientes'!AK$2)) -> 968 | AL60: =IF(SUMIFS('Detalhe Por UC'!$AB:$AB,'Detalhe Por UC'!$C:$C,'Infos Clientes'!$B60,'Detalhe Por UC'!$R:$R,'Infos Clientes'!AL$2)=0,"", SUMIFS('Detalhe Por UC'!$AB:$AB,'Detalhe Por UC'!$C:$C,'Infos Clientes'!$B60,'Detalhe Por UC'!$R:$R,'Infos Clientes'!AL$2) +SUMIFS('Detalhe Por UC'!$AC:$AC,'Detalhe Por UC'!$C:$C,'Infos Clientes'!$B60,'Detalhe Por UC'!$R:$R,'Infos Clientes'!AL$2)) -> 921 | AM60: =IF(SUMIFS('Detalhe Por UC'!$AB:$AB,'Detalhe Por UC'!$C:$C,'Infos Clientes'!$B60,'Detalhe Por UC'!$R:$R,'Infos Clientes'!AM$2)=0,"", SUMIFS('Detalhe Por UC'!$AB:$AB,'Detalhe Por UC'!$C:$C,'Infos Clientes'!$B60,'Detalhe Por UC'!$R:$R,'Infos Clientes'!AM$2) +SUMIFS('Detalhe Por UC'!$AC:$AC,'Detalhe Por UC'!$C:$C,'Infos Clientes'!$B60,'Detalhe Por UC'!$R:$R,'Infos Clientes'!AM$2)) -> 620 | AN60: =IF(SUMIFS('Detalhe Por UC'!$AB:$AB,'Detalhe Por UC'!$C:$C,'Infos Clientes'!$B60,'Detalhe Por UC'!$R:$R,'Infos Clientes'!AN$2)=0,"", SUMIFS('Detalhe Por UC'!$AB:$AB,'Detalhe Por UC'!$C:$C,'Infos Clientes'!$B60,'Detalhe Por UC'!$R:$R,'Infos Clientes'!AN$2) +SUMIFS('Detalhe Por UC'!$AC:$AC,'Detalhe Por UC'!$C:$C,'Infos Clientes'!$B60,'Detalhe Por UC'!$R:$R,'Infos Clientes'!AN$2)) -> 432 | AO60: =IF(SUMIFS('Detalhe Por UC'!$AB:$AB,'Detalhe Por UC'!$C:$C,'Infos Clientes'!$B60,'Detalhe Por UC'!$R:$R,'Infos Clientes'!AO$2)=0,"", SUMIFS('Detalhe Por UC'!$AB:$AB,'Detalhe Por UC'!$C:$C,'Infos Clientes'!$B60,'Detalhe Por UC'!$R:$R,'Infos Clientes'!AO$2) +SUMIFS('Detalhe Por UC'!$AC:$AC,'Detalhe Por UC'!$C:$C,'Infos Clientes'!$B60,'Detalhe Por UC'!$R:$R,'Infos Clientes'!AO$2)) -> 433 | AP60: =IF(SUMIFS('Detalhe Por UC'!$AB:$AB,'Detalhe Por UC'!$C:$C,'Infos Clientes'!$B60,'Detalhe Por UC'!$R:$R,'Infos Clientes'!AP$2)=0,"", SUMIFS('Detalhe Por UC'!$AB:$AB,'Detalhe Por UC'!$C:$C,'Infos Clientes'!$B60,'Detalhe Por UC'!$R:$R,'Infos Clientes'!AP$2) +SUMIFS('Detalhe Por UC'!$AC:$AC,'Detalhe Por UC'!$C:$C,'Infos Clientes'!$B60,'Detalhe Por UC'!$R:$R,'Infos Clientes'!AP$2)) -> 253 | AQ60: =IF(SUMIFS('Detalhe Por UC'!$AB:$AB,'Detalhe Por UC'!$C:$C,'Infos Clientes'!$B60,'Detalhe Por UC'!$R:$R,'Infos Clientes'!AQ$2)=0,"", SUMIFS('Detalhe Por UC'!$AB:$AB,'Detalhe Por UC'!$C:$C,'Infos Clientes'!$B60,'Detalhe Por UC'!$R:$R,'Infos Clientes'!AQ$2) +SUMIFS('Detalhe Por UC'!$AC:$AC,'Detalhe Por UC'!$C:$C,'Infos Clientes'!$B60,'Detalhe Por UC'!$R:$R,'Infos Clientes'!AQ$2)) -> 343 | ... AU60: =IF(SUMIFS('Detalhe Por UC'!$AB:$AB,'Detalhe Por UC'!$C:$C,'Infos Clientes'!$B60,'Detalhe Por UC'!$R:$R,'Infos Clientes'!AU$2)=0,"", SUMIFS('Detalhe Por UC'!$AB:$AB,'Detalhe Por UC'!$C:$C,'Infos Clientes'!$B60,'Detalhe Por UC'!$R:$R,'Infos Clientes'!AU$2) +SUMIFS('Detalhe Por UC'!$AC:$AC,'Detalhe Por UC'!$C:$C,'Infos Clientes'!$B60,'Detalhe Por UC'!$R:$R,'Infos Clientes'!AU$2))
B61: 10/239312-2 | C61: =ROW(F61) -> 61 | D61: IGREJA DO EVANGELHO QUADRANGULAR | E61: 302 | F61: 62.955.505/0165-94 | G61: ieqnioaque@gmail.com; israelregiao302@gmail.com | H61: =B61 -> 10/239312-2 | I61: BT | J61: bifasico | K61: GIROSSOL III | M61: 0.25 | Q61: =IF(_xlfn.MINIFS('Detalhe Por UC'!R:R,'Detalhe Por UC'!C:C,B61,'Detalhe Por UC'!AD:AD,">"&0)=0,"",_xlfn.MINIFS('Detalhe Por UC'!R:R,'Detalhe Por UC'!C:C,B61,'Detalhe Por UC'!AD:AD,">"&0)) -> 45658 | R61: =IF(P61<>"ATIVO",0, IF(OR(Q61="",Q61=0,O61=0),O61, O61-ROUND((MAX('Detalhe Por UC'!R:R) -Q61)/(365/12),0))) -> 0 | T61: 287.36364 | U61: =IFERROR((SUMIFS(W61:CN61,$W$2:$CN$2,">"&$Q$1-365,$W$2:$CN$2,"<="&$Q$1)/COUNTIFS(W61:CN61,">="&0,$W$2:$CN$2,">"&$Q$1-365,$W$2:$CN$2,"<="&$Q$1)),"") -> 280.33333 | X61: 312 | Y61: 264 | Z61: 304 | AA61: 457 | AB61: 0 | AC61: 259 | AD61: 211 | AE61: 224 | AF61: 197 | AG61: 313 | AH61: 272 | AI61: 370 | AJ61: =IF(SUMIFS('Detalhe Por UC'!$AB:$AB,'Detalhe Por UC'!$C:$C,'Infos Clientes'!$B61,'Detalhe Por UC'!$R:$R,'Infos Clientes'!AJ$2)=0,"", SUMIFS('Detalhe Por UC'!$AB:$AB,'Detalhe Por UC'!$C:$C,'Infos Clientes'!$B61,'Detalhe Por UC'!$R:$R,'Infos Clientes'!AJ$2) +SUMIFS('Detalhe Por UC'!$AC:$AC,'Detalhe Por UC'!$C:$C,'Infos Clientes'!$B61,'Detalhe Por UC'!$R:$R,'Infos Clientes'!AJ$2)) -> 290 | AK61: =IF(SUMIFS('Detalhe Por UC'!$AB:$AB,'Detalhe Por UC'!$C:$C,'Infos Clientes'!$B61,'Detalhe Por UC'!$R:$R,'Infos Clientes'!AK$2)=0,"", SUMIFS('Detalhe Por UC'!$AB:$AB,'Detalhe Por UC'!$C:$C,'Infos Clientes'!$B61,'Detalhe Por UC'!$R:$R,'Infos Clientes'!AK$2) +SUMIFS('Detalhe Por UC'!$AC:$AC,'Detalhe Por UC'!$C:$C,'Infos Clientes'!$B61,'Detalhe Por UC'!$R:$R,'Infos Clientes'!AK$2)) -> 305 | AL61: =IF(SUMIFS('Detalhe Por UC'!$AB:$AB,'Detalhe Por UC'!$C:$C,'Infos Clientes'!$B61,'Detalhe Por UC'!$R:$R,'Infos Clientes'!AL$2)=0,"", SUMIFS('Detalhe Por UC'!$AB:$AB,'Detalhe Por UC'!$C:$C,'Infos Clientes'!$B61,'Detalhe Por UC'!$R:$R,'Infos Clientes'!AL$2) +SUMIFS('Detalhe Por UC'!$AC:$AC,'Detalhe Por UC'!$C:$C,'Infos Clientes'!$B61,'Detalhe Por UC'!$R:$R,'Infos Clientes'!AL$2)) -> 320 | AM61: =IF(SUMIFS('Detalhe Por UC'!$AB:$AB,'Detalhe Por UC'!$C:$C,'Infos Clientes'!$B61,'Detalhe Por UC'!$R:$R,'Infos Clientes'!AM$2)=0,"", SUMIFS('Detalhe Por UC'!$AB:$AB,'Detalhe Por UC'!$C:$C,'Infos Clientes'!$B61,'Detalhe Por UC'!$R:$R,'Infos Clientes'!AM$2) +SUMIFS('Detalhe Por UC'!$AC:$AC,'Detalhe Por UC'!$C:$C,'Infos Clientes'!$B61,'Detalhe Por UC'!$R:$R,'Infos Clientes'!AM$2)) -> 272 | AN61: =IF(SUMIFS('Detalhe Por UC'!$AB:$AB,'Detalhe Por UC'!$C:$C,'Infos Clientes'!$B61,'Detalhe Por UC'!$R:$R,'Infos Clientes'!AN$2)=0,"", SUMIFS('Detalhe Por UC'!$AB:$AB,'Detalhe Por UC'!$C:$C,'Infos Clientes'!$B61,'Detalhe Por UC'!$R:$R,'Infos Clientes'!AN$2) +SUMIFS('Detalhe Por UC'!$AC:$AC,'Detalhe Por UC'!$C:$C,'Infos Clientes'!$B61,'Detalhe Por UC'!$R:$R,'Infos Clientes'!AN$2)) -> 285 | AO61: =IF(SUMIFS('Detalhe Por UC'!$AB:$AB,'Detalhe Por UC'!$C:$C,'Infos Clientes'!$B61,'Detalhe Por UC'!$R:$R,'Infos Clientes'!AO$2)=0,"", SUMIFS('Detalhe Por UC'!$AB:$AB,'Detalhe Por UC'!$C:$C,'Infos Clientes'!$B61,'Detalhe Por UC'!$R:$R,'Infos Clientes'!AO$2) +SUMIFS('Detalhe Por UC'!$AC:$AC,'Detalhe Por UC'!$C:$C,'Infos Clientes'!$B61,'Detalhe Por UC'!$R:$R,'Infos Clientes'!AO$2)) -> 236 | AP61: =IF(SUMIFS('Detalhe Por UC'!$AB:$AB,'Detalhe Por UC'!$C:$C,'Infos Clientes'!$B61,'Detalhe Por UC'!$R:$R,'Infos Clientes'!AP$2)=0,"", SUMIFS('Detalhe Por UC'!$AB:$AB,'Detalhe Por UC'!$C:$C,'Infos Clientes'!$B61,'Detalhe Por UC'!$R:$R,'Infos Clientes'!AP$2) +SUMIFS('Detalhe Por UC'!$AC:$AC,'Detalhe Por UC'!$C:$C,'Infos Clientes'!$B61,'Detalhe Por UC'!$R:$R,'Infos Clientes'!AP$2)) -> 198 | AQ61: =IF(SUMIFS('Detalhe Por UC'!$AB:$AB,'Detalhe Por UC'!$C:$C,'Infos Clientes'!$B61,'Detalhe Por UC'!$R:$R,'Infos Clientes'!AQ$2)=0,"", SUMIFS('Detalhe Por UC'!$AB:$AB,'Detalhe Por UC'!$C:$C,'Infos Clientes'!$B61,'Detalhe Por UC'!$R:$R,'Infos Clientes'!AQ$2) +SUMIFS('Detalhe Por UC'!$AC:$AC,'Detalhe Por UC'!$C:$C,'Infos Clientes'!$B61,'Detalhe Por UC'!$R:$R,'Infos Clientes'!AQ$2)) -> 242 | ... AU61: =IF(SUMIFS('Detalhe Por UC'!$AB:$AB,'Detalhe Por UC'!$C:$C,'Infos Clientes'!$B61,'Detalhe Por UC'!$R:$R,'Infos Clientes'!AU$2)=0,"", SUMIFS('Detalhe Por UC'!$AB:$AB,'Detalhe Por UC'!$C:$C,'Infos Clientes'!$B61,'Detalhe Por UC'!$R:$R,'Infos Clientes'!AU$2) +SUMIFS('Detalhe Por UC'!$AC:$AC,'Detalhe Por UC'!$C:$C,'Infos Clientes'!$B61,'Detalhe Por UC'!$R:$R,'Infos Clientes'!AU$2))
B62: 10/24514-2 | C62: =ROW(F62) -> 62 | D62: IGREJA DO EVANGELHO QUADRANGULAR | E62: 357 | F62: 62.955.505/1570-66 | G62: pastormarioconstancio@hotmail.com; regiao.357@hotmail.com | H62: =B62 -> 10/24514-2 | I62: BT | J62: trifasico | K62: GIROSSOL III | M62: 0.25 | Q62: =IF(_xlfn.MINIFS('Detalhe Por UC'!R:R,'Detalhe Por UC'!C:C,B62,'Detalhe Por UC'!AD:AD,">"&0)=0,"",_xlfn.MINIFS('Detalhe Por UC'!R:R,'Detalhe Por UC'!C:C,B62,'Detalhe Por UC'!AD:AD,">"&0)) -> 45658 | R62: =IF(P62<>"ATIVO",0, IF(OR(Q62="",Q62=0,O62=0),O62, O62-ROUND((MAX('Detalhe Por UC'!R:R) -Q62)/(365/12),0))) -> 0 | T62: 324.72727 | U62: =IFERROR((SUMIFS(W62:CN62,$W$2:$CN$2,">"&$Q$1-365,$W$2:$CN$2,"<="&$Q$1)/COUNTIFS(W62:CN62,">="&0,$W$2:$CN$2,">"&$Q$1-365,$W$2:$CN$2,"<="&$Q$1)),"") -> 233.66667 | X62: 389 | Y62: 423 | Z62: 476 | AA62: 453 | AB62: 0 | AC62: 122 | AD62: 186 | AE62: 240 | AF62: 265 | AG62: 427 | AH62: 321 | AI62: 355 | AJ62: =IF(SUMIFS('Detalhe Por UC'!$AB:$AB,'Detalhe Por UC'!$C:$C,'Infos Clientes'!$B62,'Detalhe Por UC'!$R:$R,'Infos Clientes'!AJ$2)=0,"", SUMIFS('Detalhe Por UC'!$AB:$AB,'Detalhe Por UC'!$C:$C,'Infos Clientes'!$B62,'Detalhe Por UC'!$R:$R,'Infos Clientes'!AJ$2) +SUMIFS('Detalhe Por UC'!$AC:$AC,'Detalhe Por UC'!$C:$C,'Infos Clientes'!$B62,'Detalhe Por UC'!$R:$R,'Infos Clientes'!AJ$2)) -> 304 | AK62: =IF(SUMIFS('Detalhe Por UC'!$AB:$AB,'Detalhe Por UC'!$C:$C,'Infos Clientes'!$B62,'Detalhe Por UC'!$R:$R,'Infos Clientes'!AK$2)=0,"", SUMIFS('Detalhe Por UC'!$AB:$AB,'Detalhe Por UC'!$C:$C,'Infos Clientes'!$B62,'Detalhe Por UC'!$R:$R,'Infos Clientes'!AK$2) +SUMIFS('Detalhe Por UC'!$AC:$AC,'Detalhe Por UC'!$C:$C,'Infos Clientes'!$B62,'Detalhe Por UC'!$R:$R,'Infos Clientes'!AK$2)) -> 381 | AL62: =IF(SUMIFS('Detalhe Por UC'!$AB:$AB,'Detalhe Por UC'!$C:$C,'Infos Clientes'!$B62,'Detalhe Por UC'!$R:$R,'Infos Clientes'!AL$2)=0,"", SUMIFS('Detalhe Por UC'!$AB:$AB,'Detalhe Por UC'!$C:$C,'Infos Clientes'!$B62,'Detalhe Por UC'!$R:$R,'Infos Clientes'!AL$2) +SUMIFS('Detalhe Por UC'!$AC:$AC,'Detalhe Por UC'!$C:$C,'Infos Clientes'!$B62,'Detalhe Por UC'!$R:$R,'Infos Clientes'!AL$2)) -> 327 | AM62: =IF(SUMIFS('Detalhe Por UC'!$AB:$AB,'Detalhe Por UC'!$C:$C,'Infos Clientes'!$B62,'Detalhe Por UC'!$R:$R,'Infos Clientes'!AM$2)=0,"", SUMIFS('Detalhe Por UC'!$AB:$AB,'Detalhe Por UC'!$C:$C,'Infos Clientes'!$B62,'Detalhe Por UC'!$R:$R,'Infos Clientes'!AM$2) +SUMIFS('Detalhe Por UC'!$AC:$AC,'Detalhe Por UC'!$C:$C,'Infos Clientes'!$B62,'Detalhe Por UC'!$R:$R,'Infos Clientes'!AM$2)) -> 168 | AN62: =IF(SUMIFS('Detalhe Por UC'!$AB:$AB,'Detalhe Por UC'!$C:$C,'Infos Clientes'!$B62,'Detalhe Por UC'!$R:$R,'Infos Clientes'!AN$2)=0,"", SUMIFS('Detalhe Por UC'!$AB:$AB,'Detalhe Por UC'!$C:$C,'Infos Clientes'!$B62,'Detalhe Por UC'!$R:$R,'Infos Clientes'!AN$2) +SUMIFS('Detalhe Por UC'!$AC:$AC,'Detalhe Por UC'!$C:$C,'Infos Clientes'!$B62,'Detalhe Por UC'!$R:$R,'Infos Clientes'!AN$2)) -> 207 | AO62: =IF(SUMIFS('Detalhe Por UC'!$AB:$AB,'Detalhe Por UC'!$C:$C,'Infos Clientes'!$B62,'Detalhe Por UC'!$R:$R,'Infos Clientes'!AO$2)=0,"", SUMIFS('Detalhe Por UC'!$AB:$AB,'Detalhe Por UC'!$C:$C,'Infos Clientes'!$B62,'Detalhe Por UC'!$R:$R,'Infos Clientes'!AO$2) +SUMIFS('Detalhe Por UC'!$AC:$AC,'Detalhe Por UC'!$C:$C,'Infos Clientes'!$B62,'Detalhe Por UC'!$R:$R,'Infos Clientes'!AO$2)) -> 152 | AP62: =IF(SUMIFS('Detalhe Por UC'!$AB:$AB,'Detalhe Por UC'!$C:$C,'Infos Clientes'!$B62,'Detalhe Por UC'!$R:$R,'Infos Clientes'!AP$2)=0,"", SUMIFS('Detalhe Por UC'!$AB:$AB,'Detalhe Por UC'!$C:$C,'Infos Clientes'!$B62,'Detalhe Por UC'!$R:$R,'Infos Clientes'!AP$2) +SUMIFS('Detalhe Por UC'!$AC:$AC,'Detalhe Por UC'!$C:$C,'Infos Clientes'!$B62,'Detalhe Por UC'!$R:$R,'Infos Clientes'!AP$2)) -> 138 | AQ62: =IF(SUMIFS('Detalhe Por UC'!$AB:$AB,'Detalhe Por UC'!$C:$C,'Infos Clientes'!$B62,'Detalhe Por UC'!$R:$R,'Infos Clientes'!AQ$2)=0,"", SUMIFS('Detalhe Por UC'!$AB:$AB,'Detalhe Por UC'!$C:$C,'Infos Clientes'!$B62,'Detalhe Por UC'!$R:$R,'Infos Clientes'!AQ$2) +SUMIFS('Detalhe Por UC'!$AC:$AC,'Detalhe Por UC'!$C:$C,'Infos Clientes'!$B62,'Detalhe Por UC'!$R:$R,'Infos Clientes'!AQ$2)) -> 177 | ... AU62: =IF(SUMIFS('Detalhe Por UC'!$AB:$AB,'Detalhe Por UC'!$C:$C,'Infos Clientes'!$B62,'Detalhe Por UC'!$R:$R,'Infos Clientes'!AU$2)=0,"", SUMIFS('Detalhe Por UC'!$AB:$AB,'Detalhe Por UC'!$C:$C,'Infos Clientes'!$B62,'Detalhe Por UC'!$R:$R,'Infos Clientes'!AU$2) +SUMIFS('Detalhe Por UC'!$AC:$AC,'Detalhe Por UC'!$C:$C,'Infos Clientes'!$B62,'Detalhe Por UC'!$R:$R,'Infos Clientes'!AU$2))
B63: 10/252817-2 | C63: =ROW(F63) -> 63 | D63: IGREJA DO EVANGELHO QUADRANGULAR | E63: 371 | F63: 62.955.505/2740-20 | G63: ieqcaracolms@gmail.com; regiao371@gmail.com | H63: =B63 -> 10/252817-2 | I63: BT | J63: trifasico | K63: GIROSSOL III | M63: 0.25 | Q63: =IF(_xlfn.MINIFS('Detalhe Por UC'!R:R,'Detalhe Por UC'!C:C,B63,'Detalhe Por UC'!AD:AD,">"&0)=0,"",_xlfn.MINIFS('Detalhe Por UC'!R:R,'Detalhe Por UC'!C:C,B63,'Detalhe Por UC'!AD:AD,">"&0)) -> 45658 | R63: =IF(P63<>"ATIVO",0, IF(OR(Q63="",Q63=0,O63=0),O63, O63-ROUND((MAX('Detalhe Por UC'!R:R) -Q63)/(365/12),0))) -> 0 | T63: 384.90909 | U63: =IFERROR((SUMIFS(W63:CN63,$W$2:$CN$2,">"&$Q$1-365,$W$2:$CN$2,"<="&$Q$1)/COUNTIFS(W63:CN63,">="&0,$W$2:$CN$2,">"&$Q$1-365,$W$2:$CN$2,"<="&$Q$1)),"") -> 291.45455 | X63: 433 | Y63: 512 | Z63: 596 | AA63: 663 | AB63: 0 | AC63: 398 | AD63: 209 | AE63: 324 | AF63: 232 | AG63: 265 | AH63: 227 | AI63: 343 | AJ63: =IF(SUMIFS('Detalhe Por UC'!$AB:$AB,'Detalhe Por UC'!$C:$C,'Infos Clientes'!$B63,'Detalhe Por UC'!$R:$R,'Infos Clientes'!AJ$2)=0,"", SUMIFS('Detalhe Por UC'!$AB:$AB,'Detalhe Por UC'!$C:$C,'Infos Clientes'!$B63,'Detalhe Por UC'!$R:$R,'Infos Clientes'!AJ$2) +SUMIFS('Detalhe Por UC'!$AC:$AC,'Detalhe Por UC'!$C:$C,'Infos Clientes'!$B63,'Detalhe Por UC'!$R:$R,'Infos Clientes'!AJ$2)) -> 465 | AK63: =IF(SUMIFS('Detalhe Por UC'!$AB:$AB,'Detalhe Por UC'!$C:$C,'Infos Clientes'!$B63,'Detalhe Por UC'!$R:$R,'Infos Clientes'!AK$2)=0,"", SUMIFS('Detalhe Por UC'!$AB:$AB,'Detalhe Por UC'!$C:$C,'Infos Clientes'!$B63,'Detalhe Por UC'!$R:$R,'Infos Clientes'!AK$2) +SUMIFS('Detalhe Por UC'!$AC:$AC,'Detalhe Por UC'!$C:$C,'Infos Clientes'!$B63,'Detalhe Por UC'!$R:$R,'Infos Clientes'!AK$2)) -> 338 | AL63: =IF(SUMIFS('Detalhe Por UC'!$AB:$AB,'Detalhe Por UC'!$C:$C,'Infos Clientes'!$B63,'Detalhe Por UC'!$R:$R,'Infos Clientes'!AL$2)=0,"", SUMIFS('Detalhe Por UC'!$AB:$AB,'Detalhe Por UC'!$C:$C,'Infos Clientes'!$B63,'Detalhe Por UC'!$R:$R,'Infos Clientes'!AL$2) +SUMIFS('Detalhe Por UC'!$AC:$AC,'Detalhe Por UC'!$C:$C,'Infos Clientes'!$B63,'Detalhe Por UC'!$R:$R,'Infos Clientes'!AL$2)) -> 451 | AM63: =IF(SUMIFS('Detalhe Por UC'!$AB:$AB,'Detalhe Por UC'!$C:$C,'Infos Clientes'!$B63,'Detalhe Por UC'!$R:$R,'Infos Clientes'!AM$2)=0,"", SUMIFS('Detalhe Por UC'!$AB:$AB,'Detalhe Por UC'!$C:$C,'Infos Clientes'!$B63,'Detalhe Por UC'!$R:$R,'Infos Clientes'!AM$2) +SUMIFS('Detalhe Por UC'!$AC:$AC,'Detalhe Por UC'!$C:$C,'Infos Clientes'!$B63,'Detalhe Por UC'!$R:$R,'Infos Clientes'!AM$2)) -> 231 | AN63: =IF(SUMIFS('Detalhe Por UC'!$AB:$AB,'Detalhe Por UC'!$C:$C,'Infos Clientes'!$B63,'Detalhe Por UC'!$R:$R,'Infos Clientes'!AN$2)=0,"", SUMIFS('Detalhe Por UC'!$AB:$AB,'Detalhe Por UC'!$C:$C,'Infos Clientes'!$B63,'Detalhe Por UC'!$R:$R,'Infos Clientes'!AN$2) +SUMIFS('Detalhe Por UC'!$AC:$AC,'Detalhe Por UC'!$C:$C,'Infos Clientes'!$B63,'Detalhe Por UC'!$R:$R,'Infos Clientes'!AN$2)) -> 208 | AO63: =IF(SUMIFS('Detalhe Por UC'!$AB:$AB,'Detalhe Por UC'!$C:$C,'Infos Clientes'!$B63,'Detalhe Por UC'!$R:$R,'Infos Clientes'!AO$2)=0,"", SUMIFS('Detalhe Por UC'!$AB:$AB,'Detalhe Por UC'!$C:$C,'Infos Clientes'!$B63,'Detalhe Por UC'!$R:$R,'Infos Clientes'!AO$2) +SUMIFS('Detalhe Por UC'!$AC:$AC,'Detalhe Por UC'!$C:$C,'Infos Clientes'!$B63,'Detalhe Por UC'!$R:$R,'Infos Clientes'!AO$2)) -> 148 | AP63: =IF(SUMIFS('Detalhe Por UC'!$AB:$AB,'Detalhe Por UC'!$C:$C,'Infos Clientes'!$B63,'Detalhe Por UC'!$R:$R,'Infos Clientes'!AP$2)=0,"", SUMIFS('Detalhe Por UC'!$AB:$AB,'Detalhe Por UC'!$C:$C,'Infos Clientes'!$B63,'Detalhe Por UC'!$R:$R,'Infos Clientes'!AP$2) +SUMIFS('Detalhe Por UC'!$AC:$AC,'Detalhe Por UC'!$C:$C,'Infos Clientes'!$B63,'Detalhe Por UC'!$R:$R,'Infos Clientes'!AP$2)) | AQ63: =IF(SUMIFS('Detalhe Por UC'!$AB:$AB,'Detalhe Por UC'!$C:$C,'Infos Clientes'!$B63,'Detalhe Por UC'!$R:$R,'Infos Clientes'!AQ$2)=0,"", SUMIFS('Detalhe Por UC'!$AB:$AB,'Detalhe Por UC'!$C:$C,'Infos Clientes'!$B63,'Detalhe Por UC'!$R:$R,'Infos Clientes'!AQ$2) +SUMIFS('Detalhe Por UC'!$AC:$AC,'Detalhe Por UC'!$C:$C,'Infos Clientes'!$B63,'Detalhe Por UC'!$R:$R,'Infos Clientes'!AQ$2)) -> 117 | ... AU63: =IF(SUMIFS('Detalhe Por UC'!$AB:$AB,'Detalhe Por UC'!$C:$C,'Infos Clientes'!$B63,'Detalhe Por UC'!$R:$R,'Infos Clientes'!AU$2)=0,"", SUMIFS('Detalhe Por UC'!$AB:$AB,'Detalhe Por UC'!$C:$C,'Infos Clientes'!$B63,'Detalhe Por UC'!$R:$R,'Infos Clientes'!AU$2) +SUMIFS('Detalhe Por UC'!$AC:$AC,'Detalhe Por UC'!$C:$C,'Infos Clientes'!$B63,'Detalhe Por UC'!$R:$R,'Infos Clientes'!AU$2))
B64: 10/280638-8 | C64: =ROW(F64) -> 64 | D64: IGREJA DO EVANGELHO QUADRANGULAR | E64: 349 | F64: 62.955.505/8432-53 | G64: ieqreg349cassi@gmail.com | H64: =B64 -> 10/280638-8 | I64: BT | J64: trifasico | K64: GIROSSOL III | M64: 0.25 | Q64: =IF(_xlfn.MINIFS('Detalhe Por UC'!R:R,'Detalhe Por UC'!C:C,B64,'Detalhe Por UC'!AD:AD,">"&0)=0,"",_xlfn.MINIFS('Detalhe Por UC'!R:R,'Detalhe Por UC'!C:C,B64,'Detalhe Por UC'!AD:AD,">"&0)) -> 45658 | R64: =IF(P64<>"ATIVO",0, IF(OR(Q64="",Q64=0,O64=0),O64, O64-ROUND((MAX('Detalhe Por UC'!R:R) -Q64)/(365/12),0))) -> 0 | T64: 290.18182 | U64: =IFERROR((SUMIFS(W64:CN64,$W$2:$CN$2,">"&$Q$1-365,$W$2:$CN$2,"<="&$Q$1)/COUNTIFS(W64:CN64,">="&0,$W$2:$CN$2,">"&$Q$1-365,$W$2:$CN$2,"<="&$Q$1)),"") -> 267.33333 | X64: 275 | Y64: 400 | Z64: 491 | AA64: 242 | AB64: 0 | AC64: 164 | AD64: 157 | AE64: 211 | AF64: 227 | AG64: 372 | AH64: 260 | AI64: 305 | AJ64: =IF(SUMIFS('Detalhe Por UC'!$AB:$AB,'Detalhe Por UC'!$C:$C,'Infos Clientes'!$B64,'Detalhe Por UC'!$R:$R,'Infos Clientes'!AJ$2)=0,"", SUMIFS('Detalhe Por UC'!$AB:$AB,'Detalhe Por UC'!$C:$C,'Infos Clientes'!$B64,'Detalhe Por UC'!$R:$R,'Infos Clientes'!AJ$2) +SUMIFS('Detalhe Por UC'!$AC:$AC,'Detalhe Por UC'!$C:$C,'Infos Clientes'!$B64,'Detalhe Por UC'!$R:$R,'Infos Clientes'!AJ$2)) -> 363 | AK64: =IF(SUMIFS('Detalhe Por UC'!$AB:$AB,'Detalhe Por UC'!$C:$C,'Infos Clientes'!$B64,'Detalhe Por UC'!$R:$R,'Infos Clientes'!AK$2)=0,"", SUMIFS('Detalhe Por UC'!$AB:$AB,'Detalhe Por UC'!$C:$C,'Infos Clientes'!$B64,'Detalhe Por UC'!$R:$R,'Infos Clientes'!AK$2) +SUMIFS('Detalhe Por UC'!$AC:$AC,'Detalhe Por UC'!$C:$C,'Infos Clientes'!$B64,'Detalhe Por UC'!$R:$R,'Infos Clientes'!AK$2)) -> 125 | AL64: =IF(SUMIFS('Detalhe Por UC'!$AB:$AB,'Detalhe Por UC'!$C:$C,'Infos Clientes'!$B64,'Detalhe Por UC'!$R:$R,'Infos Clientes'!AL$2)=0,"", SUMIFS('Detalhe Por UC'!$AB:$AB,'Detalhe Por UC'!$C:$C,'Infos Clientes'!$B64,'Detalhe Por UC'!$R:$R,'Infos Clientes'!AL$2) +SUMIFS('Detalhe Por UC'!$AC:$AC,'Detalhe Por UC'!$C:$C,'Infos Clientes'!$B64,'Detalhe Por UC'!$R:$R,'Infos Clientes'!AL$2)) -> 337 | AM64: =IF(SUMIFS('Detalhe Por UC'!$AB:$AB,'Detalhe Por UC'!$C:$C,'Infos Clientes'!$B64,'Detalhe Por UC'!$R:$R,'Infos Clientes'!AM$2)=0,"", SUMIFS('Detalhe Por UC'!$AB:$AB,'Detalhe Por UC'!$C:$C,'Infos Clientes'!$B64,'Detalhe Por UC'!$R:$R,'Infos Clientes'!AM$2) +SUMIFS('Detalhe Por UC'!$AC:$AC,'Detalhe Por UC'!$C:$C,'Infos Clientes'!$B64,'Detalhe Por UC'!$R:$R,'Infos Clientes'!AM$2)) -> 302 | AN64: =IF(SUMIFS('Detalhe Por UC'!$AB:$AB,'Detalhe Por UC'!$C:$C,'Infos Clientes'!$B64,'Detalhe Por UC'!$R:$R,'Infos Clientes'!AN$2)=0,"", SUMIFS('Detalhe Por UC'!$AB:$AB,'Detalhe Por UC'!$C:$C,'Infos Clientes'!$B64,'Detalhe Por UC'!$R:$R,'Infos Clientes'!AN$2) +SUMIFS('Detalhe Por UC'!$AC:$AC,'Detalhe Por UC'!$C:$C,'Infos Clientes'!$B64,'Detalhe Por UC'!$R:$R,'Infos Clientes'!AN$2)) -> 308 | AO64: =IF(SUMIFS('Detalhe Por UC'!$AB:$AB,'Detalhe Por UC'!$C:$C,'Infos Clientes'!$B64,'Detalhe Por UC'!$R:$R,'Infos Clientes'!AO$2)=0,"", SUMIFS('Detalhe Por UC'!$AB:$AB,'Detalhe Por UC'!$C:$C,'Infos Clientes'!$B64,'Detalhe Por UC'!$R:$R,'Infos Clientes'!AO$2) +SUMIFS('Detalhe Por UC'!$AC:$AC,'Detalhe Por UC'!$C:$C,'Infos Clientes'!$B64,'Detalhe Por UC'!$R:$R,'Infos Clientes'!AO$2)) -> 229 | AP64: =IF(SUMIFS('Detalhe Por UC'!$AB:$AB,'Detalhe Por UC'!$C:$C,'Infos Clientes'!$B64,'Detalhe Por UC'!$R:$R,'Infos Clientes'!AP$2)=0,"", SUMIFS('Detalhe Por UC'!$AB:$AB,'Detalhe Por UC'!$C:$C,'Infos Clientes'!$B64,'Detalhe Por UC'!$R:$R,'Infos Clientes'!AP$2) +SUMIFS('Detalhe Por UC'!$AC:$AC,'Detalhe Por UC'!$C:$C,'Infos Clientes'!$B64,'Detalhe Por UC'!$R:$R,'Infos Clientes'!AP$2)) -> 185 | AQ64: =IF(SUMIFS('Detalhe Por UC'!$AB:$AB,'Detalhe Por UC'!$C:$C,'Infos Clientes'!$B64,'Detalhe Por UC'!$R:$R,'Infos Clientes'!AQ$2)=0,"", SUMIFS('Detalhe Por UC'!$AB:$AB,'Detalhe Por UC'!$C:$C,'Infos Clientes'!$B64,'Detalhe Por UC'!$R:$R,'Infos Clientes'!AQ$2) +SUMIFS('Detalhe Por UC'!$AC:$AC,'Detalhe Por UC'!$C:$C,'Infos Clientes'!$B64,'Detalhe Por UC'!$R:$R,'Infos Clientes'!AQ$2)) -> 172 | ... AU64: =IF(SUMIFS('Detalhe Por UC'!$AB:$AB,'Detalhe Por UC'!$C:$C,'Infos Clientes'!$B64,'Detalhe Por UC'!$R:$R,'Infos Clientes'!AU$2)=0,"", SUMIFS('Detalhe Por UC'!$AB:$AB,'Detalhe Por UC'!$C:$C,'Infos Clientes'!$B64,'Detalhe Por UC'!$R:$R,'Infos Clientes'!AU$2) +SUMIFS('Detalhe Por UC'!$AC:$AC,'Detalhe Por UC'!$C:$C,'Infos Clientes'!$B64,'Detalhe Por UC'!$R:$R,'Infos Clientes'!AU$2))
B65: 10/283183-2 | C65: =ROW(F65) -> 65 | D65: IGREJA DO EVANGELHO QUADRANGULAR | E65: 994 | F65: 62.955.505/2876-01 | G65: regiao371@gmail.com | H65: =B65 -> 10/283183-2 | I65: BT | J65: trifasico | K65: GIROSSOL III | M65: 0.25 | Q65: =IF(_xlfn.MINIFS('Detalhe Por UC'!R:R,'Detalhe Por UC'!C:C,B65,'Detalhe Por UC'!AD:AD,">"&0)=0,"",_xlfn.MINIFS('Detalhe Por UC'!R:R,'Detalhe Por UC'!C:C,B65,'Detalhe Por UC'!AD:AD,">"&0)) -> 45658 | R65: =IF(P65<>"ATIVO",0, IF(OR(Q65="",Q65=0,O65=0),O65, O65-ROUND((MAX('Detalhe Por UC'!R:R) -Q65)/(365/12),0))) -> 0 | T65: 143.63636 | U65: =IFERROR((SUMIFS(W65:CN65,$W$2:$CN$2,">"&$Q$1-365,$W$2:$CN$2,"<="&$Q$1)/COUNTIFS(W65:CN65,">="&0,$W$2:$CN$2,">"&$Q$1-365,$W$2:$CN$2,"<="&$Q$1)),"") -> 152.41667 | X65: 292 | Y65: 146 | Z65: 167 | AA65: 194 | AB65: 0 | AC65: 134 | AD65: 139 | AE65: 84 | AF65: 62 | AG65: 122 | AH65: 156 | AI65: 177 | AJ65: =IF(SUMIFS('Detalhe Por UC'!$AB:$AB,'Detalhe Por UC'!$C:$C,'Infos Clientes'!$B65,'Detalhe Por UC'!$R:$R,'Infos Clientes'!AJ$2)=0,"", SUMIFS('Detalhe Por UC'!$AB:$AB,'Detalhe Por UC'!$C:$C,'Infos Clientes'!$B65,'Detalhe Por UC'!$R:$R,'Infos Clientes'!AJ$2) +SUMIFS('Detalhe Por UC'!$AC:$AC,'Detalhe Por UC'!$C:$C,'Infos Clientes'!$B65,'Detalhe Por UC'!$R:$R,'Infos Clientes'!AJ$2)) -> 199 | AK65: =IF(SUMIFS('Detalhe Por UC'!$AB:$AB,'Detalhe Por UC'!$C:$C,'Infos Clientes'!$B65,'Detalhe Por UC'!$R:$R,'Infos Clientes'!AK$2)=0,"", SUMIFS('Detalhe Por UC'!$AB:$AB,'Detalhe Por UC'!$C:$C,'Infos Clientes'!$B65,'Detalhe Por UC'!$R:$R,'Infos Clientes'!AK$2) +SUMIFS('Detalhe Por UC'!$AC:$AC,'Detalhe Por UC'!$C:$C,'Infos Clientes'!$B65,'Detalhe Por UC'!$R:$R,'Infos Clientes'!AK$2)) -> 181 | AL65: =IF(SUMIFS('Detalhe Por UC'!$AB:$AB,'Detalhe Por UC'!$C:$C,'Infos Clientes'!$B65,'Detalhe Por UC'!$R:$R,'Infos Clientes'!AL$2)=0,"", SUMIFS('Detalhe Por UC'!$AB:$AB,'Detalhe Por UC'!$C:$C,'Infos Clientes'!$B65,'Detalhe Por UC'!$R:$R,'Infos Clientes'!AL$2) +SUMIFS('Detalhe Por UC'!$AC:$AC,'Detalhe Por UC'!$C:$C,'Infos Clientes'!$B65,'Detalhe Por UC'!$R:$R,'Infos Clientes'!AL$2)) -> 183 | AM65: =IF(SUMIFS('Detalhe Por UC'!$AB:$AB,'Detalhe Por UC'!$C:$C,'Infos Clientes'!$B65,'Detalhe Por UC'!$R:$R,'Infos Clientes'!AM$2)=0,"", SUMIFS('Detalhe Por UC'!$AB:$AB,'Detalhe Por UC'!$C:$C,'Infos Clientes'!$B65,'Detalhe Por UC'!$R:$R,'Infos Clientes'!AM$2) +SUMIFS('Detalhe Por UC'!$AC:$AC,'Detalhe Por UC'!$C:$C,'Infos Clientes'!$B65,'Detalhe Por UC'!$R:$R,'Infos Clientes'!AM$2)) -> 126 | AN65: =IF(SUMIFS('Detalhe Por UC'!$AB:$AB,'Detalhe Por UC'!$C:$C,'Infos Clientes'!$B65,'Detalhe Por UC'!$R:$R,'Infos Clientes'!AN$2)=0,"", SUMIFS('Detalhe Por UC'!$AB:$AB,'Detalhe Por UC'!$C:$C,'Infos Clientes'!$B65,'Detalhe Por UC'!$R:$R,'Infos Clientes'!AN$2) +SUMIFS('Detalhe Por UC'!$AC:$AC,'Detalhe Por UC'!$C:$C,'Infos Clientes'!$B65,'Detalhe Por UC'!$R:$R,'Infos Clientes'!AN$2)) -> 155 | AO65: =IF(SUMIFS('Detalhe Por UC'!$AB:$AB,'Detalhe Por UC'!$C:$C,'Infos Clientes'!$B65,'Detalhe Por UC'!$R:$R,'Infos Clientes'!AO$2)=0,"", SUMIFS('Detalhe Por UC'!$AB:$AB,'Detalhe Por UC'!$C:$C,'Infos Clientes'!$B65,'Detalhe Por UC'!$R:$R,'Infos Clientes'!AO$2) +SUMIFS('Detalhe Por UC'!$AC:$AC,'Detalhe Por UC'!$C:$C,'Infos Clientes'!$B65,'Detalhe Por UC'!$R:$R,'Infos Clientes'!AO$2)) -> 119 | AP65: =IF(SUMIFS('Detalhe Por UC'!$AB:$AB,'Detalhe Por UC'!$C:$C,'Infos Clientes'!$B65,'Detalhe Por UC'!$R:$R,'Infos Clientes'!AP$2)=0,"", SUMIFS('Detalhe Por UC'!$AB:$AB,'Detalhe Por UC'!$C:$C,'Infos Clientes'!$B65,'Detalhe Por UC'!$R:$R,'Infos Clientes'!AP$2) +SUMIFS('Detalhe Por UC'!$AC:$AC,'Detalhe Por UC'!$C:$C,'Infos Clientes'!$B65,'Detalhe Por UC'!$R:$R,'Infos Clientes'!AP$2)) -> 102 | AQ65: =IF(SUMIFS('Detalhe Por UC'!$AB:$AB,'Detalhe Por UC'!$C:$C,'Infos Clientes'!$B65,'Detalhe Por UC'!$R:$R,'Infos Clientes'!AQ$2)=0,"", SUMIFS('Detalhe Por UC'!$AB:$AB,'Detalhe Por UC'!$C:$C,'Infos Clientes'!$B65,'Detalhe Por UC'!$R:$R,'Infos Clientes'!AQ$2) +SUMIFS('Detalhe Por UC'!$AC:$AC,'Detalhe Por UC'!$C:$C,'Infos Clientes'!$B65,'Detalhe Por UC'!$R:$R,'Infos Clientes'!AQ$2)) -> 115 | ... AU65: =IF(SUMIFS('Detalhe Por UC'!$AB:$AB,'Detalhe Por UC'!$C:$C,'Infos Clientes'!$B65,'Detalhe Por UC'!$R:$R,'Infos Clientes'!AU$2)=0,"", SUMIFS('Detalhe Por UC'!$AB:$AB,'Detalhe Por UC'!$C:$C,'Infos Clientes'!$B65,'Detalhe Por UC'!$R:$R,'Infos Clientes'!AU$2) +SUMIFS('Detalhe Por UC'!$AC:$AC,'Detalhe Por UC'!$C:$C,'Infos Clientes'!$B65,'Detalhe Por UC'!$R:$R,'Infos Clientes'!AU$2))
B66: 10/3040565-8 | C66: =ROW(F66) -> 66 | D66: IGREJA DO EVANGELHO QUADRANGULAR | E66: 319 | F66: 62.955.505/0154-31 | G66: evaniabenites@hotmail.com | H66: =B66 -> 10/3040565-8 | I66: BT | J66: bifasico | K66: GIROSSOL III | M66: 0.25 | Q66: =IF(_xlfn.MINIFS('Detalhe Por UC'!R:R,'Detalhe Por UC'!C:C,B66,'Detalhe Por UC'!AD:AD,">"&0)=0,"",_xlfn.MINIFS('Detalhe Por UC'!R:R,'Detalhe Por UC'!C:C,B66,'Detalhe Por UC'!AD:AD,">"&0)) -> 45658 | R66: =IF(P66<>"ATIVO",0, IF(OR(Q66="",Q66=0,O66=0),O66, O66-ROUND((MAX('Detalhe Por UC'!R:R) -Q66)/(365/12),0))) -> 0 | T66: 250.27273 | U66: =IFERROR((SUMIFS(W66:CN66,$W$2:$CN$2,">"&$Q$1-365,$W$2:$CN$2,"<="&$Q$1)/COUNTIFS(W66:CN66,">="&0,$W$2:$CN$2,">"&$Q$1-365,$W$2:$CN$2,"<="&$Q$1)),"") -> 310.16667 | X66: 172 | Y66: 257 | Z66: 266 | AA66: 272 | AB66: 0 | AC66: 227 | AD66: 206 | AE66: 260 | AF66: 224 | AG66: 273 | AH66: 319 | AI66: 256 | AJ66: =IF(SUMIFS('Detalhe Por UC'!$AB:$AB,'Detalhe Por UC'!$C:$C,'Infos Clientes'!$B66,'Detalhe Por UC'!$R:$R,'Infos Clientes'!AJ$2)=0,"", SUMIFS('Detalhe Por UC'!$AB:$AB,'Detalhe Por UC'!$C:$C,'Infos Clientes'!$B66,'Detalhe Por UC'!$R:$R,'Infos Clientes'!AJ$2) +SUMIFS('Detalhe Por UC'!$AC:$AC,'Detalhe Por UC'!$C:$C,'Infos Clientes'!$B66,'Detalhe Por UC'!$R:$R,'Infos Clientes'!AJ$2)) -> 193 | AK66: =IF(SUMIFS('Detalhe Por UC'!$AB:$AB,'Detalhe Por UC'!$C:$C,'Infos Clientes'!$B66,'Detalhe Por UC'!$R:$R,'Infos Clientes'!AK$2)=0,"", SUMIFS('Detalhe Por UC'!$AB:$AB,'Detalhe Por UC'!$C:$C,'Infos Clientes'!$B66,'Detalhe Por UC'!$R:$R,'Infos Clientes'!AK$2) +SUMIFS('Detalhe Por UC'!$AC:$AC,'Detalhe Por UC'!$C:$C,'Infos Clientes'!$B66,'Detalhe Por UC'!$R:$R,'Infos Clientes'!AK$2)) -> 309 | AL66: =IF(SUMIFS('Detalhe Por UC'!$AB:$AB,'Detalhe Por UC'!$C:$C,'Infos Clientes'!$B66,'Detalhe Por UC'!$R:$R,'Infos Clientes'!AL$2)=0,"", SUMIFS('Detalhe Por UC'!$AB:$AB,'Detalhe Por UC'!$C:$C,'Infos Clientes'!$B66,'Detalhe Por UC'!$R:$R,'Infos Clientes'!AL$2) +SUMIFS('Detalhe Por UC'!$AC:$AC,'Detalhe Por UC'!$C:$C,'Infos Clientes'!$B66,'Detalhe Por UC'!$R:$R,'Infos Clientes'!AL$2)) -> 374 | AM66: =IF(SUMIFS('Detalhe Por UC'!$AB:$AB,'Detalhe Por UC'!$C:$C,'Infos Clientes'!$B66,'Detalhe Por UC'!$R:$R,'Infos Clientes'!AM$2)=0,"", SUMIFS('Detalhe Por UC'!$AB:$AB,'Detalhe Por UC'!$C:$C,'Infos Clientes'!$B66,'Detalhe Por UC'!$R:$R,'Infos Clientes'!AM$2) +SUMIFS('Detalhe Por UC'!$AC:$AC,'Detalhe Por UC'!$C:$C,'Infos Clientes'!$B66,'Detalhe Por UC'!$R:$R,'Infos Clientes'!AM$2)) -> 352 | AN66: =IF(SUMIFS('Detalhe Por UC'!$AB:$AB,'Detalhe Por UC'!$C:$C,'Infos Clientes'!$B66,'Detalhe Por UC'!$R:$R,'Infos Clientes'!AN$2)=0,"", SUMIFS('Detalhe Por UC'!$AB:$AB,'Detalhe Por UC'!$C:$C,'Infos Clientes'!$B66,'Detalhe Por UC'!$R:$R,'Infos Clientes'!AN$2) +SUMIFS('Detalhe Por UC'!$AC:$AC,'Detalhe Por UC'!$C:$C,'Infos Clientes'!$B66,'Detalhe Por UC'!$R:$R,'Infos Clientes'!AN$2)) -> 311 | AO66: =IF(SUMIFS('Detalhe Por UC'!$AB:$AB,'Detalhe Por UC'!$C:$C,'Infos Clientes'!$B66,'Detalhe Por UC'!$R:$R,'Infos Clientes'!AO$2)=0,"", SUMIFS('Detalhe Por UC'!$AB:$AB,'Detalhe Por UC'!$C:$C,'Infos Clientes'!$B66,'Detalhe Por UC'!$R:$R,'Infos Clientes'!AO$2) +SUMIFS('Detalhe Por UC'!$AC:$AC,'Detalhe Por UC'!$C:$C,'Infos Clientes'!$B66,'Detalhe Por UC'!$R:$R,'Infos Clientes'!AO$2)) -> 342 | AP66: =IF(SUMIFS('Detalhe Por UC'!$AB:$AB,'Detalhe Por UC'!$C:$C,'Infos Clientes'!$B66,'Detalhe Por UC'!$R:$R,'Infos Clientes'!AP$2)=0,"", SUMIFS('Detalhe Por UC'!$AB:$AB,'Detalhe Por UC'!$C:$C,'Infos Clientes'!$B66,'Detalhe Por UC'!$R:$R,'Infos Clientes'!AP$2) +SUMIFS('Detalhe Por UC'!$AC:$AC,'Detalhe Por UC'!$C:$C,'Infos Clientes'!$B66,'Detalhe Por UC'!$R:$R,'Infos Clientes'!AP$2)) -> 286 | AQ66: =IF(SUMIFS('Detalhe Por UC'!$AB:$AB,'Detalhe Por UC'!$C:$C,'Infos Clientes'!$B66,'Detalhe Por UC'!$R:$R,'Infos Clientes'!AQ$2)=0,"", SUMIFS('Detalhe Por UC'!$AB:$AB,'Detalhe Por UC'!$C:$C,'Infos Clientes'!$B66,'Detalhe Por UC'!$R:$R,'Infos Clientes'!AQ$2) +SUMIFS('Detalhe Por UC'!$AC:$AC,'Detalhe Por UC'!$C:$C,'Infos Clientes'!$B66,'Detalhe Por UC'!$R:$R,'Infos Clientes'!AQ$2)) -> 286 | ... AU66: =IF(SUMIFS('Detalhe Por UC'!$AB:$AB,'Detalhe Por UC'!$C:$C,'Infos Clientes'!$B66,'Detalhe Por UC'!$R:$R,'Infos Clientes'!AU$2)=0,"", SUMIFS('Detalhe Por UC'!$AB:$AB,'Detalhe Por UC'!$C:$C,'Infos Clientes'!$B66,'Detalhe Por UC'!$R:$R,'Infos Clientes'!AU$2) +SUMIFS('Detalhe Por UC'!$AC:$AC,'Detalhe Por UC'!$C:$C,'Infos Clientes'!$B66,'Detalhe Por UC'!$R:$R,'Infos Clientes'!AU$2))
B67: 10/3054052-0 | C67: =ROW(F67) -> 67 | D67: IGREJA DO EVANGELHO QUADRANGULAR | E67: 357 | F67: 62.955.505/3124-87 | G67: novaalianca1969@gmail.com; regiao.357@hotmail.com | H67: =B67 -> 10/3054052-0 | I67: BT | J67: trifasico | K67: GIROSSOL III | M67: 0.25 | Q67: =IF(_xlfn.MINIFS('Detalhe Por UC'!R:R,'Detalhe Por UC'!C:C,B67,'Detalhe Por UC'!AD:AD,">"&0)=0,"",_xlfn.MINIFS('Detalhe Por UC'!R:R,'Detalhe Por UC'!C:C,B67,'Detalhe Por UC'!AD:AD,">"&0)) -> 45689 | R67: =IF(P67<>"ATIVO",0, IF(OR(Q67="",Q67=0,O67=0),O67, O67-ROUND((MAX('Detalhe Por UC'!R:R) -Q67)/(365/12),0))) -> 0 | T67: 178.4 | U67: =IFERROR((SUMIFS(W67:CN67,$W$2:$CN$2,">"&$Q$1-365,$W$2:$CN$2,"<="&$Q$1)/COUNTIFS(W67:CN67,">="&0,$W$2:$CN$2,">"&$Q$1-365,$W$2:$CN$2,"<="&$Q$1)),"") -> 122.71429 | X67: 138 | Y67: 163 | Z67: 160 | AA67: 241 | AB67: 0 | AC67: 187 | AD67: 139 | AE67: 244 | AF67: 184 | AG67: 178 | AH67: 172 | AI67: 116 | AJ67: =IF(SUMIFS('Detalhe Por UC'!$AB:$AB,'Detalhe Por UC'!$C:$C,'Infos Clientes'!$B67,'Detalhe Por UC'!$R:$R,'Infos Clientes'!AJ$2)=0,"", SUMIFS('Detalhe Por UC'!$AB:$AB,'Detalhe Por UC'!$C:$C,'Infos Clientes'!$B67,'Detalhe Por UC'!$R:$R,'Infos Clientes'!AJ$2) +SUMIFS('Detalhe Por UC'!$AC:$AC,'Detalhe Por UC'!$C:$C,'Infos Clientes'!$B67,'Detalhe Por UC'!$R:$R,'Infos Clientes'!AJ$2)) | AK67: =IF(SUMIFS('Detalhe Por UC'!$AB:$AB,'Detalhe Por UC'!$C:$C,'Infos Clientes'!$B67,'Detalhe Por UC'!$R:$R,'Infos Clientes'!AK$2)=0,"", SUMIFS('Detalhe Por UC'!$AB:$AB,'Detalhe Por UC'!$C:$C,'Infos Clientes'!$B67,'Detalhe Por UC'!$R:$R,'Infos Clientes'!AK$2) +SUMIFS('Detalhe Por UC'!$AC:$AC,'Detalhe Por UC'!$C:$C,'Infos Clientes'!$B67,'Detalhe Por UC'!$R:$R,'Infos Clientes'!AK$2)) -> 160 | AL67: =IF(SUMIFS('Detalhe Por UC'!$AB:$AB,'Detalhe Por UC'!$C:$C,'Infos Clientes'!$B67,'Detalhe Por UC'!$R:$R,'Infos Clientes'!AL$2)=0,"", SUMIFS('Detalhe Por UC'!$AB:$AB,'Detalhe Por UC'!$C:$C,'Infos Clientes'!$B67,'Detalhe Por UC'!$R:$R,'Infos Clientes'!AL$2) +SUMIFS('Detalhe Por UC'!$AC:$AC,'Detalhe Por UC'!$C:$C,'Infos Clientes'!$B67,'Detalhe Por UC'!$R:$R,'Infos Clientes'!AL$2)) -> 160 | AM67: =IF(SUMIFS('Detalhe Por UC'!$AB:$AB,'Detalhe Por UC'!$C:$C,'Infos Clientes'!$B67,'Detalhe Por UC'!$R:$R,'Infos Clientes'!AM$2)=0,"", SUMIFS('Detalhe Por UC'!$AB:$AB,'Detalhe Por UC'!$C:$C,'Infos Clientes'!$B67,'Detalhe Por UC'!$R:$R,'Infos Clientes'!AM$2) +SUMIFS('Detalhe Por UC'!$AC:$AC,'Detalhe Por UC'!$C:$C,'Infos Clientes'!$B67,'Detalhe Por UC'!$R:$R,'Infos Clientes'!AM$2)) | AN67: =IF(SUMIFS('Detalhe Por UC'!$AB:$AB,'Detalhe Por UC'!$C:$C,'Infos Clientes'!$B67,'Detalhe Por UC'!$R:$R,'Infos Clientes'!AN$2)=0,"", SUMIFS('Detalhe Por UC'!$AB:$AB,'Detalhe Por UC'!$C:$C,'Infos Clientes'!$B67,'Detalhe Por UC'!$R:$R,'Infos Clientes'!AN$2) +SUMIFS('Detalhe Por UC'!$AC:$AC,'Detalhe Por UC'!$C:$C,'Infos Clientes'!$B67,'Detalhe Por UC'!$R:$R,'Infos Clientes'!AN$2)) -> 123 | AO67: =IF(SUMIFS('Detalhe Por UC'!$AB:$AB,'Detalhe Por UC'!$C:$C,'Infos Clientes'!$B67,'Detalhe Por UC'!$R:$R,'Infos Clientes'!AO$2)=0,"", SUMIFS('Detalhe Por UC'!$AB:$AB,'Detalhe Por UC'!$C:$C,'Infos Clientes'!$B67,'Detalhe Por UC'!$R:$R,'Infos Clientes'!AO$2) +SUMIFS('Detalhe Por UC'!$AC:$AC,'Detalhe Por UC'!$C:$C,'Infos Clientes'!$B67,'Detalhe Por UC'!$R:$R,'Infos Clientes'!AO$2)) | AP67: =IF(SUMIFS('Detalhe Por UC'!$AB:$AB,'Detalhe Por UC'!$C:$C,'Infos Clientes'!$B67,'Detalhe Por UC'!$R:$R,'Infos Clientes'!AP$2)=0,"", SUMIFS('Detalhe Por UC'!$AB:$AB,'Detalhe Por UC'!$C:$C,'Infos Clientes'!$B67,'Detalhe Por UC'!$R:$R,'Infos Clientes'!AP$2) +SUMIFS('Detalhe Por UC'!$AC:$AC,'Detalhe Por UC'!$C:$C,'Infos Clientes'!$B67,'Detalhe Por UC'!$R:$R,'Infos Clientes'!AP$2)) | AQ67: =IF(SUMIFS('Detalhe Por UC'!$AB:$AB,'Detalhe Por UC'!$C:$C,'Infos Clientes'!$B67,'Detalhe Por UC'!$R:$R,'Infos Clientes'!AQ$2)=0,"", SUMIFS('Detalhe Por UC'!$AB:$AB,'Detalhe Por UC'!$C:$C,'Infos Clientes'!$B67,'Detalhe Por UC'!$R:$R,'Infos Clientes'!AQ$2) +SUMIFS('Detalhe Por UC'!$AC:$AC,'Detalhe Por UC'!$C:$C,'Infos Clientes'!$B67,'Detalhe Por UC'!$R:$R,'Infos Clientes'!AQ$2)) -> 100 | ... AU67: =IF(SUMIFS('Detalhe Por UC'!$AB:$AB,'Detalhe Por UC'!$C:$C,'Infos Clientes'!$B67,'Detalhe Por UC'!$R:$R,'Infos Clientes'!AU$2)=0,"", SUMIFS('Detalhe Por UC'!$AB:$AB,'Detalhe Por UC'!$C:$C,'Infos Clientes'!$B67,'Detalhe Por UC'!$R:$R,'Infos Clientes'!AU$2) +SUMIFS('Detalhe Por UC'!$AC:$AC,'Detalhe Por UC'!$C:$C,'Infos Clientes'!$B67,'Detalhe Por UC'!$R:$R,'Infos Clientes'!AU$2))
B68: 10/3123706-8 | C68: =ROW(F68) -> 68 | D68: IGREJA DO EVANGELHO QUADRANGULAR | E68: 362 | F68: 62.955.505/3757-21 | G68: pastoreliasmn@hotmail.com | H68: =B68 -> 10/3123706-8 | I68: BT | J68: trifasico | K68: GIROSSOL III | M68: 0.25 | Q68: =IF(_xlfn.MINIFS('Detalhe Por UC'!R:R,'Detalhe Por UC'!C:C,B68,'Detalhe Por UC'!AD:AD,">"&0)=0,"",_xlfn.MINIFS('Detalhe Por UC'!R:R,'Detalhe Por UC'!C:C,B68,'Detalhe Por UC'!AD:AD,">"&0)) -> 45658 | R68: =IF(P68<>"ATIVO",0, IF(OR(Q68="",Q68=0,O68=0),O68, O68-ROUND((MAX('Detalhe Por UC'!R:R) -Q68)/(365/12),0))) -> 0 | T68: 365.90909 | U68: =IFERROR((SUMIFS(W68:CN68,$W$2:$CN$2,">"&$Q$1-365,$W$2:$CN$2,"<="&$Q$1)/COUNTIFS(W68:CN68,">="&0,$W$2:$CN$2,">"&$Q$1-365,$W$2:$CN$2,"<="&$Q$1)),"") -> 353.75 | X68: 314 | Y68: 337 | Z68: 354 | AA68: 403 | AB68: 0 | AC68: 370 | AD68: 375 | AE68: 430 | AF68: 368 | AG68: 397 | AH68: 355 | AI68: 320 | AJ68: =IF(SUMIFS('Detalhe Por UC'!$AB:$AB,'Detalhe Por UC'!$C:$C,'Infos Clientes'!$B68,'Detalhe Por UC'!$R:$R,'Infos Clientes'!AJ$2)=0,"", SUMIFS('Detalhe Por UC'!$AB:$AB,'Detalhe Por UC'!$C:$C,'Infos Clientes'!$B68,'Detalhe Por UC'!$R:$R,'Infos Clientes'!AJ$2) +SUMIFS('Detalhe Por UC'!$AC:$AC,'Detalhe Por UC'!$C:$C,'Infos Clientes'!$B68,'Detalhe Por UC'!$R:$R,'Infos Clientes'!AJ$2)) -> 316 | AK68: =IF(SUMIFS('Detalhe Por UC'!$AB:$AB,'Detalhe Por UC'!$C:$C,'Infos Clientes'!$B68,'Detalhe Por UC'!$R:$R,'Infos Clientes'!AK$2)=0,"", SUMIFS('Detalhe Por UC'!$AB:$AB,'Detalhe Por UC'!$C:$C,'Infos Clientes'!$B68,'Detalhe Por UC'!$R:$R,'Infos Clientes'!AK$2) +SUMIFS('Detalhe Por UC'!$AC:$AC,'Detalhe Por UC'!$C:$C,'Infos Clientes'!$B68,'Detalhe Por UC'!$R:$R,'Infos Clientes'!AK$2)) -> 307 | AL68: =IF(SUMIFS('Detalhe Por UC'!$AB:$AB,'Detalhe Por UC'!$C:$C,'Infos Clientes'!$B68,'Detalhe Por UC'!$R:$R,'Infos Clientes'!AL$2)=0,"", SUMIFS('Detalhe Por UC'!$AB:$AB,'Detalhe Por UC'!$C:$C,'Infos Clientes'!$B68,'Detalhe Por UC'!$R:$R,'Infos Clientes'!AL$2) +SUMIFS('Detalhe Por UC'!$AC:$AC,'Detalhe Por UC'!$C:$C,'Infos Clientes'!$B68,'Detalhe Por UC'!$R:$R,'Infos Clientes'!AL$2)) -> 400 | AM68: =IF(SUMIFS('Detalhe Por UC'!$AB:$AB,'Detalhe Por UC'!$C:$C,'Infos Clientes'!$B68,'Detalhe Por UC'!$R:$R,'Infos Clientes'!AM$2)=0,"", SUMIFS('Detalhe Por UC'!$AB:$AB,'Detalhe Por UC'!$C:$C,'Infos Clientes'!$B68,'Detalhe Por UC'!$R:$R,'Infos Clientes'!AM$2) +SUMIFS('Detalhe Por UC'!$AC:$AC,'Detalhe Por UC'!$C:$C,'Infos Clientes'!$B68,'Detalhe Por UC'!$R:$R,'Infos Clientes'!AM$2)) -> 320 | AN68: =IF(SUMIFS('Detalhe Por UC'!$AB:$AB,'Detalhe Por UC'!$C:$C,'Infos Clientes'!$B68,'Detalhe Por UC'!$R:$R,'Infos Clientes'!AN$2)=0,"", SUMIFS('Detalhe Por UC'!$AB:$AB,'Detalhe Por UC'!$C:$C,'Infos Clientes'!$B68,'Detalhe Por UC'!$R:$R,'Infos Clientes'!AN$2) +SUMIFS('Detalhe Por UC'!$AC:$AC,'Detalhe Por UC'!$C:$C,'Infos Clientes'!$B68,'Detalhe Por UC'!$R:$R,'Infos Clientes'!AN$2)) -> 355 | AO68: =IF(SUMIFS('Detalhe Por UC'!$AB:$AB,'Detalhe Por UC'!$C:$C,'Infos Clientes'!$B68,'Detalhe Por UC'!$R:$R,'Infos Clientes'!AO$2)=0,"", SUMIFS('Detalhe Por UC'!$AB:$AB,'Detalhe Por UC'!$C:$C,'Infos Clientes'!$B68,'Detalhe Por UC'!$R:$R,'Infos Clientes'!AO$2) +SUMIFS('Detalhe Por UC'!$AC:$AC,'Detalhe Por UC'!$C:$C,'Infos Clientes'!$B68,'Detalhe Por UC'!$R:$R,'Infos Clientes'!AO$2)) -> 400 | AP68: =IF(SUMIFS('Detalhe Por UC'!$AB:$AB,'Detalhe Por UC'!$C:$C,'Infos Clientes'!$B68,'Detalhe Por UC'!$R:$R,'Infos Clientes'!AP$2)=0,"", SUMIFS('Detalhe Por UC'!$AB:$AB,'Detalhe Por UC'!$C:$C,'Infos Clientes'!$B68,'Detalhe Por UC'!$R:$R,'Infos Clientes'!AP$2) +SUMIFS('Detalhe Por UC'!$AC:$AC,'Detalhe Por UC'!$C:$C,'Infos Clientes'!$B68,'Detalhe Por UC'!$R:$R,'Infos Clientes'!AP$2)) -> 355 | AQ68: =IF(SUMIFS('Detalhe Por UC'!$AB:$AB,'Detalhe Por UC'!$C:$C,'Infos Clientes'!$B68,'Detalhe Por UC'!$R:$R,'Infos Clientes'!AQ$2)=0,"", SUMIFS('Detalhe Por UC'!$AB:$AB,'Detalhe Por UC'!$C:$C,'Infos Clientes'!$B68,'Detalhe Por UC'!$R:$R,'Infos Clientes'!AQ$2) +SUMIFS('Detalhe Por UC'!$AC:$AC,'Detalhe Por UC'!$C:$C,'Infos Clientes'!$B68,'Detalhe Por UC'!$R:$R,'Infos Clientes'!AQ$2)) -> 317 | ... AU68: =IF(SUMIFS('Detalhe Por UC'!$AB:$AB,'Detalhe Por UC'!$C:$C,'Infos Clientes'!$B68,'Detalhe Por UC'!$R:$R,'Infos Clientes'!AU$2)=0,"", SUMIFS('Detalhe Por UC'!$AB:$AB,'Detalhe Por UC'!$C:$C,'Infos Clientes'!$B68,'Detalhe Por UC'!$R:$R,'Infos Clientes'!AU$2) +SUMIFS('Detalhe Por UC'!$AC:$AC,'Detalhe Por UC'!$C:$C,'Infos Clientes'!$B68,'Detalhe Por UC'!$R:$R,'Infos Clientes'!AU$2))
B69: 10/3125732-2 | C69: =ROW(F69) -> 69 | D69: IGREJA DO EVANGELHO QUADRANGULAR | E69: 358 | F69: 62.955.505/0155-12 | G69: regiao358ms@gmail.com | H69: =B69 -> 10/3125732-2 | I69: BT | J69: bifasico | K69: GIROSSOL III | M69: 0.25 | Q69: =IF(_xlfn.MINIFS('Detalhe Por UC'!R:R,'Detalhe Por UC'!C:C,B69,'Detalhe Por UC'!AD:AD,">"&0)=0,"",_xlfn.MINIFS('Detalhe Por UC'!R:R,'Detalhe Por UC'!C:C,B69,'Detalhe Por UC'!AD:AD,">"&0)) -> 45658 | R69: =IF(P69<>"ATIVO",0, IF(OR(Q69="",Q69=0,O69=0),O69, O69-ROUND((MAX('Detalhe Por UC'!R:R) -Q69)/(365/12),0))) -> 0 | T69: 164.36364 | U69: =IFERROR((SUMIFS(W69:CN69,$W$2:$CN$2,">"&$Q$1-365,$W$2:$CN$2,"<="&$Q$1)/COUNTIFS(W69:CN69,">="&0,$W$2:$CN$2,">"&$Q$1-365,$W$2:$CN$2,"<="&$Q$1)),"") -> 192.27273 | X69: 112 | Y69: 105 | Z69: 220 | AA69: 190 | AB69: 0 | AC69: 79 | AD69: 84 | AE69: 145 | AF69: 187 | AG69: 184 | AH69: 177 | AI69: 222 | AJ69: =IF(SUMIFS('Detalhe Por UC'!$AB:$AB,'Detalhe Por UC'!$C:$C,'Infos Clientes'!$B69,'Detalhe Por UC'!$R:$R,'Infos Clientes'!AJ$2)=0,"", SUMIFS('Detalhe Por UC'!$AB:$AB,'Detalhe Por UC'!$C:$C,'Infos Clientes'!$B69,'Detalhe Por UC'!$R:$R,'Infos Clientes'!AJ$2) +SUMIFS('Detalhe Por UC'!$AC:$AC,'Detalhe Por UC'!$C:$C,'Infos Clientes'!$B69,'Detalhe Por UC'!$R:$R,'Infos Clientes'!AJ$2)) -> 215 | AK69: =IF(SUMIFS('Detalhe Por UC'!$AB:$AB,'Detalhe Por UC'!$C:$C,'Infos Clientes'!$B69,'Detalhe Por UC'!$R:$R,'Infos Clientes'!AK$2)=0,"", SUMIFS('Detalhe Por UC'!$AB:$AB,'Detalhe Por UC'!$C:$C,'Infos Clientes'!$B69,'Detalhe Por UC'!$R:$R,'Infos Clientes'!AK$2) +SUMIFS('Detalhe Por UC'!$AC:$AC,'Detalhe Por UC'!$C:$C,'Infos Clientes'!$B69,'Detalhe Por UC'!$R:$R,'Infos Clientes'!AK$2)) -> 244 | AL69: =IF(SUMIFS('Detalhe Por UC'!$AB:$AB,'Detalhe Por UC'!$C:$C,'Infos Clientes'!$B69,'Detalhe Por UC'!$R:$R,'Infos Clientes'!AL$2)=0,"", SUMIFS('Detalhe Por UC'!$AB:$AB,'Detalhe Por UC'!$C:$C,'Infos Clientes'!$B69,'Detalhe Por UC'!$R:$R,'Infos Clientes'!AL$2) +SUMIFS('Detalhe Por UC'!$AC:$AC,'Detalhe Por UC'!$C:$C,'Infos Clientes'!$B69,'Detalhe Por UC'!$R:$R,'Infos Clientes'!AL$2)) -> 208 | AM69: =IF(SUMIFS('Detalhe Por UC'!$AB:$AB,'Detalhe Por UC'!$C:$C,'Infos Clientes'!$B69,'Detalhe Por UC'!$R:$R,'Infos Clientes'!AM$2)=0,"", SUMIFS('Detalhe Por UC'!$AB:$AB,'Detalhe Por UC'!$C:$C,'Infos Clientes'!$B69,'Detalhe Por UC'!$R:$R,'Infos Clientes'!AM$2) +SUMIFS('Detalhe Por UC'!$AC:$AC,'Detalhe Por UC'!$C:$C,'Infos Clientes'!$B69,'Detalhe Por UC'!$R:$R,'Infos Clientes'!AM$2)) -> 198 | AN69: =IF(SUMIFS('Detalhe Por UC'!$AB:$AB,'Detalhe Por UC'!$C:$C,'Infos Clientes'!$B69,'Detalhe Por UC'!$R:$R,'Infos Clientes'!AN$2)=0,"", SUMIFS('Detalhe Por UC'!$AB:$AB,'Detalhe Por UC'!$C:$C,'Infos Clientes'!$B69,'Detalhe Por UC'!$R:$R,'Infos Clientes'!AN$2) +SUMIFS('Detalhe Por UC'!$AC:$AC,'Detalhe Por UC'!$C:$C,'Infos Clientes'!$B69,'Detalhe Por UC'!$R:$R,'Infos Clientes'!AN$2)) -> 183 | AO69: =IF(SUMIFS('Detalhe Por UC'!$AB:$AB,'Detalhe Por UC'!$C:$C,'Infos Clientes'!$B69,'Detalhe Por UC'!$R:$R,'Infos Clientes'!AO$2)=0,"", SUMIFS('Detalhe Por UC'!$AB:$AB,'Detalhe Por UC'!$C:$C,'Infos Clientes'!$B69,'Detalhe Por UC'!$R:$R,'Infos Clientes'!AO$2) +SUMIFS('Detalhe Por UC'!$AC:$AC,'Detalhe Por UC'!$C:$C,'Infos Clientes'!$B69,'Detalhe Por UC'!$R:$R,'Infos Clientes'!AO$2)) -> 176 | AP69: =IF(SUMIFS('Detalhe Por UC'!$AB:$AB,'Detalhe Por UC'!$C:$C,'Infos Clientes'!$B69,'Detalhe Por UC'!$R:$R,'Infos Clientes'!AP$2)=0,"", SUMIFS('Detalhe Por UC'!$AB:$AB,'Detalhe Por UC'!$C:$C,'Infos Clientes'!$B69,'Detalhe Por UC'!$R:$R,'Infos Clientes'!AP$2) +SUMIFS('Detalhe Por UC'!$AC:$AC,'Detalhe Por UC'!$C:$C,'Infos Clientes'!$B69,'Detalhe Por UC'!$R:$R,'Infos Clientes'!AP$2)) -> 136 | AQ69: =IF(SUMIFS('Detalhe Por UC'!$AB:$AB,'Detalhe Por UC'!$C:$C,'Infos Clientes'!$B69,'Detalhe Por UC'!$R:$R,'Infos Clientes'!AQ$2)=0,"", SUMIFS('Detalhe Por UC'!$AB:$AB,'Detalhe Por UC'!$C:$C,'Infos Clientes'!$B69,'Detalhe Por UC'!$R:$R,'Infos Clientes'!AQ$2) +SUMIFS('Detalhe Por UC'!$AC:$AC,'Detalhe Por UC'!$C:$C,'Infos Clientes'!$B69,'Detalhe Por UC'!$R:$R,'Infos Clientes'!AQ$2)) -> 154 | ... AU69: =IF(SUMIFS('Detalhe Por UC'!$AB:$AB,'Detalhe Por UC'!$C:$C,'Infos Clientes'!$B69,'Detalhe Por UC'!$R:$R,'Infos Clientes'!AU$2)=0,"", SUMIFS('Detalhe Por UC'!$AB:$AB,'Detalhe Por UC'!$C:$C,'Infos Clientes'!$B69,'Detalhe Por UC'!$R:$R,'Infos Clientes'!AU$2) +SUMIFS('Detalhe Por UC'!$AC:$AC,'Detalhe Por UC'!$C:$C,'Infos Clientes'!$B69,'Detalhe Por UC'!$R:$R,'Infos Clientes'!AU$2))
B70: 10/31292-6 | C70: 51 | D70: IGREJA DO EVANGELHO QUADRANGULAR | E70: 357 | F70: 62.955.505/0160-80 | G70: marizesouzar@gmail.com; regiao.357@hotmail.com | H70: =B70 -> 10/31292-6 | I70: BT | J70: bifasico | K70: GIROSSOL III | M70: 0.25 | Q70: =IF(_xlfn.MINIFS('Detalhe Por UC'!R:R,'Detalhe Por UC'!C:C,B70,'Detalhe Por UC'!AD:AD,">"&0)=0,"",_xlfn.MINIFS('Detalhe Por UC'!R:R,'Detalhe Por UC'!C:C,B70,'Detalhe Por UC'!AD:AD,">"&0)) -> 45658 | R70: =IF(P70<>"ATIVO",0, IF(OR(Q70="",Q70=0,O70=0),O70, O70-ROUND((MAX('Detalhe Por UC'!R:R) -Q70)/(365/12),0))) -> 0 | T70: 167.54545 | U70: =IFERROR((SUMIFS(W70:CN70,$W$2:$CN$2,">"&$Q$1-365,$W$2:$CN$2,"<="&$Q$1)/COUNTIFS(W70:CN70,">="&0,$W$2:$CN$2,">"&$Q$1-365,$W$2:$CN$2,"<="&$Q$1)),"") -> 177.4 | X70: 151 | Y70: 155 | Z70: 227 | AA70: 238 | AB70: 0 | AC70: 116 | AD70: 144 | AE70: 139 | AF70: 97 | AG70: 156 | AH70: 199 | AI70: 230 | AJ70: =IF(SUMIFS('Detalhe Por UC'!$AB:$AB,'Detalhe Por UC'!$C:$C,'Infos Clientes'!$B70,'Detalhe Por UC'!$R:$R,'Infos Clientes'!AJ$2)=0,"", SUMIFS('Detalhe Por UC'!$AB:$AB,'Detalhe Por UC'!$C:$C,'Infos Clientes'!$B70,'Detalhe Por UC'!$R:$R,'Infos Clientes'!AJ$2) +SUMIFS('Detalhe Por UC'!$AC:$AC,'Detalhe Por UC'!$C:$C,'Infos Clientes'!$B70,'Detalhe Por UC'!$R:$R,'Infos Clientes'!AJ$2)) -> 142 | AK70: =IF(SUMIFS('Detalhe Por UC'!$AB:$AB,'Detalhe Por UC'!$C:$C,'Infos Clientes'!$B70,'Detalhe Por UC'!$R:$R,'Infos Clientes'!AK$2)=0,"", SUMIFS('Detalhe Por UC'!$AB:$AB,'Detalhe Por UC'!$C:$C,'Infos Clientes'!$B70,'Detalhe Por UC'!$R:$R,'Infos Clientes'!AK$2) +SUMIFS('Detalhe Por UC'!$AC:$AC,'Detalhe Por UC'!$C:$C,'Infos Clientes'!$B70,'Detalhe Por UC'!$R:$R,'Infos Clientes'!AK$2)) -> 184 | AL70: =IF(SUMIFS('Detalhe Por UC'!$AB:$AB,'Detalhe Por UC'!$C:$C,'Infos Clientes'!$B70,'Detalhe Por UC'!$R:$R,'Infos Clientes'!AL$2)=0,"", SUMIFS('Detalhe Por UC'!$AB:$AB,'Detalhe Por UC'!$C:$C,'Infos Clientes'!$B70,'Detalhe Por UC'!$R:$R,'Infos Clientes'!AL$2) +SUMIFS('Detalhe Por UC'!$AC:$AC,'Detalhe Por UC'!$C:$C,'Infos Clientes'!$B70,'Detalhe Por UC'!$R:$R,'Infos Clientes'!AL$2)) -> 170 | AM70: =IF(SUMIFS('Detalhe Por UC'!$AB:$AB,'Detalhe Por UC'!$C:$C,'Infos Clientes'!$B70,'Detalhe Por UC'!$R:$R,'Infos Clientes'!AM$2)=0,"", SUMIFS('Detalhe Por UC'!$AB:$AB,'Detalhe Por UC'!$C:$C,'Infos Clientes'!$B70,'Detalhe Por UC'!$R:$R,'Infos Clientes'!AM$2) +SUMIFS('Detalhe Por UC'!$AC:$AC,'Detalhe Por UC'!$C:$C,'Infos Clientes'!$B70,'Detalhe Por UC'!$R:$R,'Infos Clientes'!AM$2)) -> 161 | AN70: =IF(SUMIFS('Detalhe Por UC'!$AB:$AB,'Detalhe Por UC'!$C:$C,'Infos Clientes'!$B70,'Detalhe Por UC'!$R:$R,'Infos Clientes'!AN$2)=0,"", SUMIFS('Detalhe Por UC'!$AB:$AB,'Detalhe Por UC'!$C:$C,'Infos Clientes'!$B70,'Detalhe Por UC'!$R:$R,'Infos Clientes'!AN$2) +SUMIFS('Detalhe Por UC'!$AC:$AC,'Detalhe Por UC'!$C:$C,'Infos Clientes'!$B70,'Detalhe Por UC'!$R:$R,'Infos Clientes'!AN$2)) | AO70: =IF(SUMIFS('Detalhe Por UC'!$AB:$AB,'Detalhe Por UC'!$C:$C,'Infos Clientes'!$B70,'Detalhe Por UC'!$R:$R,'Infos Clientes'!AO$2)=0,"", SUMIFS('Detalhe Por UC'!$AB:$AB,'Detalhe Por UC'!$C:$C,'Infos Clientes'!$B70,'Detalhe Por UC'!$R:$R,'Infos Clientes'!AO$2) +SUMIFS('Detalhe Por UC'!$AC:$AC,'Detalhe Por UC'!$C:$C,'Infos Clientes'!$B70,'Detalhe Por UC'!$R:$R,'Infos Clientes'!AO$2)) | AP70: =IF(SUMIFS('Detalhe Por UC'!$AB:$AB,'Detalhe Por UC'!$C:$C,'Infos Clientes'!$B70,'Detalhe Por UC'!$R:$R,'Infos Clientes'!AP$2)=0,"", SUMIFS('Detalhe Por UC'!$AB:$AB,'Detalhe Por UC'!$C:$C,'Infos Clientes'!$B70,'Detalhe Por UC'!$R:$R,'Infos Clientes'!AP$2) +SUMIFS('Detalhe Por UC'!$AC:$AC,'Detalhe Por UC'!$C:$C,'Infos Clientes'!$B70,'Detalhe Por UC'!$R:$R,'Infos Clientes'!AP$2)) | AQ70: =IF(SUMIFS('Detalhe Por UC'!$AB:$AB,'Detalhe Por UC'!$C:$C,'Infos Clientes'!$B70,'Detalhe Por UC'!$R:$R,'Infos Clientes'!AQ$2)=0,"", SUMIFS('Detalhe Por UC'!$AB:$AB,'Detalhe Por UC'!$C:$C,'Infos Clientes'!$B70,'Detalhe Por UC'!$R:$R,'Infos Clientes'!AQ$2) +SUMIFS('Detalhe Por UC'!$AC:$AC,'Detalhe Por UC'!$C:$C,'Infos Clientes'!$B70,'Detalhe Por UC'!$R:$R,'Infos Clientes'!AQ$2)) | ... AU70: =IF(SUMIFS('Detalhe Por UC'!$AB:$AB,'Detalhe Por UC'!$C:$C,'Infos Clientes'!$B70,'Detalhe Por UC'!$R:$R,'Infos Clientes'!AU$2)=0,"", SUMIFS('Detalhe Por UC'!$AB:$AB,'Detalhe Por UC'!$C:$C,'Infos Clientes'!$B70,'Detalhe Por UC'!$R:$R,'Infos Clientes'!AU$2) +SUMIFS('Detalhe Por UC'!$AC:$AC,'Detalhe Por UC'!$C:$C,'Infos Clientes'!$B70,'Detalhe Por UC'!$R:$R,'Infos Clientes'!AU$2))
B71: 10/3139326-7 | C71: =ROW(F71) -> 71 | D71: IGREJA DO EVANGELHO QUADRANGULAR | E71: 319 | F71: 62.955.505/1822-57 | G71: auxiliar.cedms@gmail.com | H71: =B71 -> 10/3139326-7 | I71: BT | J71: trifasico | K71: GIROSSOL III | M71: 0.25 | Q71: =IF(_xlfn.MINIFS('Detalhe Por UC'!R:R,'Detalhe Por UC'!C:C,B71,'Detalhe Por UC'!AD:AD,">"&0)=0,"",_xlfn.MINIFS('Detalhe Por UC'!R:R,'Detalhe Por UC'!C:C,B71,'Detalhe Por UC'!AD:AD,">"&0)) -> 45658 | R71: =IF(P71<>"ATIVO",0, IF(OR(Q71="",Q71=0,O71=0),O71, O71-ROUND((MAX('Detalhe Por UC'!R:R) -Q71)/(365/12),0))) -> 0 | T71: 502.09091 | U71: =IFERROR((SUMIFS(W71:CN71,$W$2:$CN$2,">"&$Q$1-365,$W$2:$CN$2,"<="&$Q$1)/COUNTIFS(W71:CN71,">="&0,$W$2:$CN$2,">"&$Q$1-365,$W$2:$CN$2,"<="&$Q$1)),"") -> 443.08333 | X71: 527 | Y71: 576 | Z71: 745 | AA71: 660 | AB71: 0 | AC71: 444 | AD71: 414 | AE71: 412 | AF71: 371 | AG71: 449 | AH71: 528 | AI71: 523 | AJ71: =IF(SUMIFS('Detalhe Por UC'!$AB:$AB,'Detalhe Por UC'!$C:$C,'Infos Clientes'!$B71,'Detalhe Por UC'!$R:$R,'Infos Clientes'!AJ$2)=0,"", SUMIFS('Detalhe Por UC'!$AB:$AB,'Detalhe Por UC'!$C:$C,'Infos Clientes'!$B71,'Detalhe Por UC'!$R:$R,'Infos Clientes'!AJ$2) +SUMIFS('Detalhe Por UC'!$AC:$AC,'Detalhe Por UC'!$C:$C,'Infos Clientes'!$B71,'Detalhe Por UC'!$R:$R,'Infos Clientes'!AJ$2)) -> 401 | AK71: =IF(SUMIFS('Detalhe Por UC'!$AB:$AB,'Detalhe Por UC'!$C:$C,'Infos Clientes'!$B71,'Detalhe Por UC'!$R:$R,'Infos Clientes'!AK$2)=0,"", SUMIFS('Detalhe Por UC'!$AB:$AB,'Detalhe Por UC'!$C:$C,'Infos Clientes'!$B71,'Detalhe Por UC'!$R:$R,'Infos Clientes'!AK$2) +SUMIFS('Detalhe Por UC'!$AC:$AC,'Detalhe Por UC'!$C:$C,'Infos Clientes'!$B71,'Detalhe Por UC'!$R:$R,'Infos Clientes'!AK$2)) -> 493 | AL71: =IF(SUMIFS('Detalhe Por UC'!$AB:$AB,'Detalhe Por UC'!$C:$C,'Infos Clientes'!$B71,'Detalhe Por UC'!$R:$R,'Infos Clientes'!AL$2)=0,"", SUMIFS('Detalhe Por UC'!$AB:$AB,'Detalhe Por UC'!$C:$C,'Infos Clientes'!$B71,'Detalhe Por UC'!$R:$R,'Infos Clientes'!AL$2) +SUMIFS('Detalhe Por UC'!$AC:$AC,'Detalhe Por UC'!$C:$C,'Infos Clientes'!$B71,'Detalhe Por UC'!$R:$R,'Infos Clientes'!AL$2)) -> 590 | AM71: =IF(SUMIFS('Detalhe Por UC'!$AB:$AB,'Detalhe Por UC'!$C:$C,'Infos Clientes'!$B71,'Detalhe Por UC'!$R:$R,'Infos Clientes'!AM$2)=0,"", SUMIFS('Detalhe Por UC'!$AB:$AB,'Detalhe Por UC'!$C:$C,'Infos Clientes'!$B71,'Detalhe Por UC'!$R:$R,'Infos Clientes'!AM$2) +SUMIFS('Detalhe Por UC'!$AC:$AC,'Detalhe Por UC'!$C:$C,'Infos Clientes'!$B71,'Detalhe Por UC'!$R:$R,'Infos Clientes'!AM$2)) -> 493 | AN71: =IF(SUMIFS('Detalhe Por UC'!$AB:$AB,'Detalhe Por UC'!$C:$C,'Infos Clientes'!$B71,'Detalhe Por UC'!$R:$R,'Infos Clientes'!AN$2)=0,"", SUMIFS('Detalhe Por UC'!$AB:$AB,'Detalhe Por UC'!$C:$C,'Infos Clientes'!$B71,'Detalhe Por UC'!$R:$R,'Infos Clientes'!AN$2) +SUMIFS('Detalhe Por UC'!$AC:$AC,'Detalhe Por UC'!$C:$C,'Infos Clientes'!$B71,'Detalhe Por UC'!$R:$R,'Infos Clientes'!AN$2)) -> 384 | AO71: =IF(SUMIFS('Detalhe Por UC'!$AB:$AB,'Detalhe Por UC'!$C:$C,'Infos Clientes'!$B71,'Detalhe Por UC'!$R:$R,'Infos Clientes'!AO$2)=0,"", SUMIFS('Detalhe Por UC'!$AB:$AB,'Detalhe Por UC'!$C:$C,'Infos Clientes'!$B71,'Detalhe Por UC'!$R:$R,'Infos Clientes'!AO$2) +SUMIFS('Detalhe Por UC'!$AC:$AC,'Detalhe Por UC'!$C:$C,'Infos Clientes'!$B71,'Detalhe Por UC'!$R:$R,'Infos Clientes'!AO$2)) -> 420 | AP71: =IF(SUMIFS('Detalhe Por UC'!$AB:$AB,'Detalhe Por UC'!$C:$C,'Infos Clientes'!$B71,'Detalhe Por UC'!$R:$R,'Infos Clientes'!AP$2)=0,"", SUMIFS('Detalhe Por UC'!$AB:$AB,'Detalhe Por UC'!$C:$C,'Infos Clientes'!$B71,'Detalhe Por UC'!$R:$R,'Infos Clientes'!AP$2) +SUMIFS('Detalhe Por UC'!$AC:$AC,'Detalhe Por UC'!$C:$C,'Infos Clientes'!$B71,'Detalhe Por UC'!$R:$R,'Infos Clientes'!AP$2)) -> 363 | AQ71: =IF(SUMIFS('Detalhe Por UC'!$AB:$AB,'Detalhe Por UC'!$C:$C,'Infos Clientes'!$B71,'Detalhe Por UC'!$R:$R,'Infos Clientes'!AQ$2)=0,"", SUMIFS('Detalhe Por UC'!$AB:$AB,'Detalhe Por UC'!$C:$C,'Infos Clientes'!$B71,'Detalhe Por UC'!$R:$R,'Infos Clientes'!AQ$2) +SUMIFS('Detalhe Por UC'!$AC:$AC,'Detalhe Por UC'!$C:$C,'Infos Clientes'!$B71,'Detalhe Por UC'!$R:$R,'Infos Clientes'!AQ$2)) -> 386 | ... AU71: =IF(SUMIFS('Detalhe Por UC'!$AB:$AB,'Detalhe Por UC'!$C:$C,'Infos Clientes'!$B71,'Detalhe Por UC'!$R:$R,'Infos Clientes'!AU$2)=0,"", SUMIFS('Detalhe Por UC'!$AB:$AB,'Detalhe Por UC'!$C:$C,'Infos Clientes'!$B71,'Detalhe Por UC'!$R:$R,'Infos Clientes'!AU$2) +SUMIFS('Detalhe Por UC'!$AC:$AC,'Detalhe Por UC'!$C:$C,'Infos Clientes'!$B71,'Detalhe Por UC'!$R:$R,'Infos Clientes'!AU$2))
B72: 10/341308-5 | C72: =ROW(F72) -> 72 | D72: IGREJA DO EVANGELHO QUADRANGULAR | E72: 306 | F72: 62.955.505/2391-19 | G72: auxiliar.cedms@gmail.com | H72: =B72 -> 10/341308-5 | I72: BT | J72: bifasico | K72: GIROSSOL III | M72: 0.25 | Q72: =IF(_xlfn.MINIFS('Detalhe Por UC'!R:R,'Detalhe Por UC'!C:C,B72,'Detalhe Por UC'!AD:AD,">"&0)=0,"",_xlfn.MINIFS('Detalhe Por UC'!R:R,'Detalhe Por UC'!C:C,B72,'Detalhe Por UC'!AD:AD,">"&0)) -> 45658 | R72: =IF(P72<>"ATIVO",0, IF(OR(Q72="",Q72=0,O72=0),O72, O72-ROUND((MAX('Detalhe Por UC'!R:R) -Q72)/(365/12),0))) -> 0 | T72: 330.27273 | U72: =IFERROR((SUMIFS(W72:CN72,$W$2:$CN$2,">"&$Q$1-365,$W$2:$CN$2,"<="&$Q$1)/COUNTIFS(W72:CN72,">="&0,$W$2:$CN$2,">"&$Q$1-365,$W$2:$CN$2,"<="&$Q$1)),"") -> 276.91667 | X72: 158 | Y72: 373 | Z72: 428 | AA72: 402 | AB72: 0 | AC72: 308 | AD72: 343 | AE72: 313 | AF72: 248 | AG72: 335 | AH72: 294 | AI72: 311 | AJ72: =IF(SUMIFS('Detalhe Por UC'!$AB:$AB,'Detalhe Por UC'!$C:$C,'Infos Clientes'!$B72,'Detalhe Por UC'!$R:$R,'Infos Clientes'!AJ$2)=0,"", SUMIFS('Detalhe Por UC'!$AB:$AB,'Detalhe Por UC'!$C:$C,'Infos Clientes'!$B72,'Detalhe Por UC'!$R:$R,'Infos Clientes'!AJ$2) +SUMIFS('Detalhe Por UC'!$AC:$AC,'Detalhe Por UC'!$C:$C,'Infos Clientes'!$B72,'Detalhe Por UC'!$R:$R,'Infos Clientes'!AJ$2)) -> 278 | AK72: =IF(SUMIFS('Detalhe Por UC'!$AB:$AB,'Detalhe Por UC'!$C:$C,'Infos Clientes'!$B72,'Detalhe Por UC'!$R:$R,'Infos Clientes'!AK$2)=0,"", SUMIFS('Detalhe Por UC'!$AB:$AB,'Detalhe Por UC'!$C:$C,'Infos Clientes'!$B72,'Detalhe Por UC'!$R:$R,'Infos Clientes'!AK$2) +SUMIFS('Detalhe Por UC'!$AC:$AC,'Detalhe Por UC'!$C:$C,'Infos Clientes'!$B72,'Detalhe Por UC'!$R:$R,'Infos Clientes'!AK$2)) -> 374 | AL72: =IF(SUMIFS('Detalhe Por UC'!$AB:$AB,'Detalhe Por UC'!$C:$C,'Infos Clientes'!$B72,'Detalhe Por UC'!$R:$R,'Infos Clientes'!AL$2)=0,"", SUMIFS('Detalhe Por UC'!$AB:$AB,'Detalhe Por UC'!$C:$C,'Infos Clientes'!$B72,'Detalhe Por UC'!$R:$R,'Infos Clientes'!AL$2) +SUMIFS('Detalhe Por UC'!$AC:$AC,'Detalhe Por UC'!$C:$C,'Infos Clientes'!$B72,'Detalhe Por UC'!$R:$R,'Infos Clientes'!AL$2)) -> 359 | AM72: =IF(SUMIFS('Detalhe Por UC'!$AB:$AB,'Detalhe Por UC'!$C:$C,'Infos Clientes'!$B72,'Detalhe Por UC'!$R:$R,'Infos Clientes'!AM$2)=0,"", SUMIFS('Detalhe Por UC'!$AB:$AB,'Detalhe Por UC'!$C:$C,'Infos Clientes'!$B72,'Detalhe Por UC'!$R:$R,'Infos Clientes'!AM$2) +SUMIFS('Detalhe Por UC'!$AC:$AC,'Detalhe Por UC'!$C:$C,'Infos Clientes'!$B72,'Detalhe Por UC'!$R:$R,'Infos Clientes'!AM$2)) -> 325 | AN72: =IF(SUMIFS('Detalhe Por UC'!$AB:$AB,'Detalhe Por UC'!$C:$C,'Infos Clientes'!$B72,'Detalhe Por UC'!$R:$R,'Infos Clientes'!AN$2)=0,"", SUMIFS('Detalhe Por UC'!$AB:$AB,'Detalhe Por UC'!$C:$C,'Infos Clientes'!$B72,'Detalhe Por UC'!$R:$R,'Infos Clientes'!AN$2) +SUMIFS('Detalhe Por UC'!$AC:$AC,'Detalhe Por UC'!$C:$C,'Infos Clientes'!$B72,'Detalhe Por UC'!$R:$R,'Infos Clientes'!AN$2)) -> 279 | AO72: =IF(SUMIFS('Detalhe Por UC'!$AB:$AB,'Detalhe Por UC'!$C:$C,'Infos Clientes'!$B72,'Detalhe Por UC'!$R:$R,'Infos Clientes'!AO$2)=0,"", SUMIFS('Detalhe Por UC'!$AB:$AB,'Detalhe Por UC'!$C:$C,'Infos Clientes'!$B72,'Detalhe Por UC'!$R:$R,'Infos Clientes'!AO$2) +SUMIFS('Detalhe Por UC'!$AC:$AC,'Detalhe Por UC'!$C:$C,'Infos Clientes'!$B72,'Detalhe Por UC'!$R:$R,'Infos Clientes'!AO$2)) -> 228 | AP72: =IF(SUMIFS('Detalhe Por UC'!$AB:$AB,'Detalhe Por UC'!$C:$C,'Infos Clientes'!$B72,'Detalhe Por UC'!$R:$R,'Infos Clientes'!AP$2)=0,"", SUMIFS('Detalhe Por UC'!$AB:$AB,'Detalhe Por UC'!$C:$C,'Infos Clientes'!$B72,'Detalhe Por UC'!$R:$R,'Infos Clientes'!AP$2) +SUMIFS('Detalhe Por UC'!$AC:$AC,'Detalhe Por UC'!$C:$C,'Infos Clientes'!$B72,'Detalhe Por UC'!$R:$R,'Infos Clientes'!AP$2)) -> 222 | AQ72: =IF(SUMIFS('Detalhe Por UC'!$AB:$AB,'Detalhe Por UC'!$C:$C,'Infos Clientes'!$B72,'Detalhe Por UC'!$R:$R,'Infos Clientes'!AQ$2)=0,"", SUMIFS('Detalhe Por UC'!$AB:$AB,'Detalhe Por UC'!$C:$C,'Infos Clientes'!$B72,'Detalhe Por UC'!$R:$R,'Infos Clientes'!AQ$2) +SUMIFS('Detalhe Por UC'!$AC:$AC,'Detalhe Por UC'!$C:$C,'Infos Clientes'!$B72,'Detalhe Por UC'!$R:$R,'Infos Clientes'!AQ$2)) -> 233 | ... AU72: =IF(SUMIFS('Detalhe Por UC'!$AB:$AB,'Detalhe Por UC'!$C:$C,'Infos Clientes'!$B72,'Detalhe Por UC'!$R:$R,'Infos Clientes'!AU$2)=0,"", SUMIFS('Detalhe Por UC'!$AB:$AB,'Detalhe Por UC'!$C:$C,'Infos Clientes'!$B72,'Detalhe Por UC'!$R:$R,'Infos Clientes'!AU$2) +SUMIFS('Detalhe Por UC'!$AC:$AC,'Detalhe Por UC'!$C:$C,'Infos Clientes'!$B72,'Detalhe Por UC'!$R:$R,'Infos Clientes'!AU$2))
B73: 10/395471-6 | C73: =ROW(F73) -> 73 | D73: IGREJA DO EVANGELHO QUADRANGULAR | E73: 306 | F73: 62.955.505/2488-86 | G73: auxiliar.cedms@gmail.com | H73: =B73 -> 10/395471-6 | I73: BT | J73: trifasico | K73: GIROSSOL III | M73: 0.25 | Q73: =IF(_xlfn.MINIFS('Detalhe Por UC'!R:R,'Detalhe Por UC'!C:C,B73,'Detalhe Por UC'!AD:AD,">"&0)=0,"",_xlfn.MINIFS('Detalhe Por UC'!R:R,'Detalhe Por UC'!C:C,B73,'Detalhe Por UC'!AD:AD,">"&0)) -> 45658 | R73: =IF(P73<>"ATIVO",0, IF(OR(Q73="",Q73=0,O73=0),O73, O73-ROUND((MAX('Detalhe Por UC'!R:R) -Q73)/(365/12),0))) -> 0 | T73: 249.81818 | U73: =IFERROR((SUMIFS(W73:CN73,$W$2:$CN$2,">"&$Q$1-365,$W$2:$CN$2,"<="&$Q$1)/COUNTIFS(W73:CN73,">="&0,$W$2:$CN$2,">"&$Q$1-365,$W$2:$CN$2,"<="&$Q$1)),"") -> 317.58333 | X73: 121 | Y73: 124 | Z73: 322 | AA73: 352 | AB73: 0 | AC73: 93 | AD73: 171 | AE73: 167 | AF73: 198 | AG73: 239 | AH73: 271 | AI73: 359 | AJ73: =IF(SUMIFS('Detalhe Por UC'!$AB:$AB,'Detalhe Por UC'!$C:$C,'Infos Clientes'!$B73,'Detalhe Por UC'!$R:$R,'Infos Clientes'!AJ$2)=0,"", SUMIFS('Detalhe Por UC'!$AB:$AB,'Detalhe Por UC'!$C:$C,'Infos Clientes'!$B73,'Detalhe Por UC'!$R:$R,'Infos Clientes'!AJ$2) +SUMIFS('Detalhe Por UC'!$AC:$AC,'Detalhe Por UC'!$C:$C,'Infos Clientes'!$B73,'Detalhe Por UC'!$R:$R,'Infos Clientes'!AJ$2)) -> 452 | AK73: =IF(SUMIFS('Detalhe Por UC'!$AB:$AB,'Detalhe Por UC'!$C:$C,'Infos Clientes'!$B73,'Detalhe Por UC'!$R:$R,'Infos Clientes'!AK$2)=0,"", SUMIFS('Detalhe Por UC'!$AB:$AB,'Detalhe Por UC'!$C:$C,'Infos Clientes'!$B73,'Detalhe Por UC'!$R:$R,'Infos Clientes'!AK$2) +SUMIFS('Detalhe Por UC'!$AC:$AC,'Detalhe Por UC'!$C:$C,'Infos Clientes'!$B73,'Detalhe Por UC'!$R:$R,'Infos Clientes'!AK$2)) -> 406 | AL73: =IF(SUMIFS('Detalhe Por UC'!$AB:$AB,'Detalhe Por UC'!$C:$C,'Infos Clientes'!$B73,'Detalhe Por UC'!$R:$R,'Infos Clientes'!AL$2)=0,"", SUMIFS('Detalhe Por UC'!$AB:$AB,'Detalhe Por UC'!$C:$C,'Infos Clientes'!$B73,'Detalhe Por UC'!$R:$R,'Infos Clientes'!AL$2) +SUMIFS('Detalhe Por UC'!$AC:$AC,'Detalhe Por UC'!$C:$C,'Infos Clientes'!$B73,'Detalhe Por UC'!$R:$R,'Infos Clientes'!AL$2)) -> 499 | AM73: =IF(SUMIFS('Detalhe Por UC'!$AB:$AB,'Detalhe Por UC'!$C:$C,'Infos Clientes'!$B73,'Detalhe Por UC'!$R:$R,'Infos Clientes'!AM$2)=0,"", SUMIFS('Detalhe Por UC'!$AB:$AB,'Detalhe Por UC'!$C:$C,'Infos Clientes'!$B73,'Detalhe Por UC'!$R:$R,'Infos Clientes'!AM$2) +SUMIFS('Detalhe Por UC'!$AC:$AC,'Detalhe Por UC'!$C:$C,'Infos Clientes'!$B73,'Detalhe Por UC'!$R:$R,'Infos Clientes'!AM$2)) -> 306 | AN73: =IF(SUMIFS('Detalhe Por UC'!$AB:$AB,'Detalhe Por UC'!$C:$C,'Infos Clientes'!$B73,'Detalhe Por UC'!$R:$R,'Infos Clientes'!AN$2)=0,"", SUMIFS('Detalhe Por UC'!$AB:$AB,'Detalhe Por UC'!$C:$C,'Infos Clientes'!$B73,'Detalhe Por UC'!$R:$R,'Infos Clientes'!AN$2) +SUMIFS('Detalhe Por UC'!$AC:$AC,'Detalhe Por UC'!$C:$C,'Infos Clientes'!$B73,'Detalhe Por UC'!$R:$R,'Infos Clientes'!AN$2)) -> 245 | AO73: =IF(SUMIFS('Detalhe Por UC'!$AB:$AB,'Detalhe Por UC'!$C:$C,'Infos Clientes'!$B73,'Detalhe Por UC'!$R:$R,'Infos Clientes'!AO$2)=0,"", SUMIFS('Detalhe Por UC'!$AB:$AB,'Detalhe Por UC'!$C:$C,'Infos Clientes'!$B73,'Detalhe Por UC'!$R:$R,'Infos Clientes'!AO$2) +SUMIFS('Detalhe Por UC'!$AC:$AC,'Detalhe Por UC'!$C:$C,'Infos Clientes'!$B73,'Detalhe Por UC'!$R:$R,'Infos Clientes'!AO$2)) -> 232 | AP73: =IF(SUMIFS('Detalhe Por UC'!$AB:$AB,'Detalhe Por UC'!$C:$C,'Infos Clientes'!$B73,'Detalhe Por UC'!$R:$R,'Infos Clientes'!AP$2)=0,"", SUMIFS('Detalhe Por UC'!$AB:$AB,'Detalhe Por UC'!$C:$C,'Infos Clientes'!$B73,'Detalhe Por UC'!$R:$R,'Infos Clientes'!AP$2) +SUMIFS('Detalhe Por UC'!$AC:$AC,'Detalhe Por UC'!$C:$C,'Infos Clientes'!$B73,'Detalhe Por UC'!$R:$R,'Infos Clientes'!AP$2)) -> 220 | AQ73: =IF(SUMIFS('Detalhe Por UC'!$AB:$AB,'Detalhe Por UC'!$C:$C,'Infos Clientes'!$B73,'Detalhe Por UC'!$R:$R,'Infos Clientes'!AQ$2)=0,"", SUMIFS('Detalhe Por UC'!$AB:$AB,'Detalhe Por UC'!$C:$C,'Infos Clientes'!$B73,'Detalhe Por UC'!$R:$R,'Infos Clientes'!AQ$2) +SUMIFS('Detalhe Por UC'!$AC:$AC,'Detalhe Por UC'!$C:$C,'Infos Clientes'!$B73,'Detalhe Por UC'!$R:$R,'Infos Clientes'!AQ$2)) -> 207 | ... AU73: =IF(SUMIFS('Detalhe Por UC'!$AB:$AB,'Detalhe Por UC'!$C:$C,'Infos Clientes'!$B73,'Detalhe Por UC'!$R:$R,'Infos Clientes'!AU$2)=0,"", SUMIFS('Detalhe Por UC'!$AB:$AB,'Detalhe Por UC'!$C:$C,'Infos Clientes'!$B73,'Detalhe Por UC'!$R:$R,'Infos Clientes'!AU$2) +SUMIFS('Detalhe Por UC'!$AC:$AC,'Detalhe Por UC'!$C:$C,'Infos Clientes'!$B73,'Detalhe Por UC'!$R:$R,'Infos Clientes'!AU$2))
B74: 10/399338-3 | C74: =ROW(F74) -> 74 | D74: IGREJA DO EVANGELHO QUADRANGULAR | E74: 306 | F74: 62.955.505/2132-33 | G74: auxiliar.cedms@gmail.com | H74: =B74 -> 10/399338-3 | I74: BT | J74: trifasico | K74: GIROSSOL III | M74: 0.25 | Q74: =IF(_xlfn.MINIFS('Detalhe Por UC'!R:R,'Detalhe Por UC'!C:C,B74,'Detalhe Por UC'!AD:AD,">"&0)=0,"",_xlfn.MINIFS('Detalhe Por UC'!R:R,'Detalhe Por UC'!C:C,B74,'Detalhe Por UC'!AD:AD,">"&0)) -> 45658 | R74: =IF(P74<>"ATIVO",0, IF(OR(Q74="",Q74=0,O74=0),O74, O74-ROUND((MAX('Detalhe Por UC'!R:R) -Q74)/(365/12),0))) -> 0 | T74: 659.09091 | U74: =IFERROR((SUMIFS(W74:CN74,$W$2:$CN$2,">"&$Q$1-365,$W$2:$CN$2,"<="&$Q$1)/COUNTIFS(W74:CN74,">="&0,$W$2:$CN$2,">"&$Q$1-365,$W$2:$CN$2,"<="&$Q$1)),"") -> 505.58333 | X74: 533 | Y74: 726 | Z74: 984 | AA74: 828 | AB74: 0 | AC74: 560 | AD74: 336 | AE74: 465 | AF74: 501 | AG74: 735 | AH74: 648 | AI74: 895 | AJ74: =IF(SUMIFS('Detalhe Por UC'!$AB:$AB,'Detalhe Por UC'!$C:$C,'Infos Clientes'!$B74,'Detalhe Por UC'!$R:$R,'Infos Clientes'!AJ$2)=0,"", SUMIFS('Detalhe Por UC'!$AB:$AB,'Detalhe Por UC'!$C:$C,'Infos Clientes'!$B74,'Detalhe Por UC'!$R:$R,'Infos Clientes'!AJ$2) +SUMIFS('Detalhe Por UC'!$AC:$AC,'Detalhe Por UC'!$C:$C,'Infos Clientes'!$B74,'Detalhe Por UC'!$R:$R,'Infos Clientes'!AJ$2)) -> 572 | AK74: =IF(SUMIFS('Detalhe Por UC'!$AB:$AB,'Detalhe Por UC'!$C:$C,'Infos Clientes'!$B74,'Detalhe Por UC'!$R:$R,'Infos Clientes'!AK$2)=0,"", SUMIFS('Detalhe Por UC'!$AB:$AB,'Detalhe Por UC'!$C:$C,'Infos Clientes'!$B74,'Detalhe Por UC'!$R:$R,'Infos Clientes'!AK$2) +SUMIFS('Detalhe Por UC'!$AC:$AC,'Detalhe Por UC'!$C:$C,'Infos Clientes'!$B74,'Detalhe Por UC'!$R:$R,'Infos Clientes'!AK$2)) -> 639 | AL74: =IF(SUMIFS('Detalhe Por UC'!$AB:$AB,'Detalhe Por UC'!$C:$C,'Infos Clientes'!$B74,'Detalhe Por UC'!$R:$R,'Infos Clientes'!AL$2)=0,"", SUMIFS('Detalhe Por UC'!$AB:$AB,'Detalhe Por UC'!$C:$C,'Infos Clientes'!$B74,'Detalhe Por UC'!$R:$R,'Infos Clientes'!AL$2) +SUMIFS('Detalhe Por UC'!$AC:$AC,'Detalhe Por UC'!$C:$C,'Infos Clientes'!$B74,'Detalhe Por UC'!$R:$R,'Infos Clientes'!AL$2)) -> 757 | AM74: =IF(SUMIFS('Detalhe Por UC'!$AB:$AB,'Detalhe Por UC'!$C:$C,'Infos Clientes'!$B74,'Detalhe Por UC'!$R:$R,'Infos Clientes'!AM$2)=0,"", SUMIFS('Detalhe Por UC'!$AB:$AB,'Detalhe Por UC'!$C:$C,'Infos Clientes'!$B74,'Detalhe Por UC'!$R:$R,'Infos Clientes'!AM$2) +SUMIFS('Detalhe Por UC'!$AC:$AC,'Detalhe Por UC'!$C:$C,'Infos Clientes'!$B74,'Detalhe Por UC'!$R:$R,'Infos Clientes'!AM$2)) -> 605 | AN74: =IF(SUMIFS('Detalhe Por UC'!$AB:$AB,'Detalhe Por UC'!$C:$C,'Infos Clientes'!$B74,'Detalhe Por UC'!$R:$R,'Infos Clientes'!AN$2)=0,"", SUMIFS('Detalhe Por UC'!$AB:$AB,'Detalhe Por UC'!$C:$C,'Infos Clientes'!$B74,'Detalhe Por UC'!$R:$R,'Infos Clientes'!AN$2) +SUMIFS('Detalhe Por UC'!$AC:$AC,'Detalhe Por UC'!$C:$C,'Infos Clientes'!$B74,'Detalhe Por UC'!$R:$R,'Infos Clientes'!AN$2)) -> 422 | AO74: =IF(SUMIFS('Detalhe Por UC'!$AB:$AB,'Detalhe Por UC'!$C:$C,'Infos Clientes'!$B74,'Detalhe Por UC'!$R:$R,'Infos Clientes'!AO$2)=0,"", SUMIFS('Detalhe Por UC'!$AB:$AB,'Detalhe Por UC'!$C:$C,'Infos Clientes'!$B74,'Detalhe Por UC'!$R:$R,'Infos Clientes'!AO$2) +SUMIFS('Detalhe Por UC'!$AC:$AC,'Detalhe Por UC'!$C:$C,'Infos Clientes'!$B74,'Detalhe Por UC'!$R:$R,'Infos Clientes'!AO$2)) -> 313 | AP74: =IF(SUMIFS('Detalhe Por UC'!$AB:$AB,'Detalhe Por UC'!$C:$C,'Infos Clientes'!$B74,'Detalhe Por UC'!$R:$R,'Infos Clientes'!AP$2)=0,"", SUMIFS('Detalhe Por UC'!$AB:$AB,'Detalhe Por UC'!$C:$C,'Infos Clientes'!$B74,'Detalhe Por UC'!$R:$R,'Infos Clientes'!AP$2) +SUMIFS('Detalhe Por UC'!$AC:$AC,'Detalhe Por UC'!$C:$C,'Infos Clientes'!$B74,'Detalhe Por UC'!$R:$R,'Infos Clientes'!AP$2)) -> 241 | AQ74: =IF(SUMIFS('Detalhe Por UC'!$AB:$AB,'Detalhe Por UC'!$C:$C,'Infos Clientes'!$B74,'Detalhe Por UC'!$R:$R,'Infos Clientes'!AQ$2)=0,"", SUMIFS('Detalhe Por UC'!$AB:$AB,'Detalhe Por UC'!$C:$C,'Infos Clientes'!$B74,'Detalhe Por UC'!$R:$R,'Infos Clientes'!AQ$2) +SUMIFS('Detalhe Por UC'!$AC:$AC,'Detalhe Por UC'!$C:$C,'Infos Clientes'!$B74,'Detalhe Por UC'!$R:$R,'Infos Clientes'!AQ$2)) -> 238 | ... AU74: =IF(SUMIFS('Detalhe Por UC'!$AB:$AB,'Detalhe Por UC'!$C:$C,'Infos Clientes'!$B74,'Detalhe Por UC'!$R:$R,'Infos Clientes'!AU$2)=0,"", SUMIFS('Detalhe Por UC'!$AB:$AB,'Detalhe Por UC'!$C:$C,'Infos Clientes'!$B74,'Detalhe Por UC'!$R:$R,'Infos Clientes'!AU$2) +SUMIFS('Detalhe Por UC'!$AC:$AC,'Detalhe Por UC'!$C:$C,'Infos Clientes'!$B74,'Detalhe Por UC'!$R:$R,'Infos Clientes'!AU$2))
B75: 10/40190-1 | C75: =ROW(F75) -> 75 | D75: IGREJA DO EVANGELHO QUADRANGULAR | E75: 319 | F75: 62.955.505/1775-04 | G75: auxiliar.cedms@gmail.com | H75: =B75 -> 10/40190-1 | I75: BT | J75: bifasico | K75: GIROSSOL III | M75: 0.25 | Q75: =IF(_xlfn.MINIFS('Detalhe Por UC'!R:R,'Detalhe Por UC'!C:C,B75,'Detalhe Por UC'!AD:AD,">"&0)=0,"",_xlfn.MINIFS('Detalhe Por UC'!R:R,'Detalhe Por UC'!C:C,B75,'Detalhe Por UC'!AD:AD,">"&0)) -> 45658 | R75: =IF(P75<>"ATIVO",0, IF(OR(Q75="",Q75=0,O75=0),O75, O75-ROUND((MAX('Detalhe Por UC'!R:R) -Q75)/(365/12),0))) -> 0 | T75: 336.36364 | U75: =IFERROR((SUMIFS(W75:CN75,$W$2:$CN$2,">"&$Q$1-365,$W$2:$CN$2,"<="&$Q$1)/COUNTIFS(W75:CN75,">="&0,$W$2:$CN$2,">"&$Q$1-365,$W$2:$CN$2,"<="&$Q$1)),"") -> 321.88889 | X75: 399 | Y75: 356 | Z75: 382 | AA75: 343 | AB75: 0 | AC75: 292 | AD75: 330 | AE75: 321 | AF75: 327 | AG75: 342 | AH75: 327 | AI75: 334 | AJ75: =IF(SUMIFS('Detalhe Por UC'!$AB:$AB,'Detalhe Por UC'!$C:$C,'Infos Clientes'!$B75,'Detalhe Por UC'!$R:$R,'Infos Clientes'!AJ$2)=0,"", SUMIFS('Detalhe Por UC'!$AB:$AB,'Detalhe Por UC'!$C:$C,'Infos Clientes'!$B75,'Detalhe Por UC'!$R:$R,'Infos Clientes'!AJ$2) +SUMIFS('Detalhe Por UC'!$AC:$AC,'Detalhe Por UC'!$C:$C,'Infos Clientes'!$B75,'Detalhe Por UC'!$R:$R,'Infos Clientes'!AJ$2)) -> 346 | AK75: =IF(SUMIFS('Detalhe Por UC'!$AB:$AB,'Detalhe Por UC'!$C:$C,'Infos Clientes'!$B75,'Detalhe Por UC'!$R:$R,'Infos Clientes'!AK$2)=0,"", SUMIFS('Detalhe Por UC'!$AB:$AB,'Detalhe Por UC'!$C:$C,'Infos Clientes'!$B75,'Detalhe Por UC'!$R:$R,'Infos Clientes'!AK$2) +SUMIFS('Detalhe Por UC'!$AC:$AC,'Detalhe Por UC'!$C:$C,'Infos Clientes'!$B75,'Detalhe Por UC'!$R:$R,'Infos Clientes'!AK$2)) -> 339 | AL75: =IF(SUMIFS('Detalhe Por UC'!$AB:$AB,'Detalhe Por UC'!$C:$C,'Infos Clientes'!$B75,'Detalhe Por UC'!$R:$R,'Infos Clientes'!AL$2)=0,"", SUMIFS('Detalhe Por UC'!$AB:$AB,'Detalhe Por UC'!$C:$C,'Infos Clientes'!$B75,'Detalhe Por UC'!$R:$R,'Infos Clientes'!AL$2) +SUMIFS('Detalhe Por UC'!$AC:$AC,'Detalhe Por UC'!$C:$C,'Infos Clientes'!$B75,'Detalhe Por UC'!$R:$R,'Infos Clientes'!AL$2)) -> 307 | AM75: =IF(SUMIFS('Detalhe Por UC'!$AB:$AB,'Detalhe Por UC'!$C:$C,'Infos Clientes'!$B75,'Detalhe Por UC'!$R:$R,'Infos Clientes'!AM$2)=0,"", SUMIFS('Detalhe Por UC'!$AB:$AB,'Detalhe Por UC'!$C:$C,'Infos Clientes'!$B75,'Detalhe Por UC'!$R:$R,'Infos Clientes'!AM$2) +SUMIFS('Detalhe Por UC'!$AC:$AC,'Detalhe Por UC'!$C:$C,'Infos Clientes'!$B75,'Detalhe Por UC'!$R:$R,'Infos Clientes'!AM$2)) -> 317 | AN75: =IF(SUMIFS('Detalhe Por UC'!$AB:$AB,'Detalhe Por UC'!$C:$C,'Infos Clientes'!$B75,'Detalhe Por UC'!$R:$R,'Infos Clientes'!AN$2)=0,"", SUMIFS('Detalhe Por UC'!$AB:$AB,'Detalhe Por UC'!$C:$C,'Infos Clientes'!$B75,'Detalhe Por UC'!$R:$R,'Infos Clientes'!AN$2) +SUMIFS('Detalhe Por UC'!$AC:$AC,'Detalhe Por UC'!$C:$C,'Infos Clientes'!$B75,'Detalhe Por UC'!$R:$R,'Infos Clientes'!AN$2)) -> 345 | AO75: =IF(SUMIFS('Detalhe Por UC'!$AB:$AB,'Detalhe Por UC'!$C:$C,'Infos Clientes'!$B75,'Detalhe Por UC'!$R:$R,'Infos Clientes'!AO$2)=0,"", SUMIFS('Detalhe Por UC'!$AB:$AB,'Detalhe Por UC'!$C:$C,'Infos Clientes'!$B75,'Detalhe Por UC'!$R:$R,'Infos Clientes'!AO$2) +SUMIFS('Detalhe Por UC'!$AC:$AC,'Detalhe Por UC'!$C:$C,'Infos Clientes'!$B75,'Detalhe Por UC'!$R:$R,'Infos Clientes'!AO$2)) -> 284 | AP75: =IF(SUMIFS('Detalhe Por UC'!$AB:$AB,'Detalhe Por UC'!$C:$C,'Infos Clientes'!$B75,'Detalhe Por UC'!$R:$R,'Infos Clientes'!AP$2)=0,"", SUMIFS('Detalhe Por UC'!$AB:$AB,'Detalhe Por UC'!$C:$C,'Infos Clientes'!$B75,'Detalhe Por UC'!$R:$R,'Infos Clientes'!AP$2) +SUMIFS('Detalhe Por UC'!$AC:$AC,'Detalhe Por UC'!$C:$C,'Infos Clientes'!$B75,'Detalhe Por UC'!$R:$R,'Infos Clientes'!AP$2)) -> 259 | AQ75: =IF(SUMIFS('Detalhe Por UC'!$AB:$AB,'Detalhe Por UC'!$C:$C,'Infos Clientes'!$B75,'Detalhe Por UC'!$R:$R,'Infos Clientes'!AQ$2)=0,"", SUMIFS('Detalhe Por UC'!$AB:$AB,'Detalhe Por UC'!$C:$C,'Infos Clientes'!$B75,'Detalhe Por UC'!$R:$R,'Infos Clientes'!AQ$2) +SUMIFS('Detalhe Por UC'!$AC:$AC,'Detalhe Por UC'!$C:$C,'Infos Clientes'!$B75,'Detalhe Por UC'!$R:$R,'Infos Clientes'!AQ$2)) | ... AU75: =IF(SUMIFS('Detalhe Por UC'!$AB:$AB,'Detalhe Por UC'!$C:$C,'Infos Clientes'!$B75,'Detalhe Por UC'!$R:$R,'Infos Clientes'!AU$2)=0,"", SUMIFS('Detalhe Por UC'!$AB:$AB,'Detalhe Por UC'!$C:$C,'Infos Clientes'!$B75,'Detalhe Por UC'!$R:$R,'Infos Clientes'!AU$2) +SUMIFS('Detalhe Por UC'!$AC:$AC,'Detalhe Por UC'!$C:$C,'Infos Clientes'!$B75,'Detalhe Por UC'!$R:$R,'Infos Clientes'!AU$2))
